{"1": {"p": 128,"j": 7,"h": 51,"m": 2,"r": 102,"i": "اَلْحَمْدُ|لِلّٰهِ|الَّذِیْ|خَلَقَ|السَّمٰوٰتِ|وَالْاَرْضَ|وَجَعَلَ|الظُّلُمٰتِ|وَالنُّوْرَ ؕ۬—|ثُمَّ|الَّذِیْنَ|كَفَرُوْا|بِرَبِّهِمْ|یَعْدِلُوْنَ","u": "ٱلۡحَمۡدُ|لِلَّهِ|ٱلَّذِي|خَلَقَ|ٱلسَّمَٰوَٰتِ|وَٱلۡأَرۡضَ|وَجَعَلَ|ٱلظُّلُمَٰتِ|وَٱلنُّورَۖ|ثُمَّ|ٱلَّذِينَ|كَفَرُواْ|بِرَبِّهِمۡ|يَعۡدِلُونَ","t": "al-hamdu|lillahi|alladhi|khalaqa|al-samawati|wal-arda|waja'ala|al-zulumati|wal-nura|thumma|alladhina|kafaru|birabbihim|ya'diluna","e": "۟/١/."},"2": {"p": 128,"j": 7,"h": 51,"m": 2,"r": 102,"i": "هُوَ|الَّذِیْ|خَلَقَكُمْ|مِّنْ|طِیْنٍ|ثُمَّ|قَضٰۤی|اَجَلًا ؕ—|وَاَجَلٌ|مُّسَمًّی|عِنْدَهٗ|ثُمَّ|اَنْتُمْ|تَمْتَرُوْنَ","u": "هُوَ|ٱلَّذِي|خَلَقَكُم|مِّن|طِينٖ|ثُمَّ|قَضَىٰٓ|أَجَلٗاۖ|وَأَجَلٞ|مُّسَمًّى|عِندَهُۥۖ|ثُمَّ|أَنتُمۡ|تَمۡتَرُونَ","t": "huwa|alladhi|khalaqakum|min|tinin|thumma|qada|ajalan|wa-ajalun|musamman|indahu|thumma|antum|tamtaruna","e": "۟/٢/."},"3": {"p": 128,"j": 7,"h": 51,"m": 2,"r": 102,"i": "وَهُوَ|اللّٰهُ|فِی|السَّمٰوٰتِ|وَفِی|الْاَرْضِ ؕ—|یَعْلَمُ|سِرَّكُمْ|وَجَهْرَكُمْ|وَیَعْلَمُ|مَا|تَكْسِبُوْنَ","u": "وَهُوَ|ٱللَّهُ|فِي|ٱلسَّمَٰوَٰتِ|وَفِي|ٱلۡأَرۡضِ|يَعۡلَمُ|سِرَّكُمۡ|وَجَهۡرَكُمۡ|وَيَعۡلَمُ|مَا|تَكۡسِبُونَ","t": "wahuwa|al-lahu|fi|al-samawati|wafi|al-ardi|ya'lamu|sirrakum|wajahrakum|waya'lamu|ma|taksibuna","e": "۟/٣/."},"4": {"p": 128,"j": 7,"h": 51,"m": 2,"r": 102,"i": "وَمَا|تَاْتِیْهِمْ|مِّنْ|اٰیَةٍ|مِّنْ|اٰیٰتِ|رَبِّهِمْ|اِلَّا|كَانُوْا|عَنْهَا|مُعْرِضِیْنَ","u": "وَمَا|تَأۡتِيهِم|مِّنۡ|ءَايَةٖ|مِّنۡ|ءَايَٰتِ|رَبِّهِمۡ|إِلَّا|كَانُواْ|عَنۡهَا|مُعۡرِضِينَ","t": "wama|tatihim|min|ayatin|min|ayati|rabbihim|illa|kanu|anha|mu'ridina","e": "۟/٤/."},"5": {"p": 128,"j": 7,"h": 51,"m": 2,"r": 102,"i": "فَقَدْ|كَذَّبُوْا|بِالْحَقِّ|لَمَّا|جَآءَهُمْ ؕ—|فَسَوْفَ|یَاْتِیْهِمْ|اَنْۢبٰٓؤُا|مَا|كَانُوْا|بِهٖ|یَسْتَهْزِءُوْنَ","u": "فَقَدۡ|كَذَّبُواْ|بِٱلۡحَقِّ|لَمَّا|جَآءَهُمۡ|فَسَوۡفَ|يَأۡتِيهِمۡ|أَنۢبَٰٓؤُاْ|مَا|كَانُواْ|بِهِۦ|يَسۡتَهۡزِءُونَ","t": "faqad|kadhabu|bil-haqi|lamma|jaahum|fasawfa|yatihim|anbau|ma|kanu|bihi|yastahziuna","e": "۟/٥/."},"6": {"p": 128,"j": 7,"h": 51,"m": 2,"r": 102,"i": "اَلَمْ|یَرَوْا|كَمْ|اَهْلَكْنَا|مِنْ|قَبْلِهِمْ|مِّنْ|قَرْنٍ|مَّكَّنّٰهُمْ|فِی|الْاَرْضِ|مَا|لَمْ|نُمَكِّنْ|لَّكُمْ|وَاَرْسَلْنَا|السَّمَآءَ|عَلَیْهِمْ|مِّدْرَارًا ۪—|وَّجَعَلْنَا|الْاَنْهٰرَ|تَجْرِیْ|مِنْ|تَحْتِهِمْ|فَاَهْلَكْنٰهُمْ|بِذُنُوْبِهِمْ|وَاَنْشَاْنَا|مِنْ|بَعْدِهِمْ|قَرْنًا|اٰخَرِیْنَ","u": "أَلَمۡ|يَرَوۡاْ|كَمۡ|أَهۡلَكۡنَا|مِن|قَبۡلِهِم|مِّن|قَرۡنٖ|مَّكَّنَّٰهُمۡ|فِي|ٱلۡأَرۡضِ|مَا|لَمۡ|نُمَكِّن|لَّكُمۡ|وَأَرۡسَلۡنَا|ٱلسَّمَآءَ|عَلَيۡهِم|مِّدۡرَارٗا|وَجَعَلۡنَا|ٱلۡأَنۡهَٰرَ|تَجۡرِي|مِن|تَحۡتِهِمۡ|فَأَهۡلَكۡنَٰهُم|بِذُنُوبِهِمۡ|وَأَنشَأۡنَا|مِنۢ|بَعۡدِهِمۡ|قَرۡنًا|ءَاخَرِينَ","t": "alam|yaraw|kam|ahlakna|min|qablihim|min|qarnin|makkannahum|fi|al-ardi|ma|lam|numakkin|lakum|wa-arsalna|al-samaa|alayhim|mid'raran|waja'alna|al-anhara|tajri|min|tahtihim|fa-ahlaknahum|bidhunubihim|wa-anshana|min|ba'dihim|qarnan|akharina","e": "۟/٦/."},"7": {"p": 128,"j": 7,"h": 51,"m": 2,"r": 102,"i": "وَلَوْ|نَزَّلْنَا|عَلَیْكَ|كِتٰبًا|فِیْ|قِرْطَاسٍ|فَلَمَسُوْهُ|بِاَیْدِیْهِمْ|لَقَالَ|الَّذِیْنَ|كَفَرُوْۤا|اِنْ|هٰذَاۤ|اِلَّا|سِحْرٌ|مُّبِیْنٌ","u": "وَلَوۡ|نَزَّلۡنَا|عَلَيۡكَ|كِتَٰبٗا|فِي|قِرۡطَاسٖ|فَلَمَسُوهُ|بِأَيۡدِيهِمۡ|لَقَالَ|ٱلَّذِينَ|كَفَرُوٓاْ|إِنۡ|هَٰذَآ|إِلَّا|سِحۡرٞ|مُّبِينٞ","t": "walaw|nazzalna|alayka|kitaban|fi|qir'tasin|falamasuhu|bi-aydihim|laqala|alladhina|kafaru|in|hadha|illa|sih'run|mubinun","e": "۟/٧/."},"8": {"p": 128,"j": 7,"h": 51,"m": 2,"r": 102,"i": "وَقَالُوْا|لَوْلَاۤ|اُنْزِلَ|عَلَیْهِ|مَلَكٌ ؕ—|وَلَوْ|اَنْزَلْنَا|مَلَكًا|لَّقُضِیَ|الْاَمْرُ|ثُمَّ|لَا|یُنْظَرُوْنَ","u": "وَقَالُواْ|لَوۡلَآ|أُنزِلَ|عَلَيۡهِ|مَلَكٞۖ|وَلَوۡ|أَنزَلۡنَا|مَلَكٗا|لَّقُضِيَ|ٱلۡأَمۡرُ|ثُمَّ|لَا|يُنظَرُونَ","t": "waqalu|lawla|unzila|alayhi|malakun|walaw|anzalna|malakan|laqudiya|al-amru|thumma|la|yunzaruna","e": "۟/٨/."},"9": {"p": 129,"j": 7,"h": 51,"m": 2,"r": 102,"i": "وَلَوْ|جَعَلْنٰهُ|مَلَكًا|لَّجَعَلْنٰهُ|رَجُلًا|وَّلَلَبَسْنَا|عَلَیْهِمْ|مَّا|یَلْبِسُوْنَ","u": "وَلَوۡ|جَعَلۡنَٰهُ|مَلَكٗا|لَّجَعَلۡنَٰهُ|رَجُلٗا|وَلَلَبَسۡنَا|عَلَيۡهِم|مَّا|يَلۡبِسُونَ","t": "walaw|ja'alnahu|malakan|laja'alnahu|rajulan|walalabasna|alayhim|ma|yalbisuna","e": "۟/٩/."},"10": {"p": 129,"j": 7,"h": 51,"m": 2,"r": 102,"i": "وَلَقَدِ|اسْتُهْزِئَ|بِرُسُلٍ|مِّنْ|قَبْلِكَ|فَحَاقَ|بِالَّذِیْنَ|سَخِرُوْا|مِنْهُمْ|مَّا|كَانُوْا|بِهٖ|یَسْتَهْزِءُوْنَ","u": "وَلَقَدِ|ٱسۡتُهۡزِئَ|بِرُسُلٖ|مِّن|قَبۡلِكَ|فَحَاقَ|بِٱلَّذِينَ|سَخِرُواْ|مِنۡهُم|مَّا|كَانُواْ|بِهِۦ|يَسۡتَهۡزِءُونَ","t": "walaqadi|us'tuh'zi-a|birusulin|min|qablika|fahaqa|bi-alladhina|sakhiru|min'hum|ma|kanu|bihi|yastahziuna","e": "۟۠/١٠/."},"11": {"p": 129,"j": 7,"h": 51,"m": 2,"r": 103,"i": "قُلْ|سِیْرُوْا|فِی|الْاَرْضِ|ثُمَّ|اَنْظُرُوْا|كَیْفَ|كَانَ|عَاقِبَةُ|الْمُكَذِّبِیْنَ","u": "قُلۡ|سِيرُواْ|فِي|ٱلۡأَرۡضِ|ثُمَّ|ٱنظُرُواْ|كَيۡفَ|كَانَ|عَٰقِبَةُ|ٱلۡمُكَذِّبِينَ","t": "qul|siru|fi|al-ardi|thumma|unzuru|kayfa|kana|aqibatu|al-mukadhibina","e": "۟/١١/."},"12": {"p": 129,"j": 7,"h": 51,"m": 2,"r": 103,"i": "قُلْ|لِّمَنْ|مَّا|فِی|السَّمٰوٰتِ|وَالْاَرْضِ ؕ—|قُلْ|لِّلّٰهِ ؕ—|كَتَبَ|عَلٰی|نَفْسِهِ|الرَّحْمَةَ ؕ—|لَیَجْمَعَنَّكُمْ|اِلٰی|یَوْمِ|الْقِیٰمَةِ|لَا|رَیْبَ|فِیْهِ ؕ—|اَلَّذِیْنَ|خَسِرُوْۤا|اَنْفُسَهُمْ|فَهُمْ|لَا|یُؤْمِنُوْنَ","u": "قُل|لِّمَن|مَّا|فِي|ٱلسَّمَٰوَٰتِ|وَٱلۡأَرۡضِۖ|قُل|لِّلَّهِۚ|كَتَبَ|عَلَىٰ|نَفۡسِهِ|ٱلرَّحۡمَةَۚ|لَيَجۡمَعَنَّكُمۡ|إِلَىٰ|يَوۡمِ|ٱلۡقِيَٰمَةِ|لَا|رَيۡبَ|فِيهِۚ|ٱلَّذِينَ|خَسِرُوٓاْ|أَنفُسَهُمۡ|فَهُمۡ|لَا|يُؤۡمِنُونَ","t": "qul|liman|ma|fi|al-samawati|wal-ardi|qul|lillahi|kataba|ala|nafsihi|al-rahmata|layajma'annakum|ila|yawmi|al-qiyamati|la|rayba|fihi|alladhina|khasiru|anfusahum|fahum|la|yu'minuna","e": "۟/١٢/."},"13": {"p": 129,"j": 7,"h": 52,"m": 2,"r": 103,"i": "وَلَهٗ|مَا|سَكَنَ|فِی|الَّیْلِ|وَالنَّهَارِ ؕ—|وَهُوَ|السَّمِیْعُ|الْعَلِیْمُ","u": "۞وَلَهُۥ|مَا|سَكَنَ|فِي|ٱلَّيۡلِ|وَٱلنَّهَارِۚ|وَهُوَ|ٱلسَّمِيعُ|ٱلۡعَلِيمُ","t": "walahu|ma|sakana|fi|al-layli|wal-nahari|wahuwa|al-sami'u|al-'alimu","e": "۟/١٣/."},"14": {"p": 129,"j": 7,"h": 52,"m": 2,"r": 103,"i": "قُلْ|اَغَیْرَ|اللّٰهِ|اَتَّخِذُ|وَلِیًّا|فَاطِرِ|السَّمٰوٰتِ|وَالْاَرْضِ|وَهُوَ|یُطْعِمُ|وَلَا|یُطْعَمُ ؕ—|قُلْ|اِنِّیْۤ|اُمِرْتُ|اَنْ|اَكُوْنَ|اَوَّلَ|مَنْ|اَسْلَمَ|وَلَا|تَكُوْنَنَّ|مِنَ|الْمُشْرِكِیْنَ","u": "قُلۡ|أَغَيۡرَ|ٱللَّهِ|أَتَّخِذُ|وَلِيّٗا|فَاطِرِ|ٱلسَّمَٰوَٰتِ|وَٱلۡأَرۡضِ|وَهُوَ|يُطۡعِمُ|وَلَا|يُطۡعَمُۗ|قُلۡ|إِنِّيٓ|أُمِرۡتُ|أَنۡ|أَكُونَ|أَوَّلَ|مَنۡ|أَسۡلَمَۖ|وَلَا|تَكُونَنَّ|مِنَ|ٱلۡمُشۡرِكِينَ","t": "qul|aghayra|al-lahi|attakhidhu|waliyyan|fatiri|al-samawati|wal-ardi|wahuwa|yut'imu|wala|yut'amu|qul|inni|umir'tu|an|akuna|awwala|man|aslama|wala|takunanna|mina|al-mush'rikina","e": "۟/١٤/."},"15": {"p": 129,"j": 7,"h": 52,"m": 2,"r": 103,"i": "قُلْ|اِنِّیْۤ|اَخَافُ|اِنْ|عَصَیْتُ|رَبِّیْ|عَذَابَ|یَوْمٍ|عَظِیْمٍ","u": "قُلۡ|إِنِّيٓ|أَخَافُ|إِنۡ|عَصَيۡتُ|رَبِّي|عَذَابَ|يَوۡمٍ|عَظِيمٖ","t": "qul|inni|akhafu|in|asaytu|rabbi|adhaba|yawmin|azimin","e": "۟/١٥/."},"16": {"p": 129,"j": 7,"h": 52,"m": 2,"r": 103,"i": "مَنْ|یُّصْرَفْ|عَنْهُ|یَوْمَىِٕذٍ|فَقَدْ|رَحِمَهٗ ؕ—|وَذٰلِكَ|الْفَوْزُ|الْمُبِیْنُ","u": "مَّن|يُصۡرَفۡ|عَنۡهُ|يَوۡمَئِذٖ|فَقَدۡ|رَحِمَهُۥۚ|وَذَٰلِكَ|ٱلۡفَوۡزُ|ٱلۡمُبِينُ","t": "man|yus'raf|anhu|yawma-idhin|faqad|rahimahu|wadhalika|al-fawzu|al-mubinu","e": "۟/١٦/."},"17": {"p": 129,"j": 7,"h": 52,"m": 2,"r": 103,"i": "وَاِنْ|یَّمْسَسْكَ|اللّٰهُ|بِضُرٍّ|فَلَا|كَاشِفَ|لَهٗۤ|اِلَّا|هُوَ ؕ—|وَاِنْ|یَّمْسَسْكَ|بِخَیْرٍ|فَهُوَ|عَلٰی|كُلِّ|شَیْءٍ|قَدِیْرٌ","u": "وَإِن|يَمۡسَسۡكَ|ٱللَّهُ|بِضُرّٖ|فَلَا|كَاشِفَ|لَهُۥٓ|إِلَّا|هُوَۖ|وَإِن|يَمۡسَسۡكَ|بِخَيۡرٖ|فَهُوَ|عَلَىٰ|كُلِّ|شَيۡءٖ|قَدِيرٞ","t": "wa-in|yamsaska|al-lahu|bidurrin|fala|kashifa|lahu|illa|huwa|wa-in|yamsaska|bikhayrin|fahuwa|ala|kulli|shayin|qadirun","e": "۟/١٧/."},"18": {"p": 129,"j": 7,"h": 52,"m": 2,"r": 103,"i": "وَهُوَ|الْقَاهِرُ|فَوْقَ|عِبَادِهٖ ؕ—|وَهُوَ|الْحَكِیْمُ|الْخَبِیْرُ","u": "وَهُوَ|ٱلۡقَاهِرُ|فَوۡقَ|عِبَادِهِۦۚ|وَهُوَ|ٱلۡحَكِيمُ|ٱلۡخَبِيرُ","t": "wahuwa|al-qahiru|fawqa|ibadihi|wahuwa|al-hakimu|al-khabiru","e": "۟/١٨/."},"19": {"p": 130,"j": 7,"h": 52,"m": 2,"r": 103,"i": "قُلْ|اَیُّ|شَیْءٍ|اَكْبَرُ|شَهَادَةً ؕ—|قُلِ|اللّٰهُ ۫—|شَهِیْدٌۢ|بَیْنِیْ|وَبَیْنَكُمْ ۫—|وَاُوْحِیَ|اِلَیَّ|هٰذَا|الْقُرْاٰنُ|لِاُنْذِرَكُمْ|بِهٖ|وَمَنْ|بَلَغَ ؕ—|اَىِٕنَّكُمْ|لَتَشْهَدُوْنَ|اَنَّ|مَعَ|اللّٰهِ|اٰلِهَةً|اُخْرٰی ؕ—|قُلْ|لَّاۤ|اَشْهَدُ ۚ—|قُلْ|اِنَّمَا|هُوَ|اِلٰهٌ|وَّاحِدٌ|وَّاِنَّنِیْ|بَرِیْٓءٌ|مِّمَّا|تُشْرِكُوْنَ","u": "قُلۡ|أَيُّ|شَيۡءٍ|أَكۡبَرُ|شَهَٰدَةٗۖ|قُلِ|ٱللَّهُۖ|شَهِيدُۢ|بَيۡنِي|وَبَيۡنَكُمۡۚ|وَأُوحِيَ|إِلَيَّ|هَٰذَا|ٱلۡقُرۡءَانُ|لِأُنذِرَكُم|بِهِۦ|وَمَنۢ|بَلَغَۚ|أَئِنَّكُمۡ|لَتَشۡهَدُونَ|أَنَّ|مَعَ|ٱللَّهِ|ءَالِهَةً|أُخۡرَىٰۚ|قُل|لَّآ|أَشۡهَدُۚ|قُلۡ|إِنَّمَا|هُوَ|إِلَٰهٞ|وَٰحِدٞ|وَإِنَّنِي|بَرِيٓءٞ|مِّمَّا|تُشۡرِكُونَ","t": "qul|ayyu|shayin|akbaru|shahadatan|quli|al-lahu|shahidun|bayni|wabaynakum|wauhiya|ilayya|hadha|al-qur'anu|li-undhirakum|bihi|waman|balagha|a-innakum|latashhaduna|anna|ma'a|al-lahi|alihatan|ukh'ra|qul|la|ashhadu|qul|innama|huwa|ilahun|wahidun|wa-innani|barion|mimma|tush'rikuna","e": "۟ۘ/١٩/."},"20": {"p": 130,"j": 7,"h": 52,"m": 2,"r": 103,"i": "اَلَّذِیْنَ|اٰتَیْنٰهُمُ|الْكِتٰبَ|یَعْرِفُوْنَهٗ|كَمَا|یَعْرِفُوْنَ|اَبْنَآءَهُمْ ۘ—|اَلَّذِیْنَ|خَسِرُوْۤا|اَنْفُسَهُمْ|فَهُمْ|لَا|یُؤْمِنُوْنَ","u": "ٱلَّذِينَ|ءَاتَيۡنَٰهُمُ|ٱلۡكِتَٰبَ|يَعۡرِفُونَهُۥ|كَمَا|يَعۡرِفُونَ|أَبۡنَآءَهُمُۘ|ٱلَّذِينَ|خَسِرُوٓاْ|أَنفُسَهُمۡ|فَهُمۡ|لَا|يُؤۡمِنُونَ","t": "alladhina|ataynahumu|al-kitaba|ya'rifunahu|kama|ya'rifuna|abnaahumu|alladhina|khasiru|anfusahum|fahum|la|yu'minuna","e": "۟۠/٢٠/."},"21": {"p": 130,"j": 7,"h": 52,"m": 2,"r": 104,"i": "وَمَنْ|اَظْلَمُ|مِمَّنِ|افْتَرٰی|عَلَی|اللّٰهِ|كَذِبًا|اَوْ|كَذَّبَ|بِاٰیٰتِهٖ ؕ—|اِنَّهٗ|لَا|یُفْلِحُ|الظّٰلِمُوْنَ","u": "وَمَنۡ|أَظۡلَمُ|مِمَّنِ|ٱفۡتَرَىٰ|عَلَى|ٱللَّهِ|كَذِبًا|أَوۡ|كَذَّبَ|بِـَٔايَٰتِهِۦٓۚ|إِنَّهُۥ|لَا|يُفۡلِحُ|ٱلظَّٰلِمُونَ","t": "waman|azlamu|mimmani|if'tara|ala|al-lahi|kadhiban|aw|kadhaba|biayatihi|innahu|la|yuf'lihu|al-zalimuna","e": "۟/٢١/."},"22": {"p": 130,"j": 7,"h": 52,"m": 2,"r": 104,"i": "وَیَوْمَ|نَحْشُرُهُمْ|جَمِیْعًا|ثُمَّ|نَقُوْلُ|لِلَّذِیْنَ|اَشْرَكُوْۤا|اَیْنَ|شُرَكَآؤُكُمُ|الَّذِیْنَ|كُنْتُمْ|تَزْعُمُوْنَ","u": "وَيَوۡمَ|نَحۡشُرُهُمۡ|جَمِيعٗا|ثُمَّ|نَقُولُ|لِلَّذِينَ|أَشۡرَكُوٓاْ|أَيۡنَ|شُرَكَآؤُكُمُ|ٱلَّذِينَ|كُنتُمۡ|تَزۡعُمُونَ","t": "wayawma|nahshuruhum|jami'an|thumma|naqulu|lilladhina|ashraku|ayna|shurakaukumu|alladhina|kuntum|taz'umuna","e": "۟/٢٢/."},"23": {"p": 130,"j": 7,"h": 52,"m": 2,"r": 104,"i": "ثُمَّ|لَمْ|تَكُنْ|فِتْنَتُهُمْ|اِلَّاۤ|اَنْ|قَالُوْا|وَاللّٰهِ|رَبِّنَا|مَا|كُنَّا|مُشْرِكِیْنَ","u": "ثُمَّ|لَمۡ|تَكُن|فِتۡنَتُهُمۡ|إِلَّآ|أَن|قَالُواْ|وَٱللَّهِ|رَبِّنَا|مَا|كُنَّا|مُشۡرِكِينَ","t": "thumma|lam|takun|fit'natuhum|illa|an|qalu|wal-lahi|rabbina|ma|kunna|mush'rikina","e": "۟/٢٣/."},"24": {"p": 130,"j": 7,"h": 52,"m": 2,"r": 104,"i": "اُنْظُرْ|كَیْفَ|كَذَبُوْا|عَلٰۤی|اَنْفُسِهِمْ|وَضَلَّ|عَنْهُمْ|مَّا|كَانُوْا|یَفْتَرُوْنَ","u": "ٱنظُرۡ|كَيۡفَ|كَذَبُواْ|عَلَىٰٓ|أَنفُسِهِمۡۚ|وَضَلَّ|عَنۡهُم|مَّا|كَانُواْ|يَفۡتَرُونَ","t": "unzur|kayfa|kadhabu|ala|anfusihim|wadalla|anhum|ma|kanu|yaftaruna","e": "۟/٢٤/."},"25": {"p": 130,"j": 7,"h": 52,"m": 2,"r": 104,"i": "وَمِنْهُمْ|مَّنْ|یَّسْتَمِعُ|اِلَیْكَ ۚ—|وَجَعَلْنَا|عَلٰی|قُلُوْبِهِمْ|اَكِنَّةً|اَنْ|یَّفْقَهُوْهُ|وَفِیْۤ|اٰذَانِهِمْ|وَقْرًا ؕ—|وَاِنْ|یَّرَوْا|كُلَّ|اٰیَةٍ|لَّا|یُؤْمِنُوْا|بِهَا ؕ—|حَتّٰۤی|اِذَا|جَآءُوْكَ|یُجَادِلُوْنَكَ|یَقُوْلُ|الَّذِیْنَ|كَفَرُوْۤا|اِنْ|هٰذَاۤ|اِلَّاۤ|اَسَاطِیْرُ|الْاَوَّلِیْنَ","u": "وَمِنۡهُم|مَّن|يَسۡتَمِعُ|إِلَيۡكَۖ|وَجَعَلۡنَا|عَلَىٰ|قُلُوبِهِمۡ|أَكِنَّةً|أَن|يَفۡقَهُوهُ|وَفِيٓ|ءَاذَانِهِمۡ|وَقۡرٗاۚ|وَإِن|يَرَوۡاْ|كُلَّ|ءَايَةٖ|لَّا|يُؤۡمِنُواْ|بِهَاۖ|حَتَّىٰٓ|إِذَا|جَآءُوكَ|يُجَٰدِلُونَكَ|يَقُولُ|ٱلَّذِينَ|كَفَرُوٓاْ|إِنۡ|هَٰذَآ|إِلَّآ|أَسَٰطِيرُ|ٱلۡأَوَّلِينَ","t": "wamin'hum|man|yastami'u|ilayka|waja'alna|ala|qulubihim|akinnatan|an|yafqahuhu|wafi|adhanihim|waqran|wa-in|yaraw|kulla|ayatin|la|yu'minu|biha|hatta|idha|jauka|yujadilunaka|yaqulu|alladhina|kafaru|in|hadha|illa|asatiru|al-awalina","e": "۟/٢٥/."},"26": {"p": 130,"j": 7,"h": 52,"m": 2,"r": 104,"i": "وَهُمْ|یَنْهَوْنَ|عَنْهُ|وَیَنْـَٔوْنَ|عَنْهُ ۚ—|وَاِنْ|یُّهْلِكُوْنَ|اِلَّاۤ|اَنْفُسَهُمْ|وَمَا|یَشْعُرُوْنَ","u": "وَهُمۡ|يَنۡهَوۡنَ|عَنۡهُ|وَيَنۡـَٔوۡنَ|عَنۡهُۖ|وَإِن|يُهۡلِكُونَ|إِلَّآ|أَنفُسَهُمۡ|وَمَا|يَشۡعُرُونَ","t": "wahum|yanhawna|anhu|wayanawna|anhu|wa-in|yuh'likuna|illa|anfusahum|wama|yash'uruna","e": "۟/٢٦/."},"27": {"p": 130,"j": 7,"h": 52,"m": 2,"r": 104,"i": "وَلَوْ|تَرٰۤی|اِذْ|وُقِفُوْا|عَلَی|النَّارِ|فَقَالُوْا|یٰلَیْتَنَا|نُرَدُّ|وَلَا|نُكَذِّبَ|بِاٰیٰتِ|رَبِّنَا|وَنَكُوْنَ|مِنَ|الْمُؤْمِنِیْنَ","u": "وَلَوۡ|تَرَىٰٓ|إِذۡ|وُقِفُواْ|عَلَى|ٱلنَّارِ|فَقَالُواْ|يَٰلَيۡتَنَا|نُرَدُّ|وَلَا|نُكَذِّبَ|بِـَٔايَٰتِ|رَبِّنَا|وَنَكُونَ|مِنَ|ٱلۡمُؤۡمِنِينَ","t": "walaw|tara|idh|wuqifu|ala|al-nari|faqalu|yalaytana|nuraddu|wala|nukadhiba|biayati|rabbina|wanakuna|mina|al-mu'minina","e": "۟/٢٧/."},"28": {"p": 131,"j": 7,"h": 52,"m": 2,"r": 104,"i": "بَلْ|بَدَا|لَهُمْ|مَّا|كَانُوْا|یُخْفُوْنَ|مِنْ|قَبْلُ ؕ—|وَلَوْ|رُدُّوْا|لَعَادُوْا|لِمَا|نُهُوْا|عَنْهُ|وَاِنَّهُمْ|لَكٰذِبُوْنَ","u": "بَلۡ|بَدَا|لَهُم|مَّا|كَانُواْ|يُخۡفُونَ|مِن|قَبۡلُۖ|وَلَوۡ|رُدُّواْ|لَعَادُواْ|لِمَا|نُهُواْ|عَنۡهُ|وَإِنَّهُمۡ|لَكَٰذِبُونَ","t": "bal|bada|lahum|ma|kanu|yukh'funa|min|qablu|walaw|ruddu|la'adu|lima|nuhu|anhu|wa-innahum|lakadhibuna","e": "۟/٢٨/."},"29": {"p": 131,"j": 7,"h": 52,"m": 2,"r": 104,"i": "وَقَالُوْۤا|اِنْ|هِیَ|اِلَّا|حَیَاتُنَا|الدُّنْیَا|وَمَا|نَحْنُ|بِمَبْعُوْثِیْنَ","u": "وَقَالُوٓاْ|إِنۡ|هِيَ|إِلَّا|حَيَاتُنَا|ٱلدُّنۡيَا|وَمَا|نَحۡنُ|بِمَبۡعُوثِينَ","t": "waqalu|in|hiya|illa|hayatuna|al-dun'ya|wama|nahnu|bimab'uthina","e": "۟/٢٩/."},"30": {"p": 131,"j": 7,"h": 52,"m": 2,"r": 104,"i": "وَلَوْ|تَرٰۤی|اِذْ|وُقِفُوْا|عَلٰی|رَبِّهِمْ ؕ—|قَالَ|اَلَیْسَ|هٰذَا|بِالْحَقِّ ؕ—|قَالُوْا|بَلٰی|وَرَبِّنَا ؕ—|قَالَ|فَذُوْقُوا|الْعَذَابَ|بِمَا|كُنْتُمْ|تَكْفُرُوْنَ","u": "وَلَوۡ|تَرَىٰٓ|إِذۡ|وُقِفُواْ|عَلَىٰ|رَبِّهِمۡۚ|قَالَ|أَلَيۡسَ|هَٰذَا|بِٱلۡحَقِّۚ|قَالُواْ|بَلَىٰ|وَرَبِّنَاۚ|قَالَ|فَذُوقُواْ|ٱلۡعَذَابَ|بِمَا|كُنتُمۡ|تَكۡفُرُونَ","t": "walaw|tara|idh|wuqifu|ala|rabbihim|qala|alaysa|hadha|bil-haqi|qalu|bala|warabbina|qala|fadhuqu|al-'adhaba|bima|kuntum|takfuruna","e": "۟۠/٣٠/."},"31": {"p": 131,"j": 7,"h": 52,"m": 2,"r": 105,"i": "قَدْ|خَسِرَ|الَّذِیْنَ|كَذَّبُوْا|بِلِقَآءِ|اللّٰهِ ؕ—|حَتّٰۤی|اِذَا|جَآءَتْهُمُ|السَّاعَةُ|بَغْتَةً|قَالُوْا|یٰحَسْرَتَنَا|عَلٰی|مَا|فَرَّطْنَا|فِیْهَا ۙ—|وَهُمْ|یَحْمِلُوْنَ|اَوْزَارَهُمْ|عَلٰی|ظُهُوْرِهِمْ ؕ—|اَلَا|سَآءَ|مَا|یَزِرُوْنَ","u": "قَدۡ|خَسِرَ|ٱلَّذِينَ|كَذَّبُواْ|بِلِقَآءِ|ٱللَّهِۖ|حَتَّىٰٓ|إِذَا|جَآءَتۡهُمُ|ٱلسَّاعَةُ|بَغۡتَةٗ|قَالُواْ|يَٰحَسۡرَتَنَا|عَلَىٰ|مَا|فَرَّطۡنَا|فِيهَا|وَهُمۡ|يَحۡمِلُونَ|أَوۡزَارَهُمۡ|عَلَىٰ|ظُهُورِهِمۡۚ|أَلَا|سَآءَ|مَا|يَزِرُونَ","t": "qad|khasira|alladhina|kadhabu|biliqai|al-lahi|hatta|idha|jaathumu|al-sa'atu|baghtatan|qalu|yahasratana|ala|ma|farratna|fiha|wahum|yahmiluna|awzarahum|ala|zuhurihim|ala|saa|ma|yaziruna","e": "۟/٣١/."},"32": {"p": 131,"j": 7,"h": 52,"m": 2,"r": 105,"i": "وَمَا|الْحَیٰوةُ|الدُّنْیَاۤ|اِلَّا|لَعِبٌ|وَّلَهْوٌ ؕ—|وَلَلدَّارُ|الْاٰخِرَةُ|خَیْرٌ|لِّلَّذِیْنَ|یَتَّقُوْنَ ؕ—|اَفَلَا|تَعْقِلُوْنَ","u": "وَمَا|ٱلۡحَيَوٰةُ|ٱلدُّنۡيَآ|إِلَّا|لَعِبٞ|وَلَهۡوٞۖ|وَلَلدَّارُ|ٱلۡأٓخِرَةُ|خَيۡرٞ|لِّلَّذِينَ|يَتَّقُونَۚ|أَفَلَا|تَعۡقِلُونَ","t": "wama|al-hayatu|al-dun'ya|illa|la'ibun|walahwun|walalddaru|al-akhiratu|khayrun|lilladhina|yattaquna|afala|ta'qiluna","e": "۟/٣٢/."},"33": {"p": 131,"j": 7,"h": 52,"m": 2,"r": 105,"i": "قَدْ|نَعْلَمُ|اِنَّهٗ|لَیَحْزُنُكَ|الَّذِیْ|یَقُوْلُوْنَ|فَاِنَّهُمْ|لَا|یُكَذِّبُوْنَكَ|وَلٰكِنَّ|الظّٰلِمِیْنَ|بِاٰیٰتِ|اللّٰهِ|یَجْحَدُوْنَ","u": "قَدۡ|نَعۡلَمُ|إِنَّهُۥ|لَيَحۡزُنُكَ|ٱلَّذِي|يَقُولُونَۖ|فَإِنَّهُمۡ|لَا|يُكَذِّبُونَكَ|وَلَٰكِنَّ|ٱلظَّٰلِمِينَ|بِـَٔايَٰتِ|ٱللَّهِ|يَجۡحَدُونَ","t": "qad|na'lamu|innahu|layahzunuka|alladhi|yaquluna|fa-innahum|la|yukadhibunaka|walakinna|al-zalimina|biayati|al-lahi|yajhaduna","e": "۟/٣٣/."},"34": {"p": 131,"j": 7,"h": 52,"m": 2,"r": 105,"i": "وَلَقَدْ|كُذِّبَتْ|رُسُلٌ|مِّنْ|قَبْلِكَ|فَصَبَرُوْا|عَلٰی|مَا|كُذِّبُوْا|وَاُوْذُوْا|حَتّٰۤی|اَتٰىهُمْ|نَصْرُنَا ۚ—|وَلَا|مُبَدِّلَ|لِكَلِمٰتِ|اللّٰهِ ۚ—|وَلَقَدْ|جَآءَكَ|مِنْ|نَّبَاۡ|الْمُرْسَلِیْنَ","u": "وَلَقَدۡ|كُذِّبَتۡ|رُسُلٞ|مِّن|قَبۡلِكَ|فَصَبَرُواْ|عَلَىٰ|مَا|كُذِّبُواْ|وَأُوذُواْ|حَتَّىٰٓ|أَتَىٰهُمۡ|نَصۡرُنَاۚ|وَلَا|مُبَدِّلَ|لِكَلِمَٰتِ|ٱللَّهِۚ|وَلَقَدۡ|جَآءَكَ|مِن|نَّبَإِيْ|ٱلۡمُرۡسَلِينَ","t": "walaqad|kudhibat|rusulun|min|qablika|fasabaru|ala|ma|kudhibu|waudhu|hatta|atahum|nasruna|wala|mubaddila|likalimati|al-lahi|walaqad|jaaka|min|naba-i|al-mur'salina","e": "۟/٣٤/."},"35": {"p": 131,"j": 7,"h": 52,"m": 2,"r": 105,"i": "وَاِنْ|كَانَ|كَبُرَ|عَلَیْكَ|اِعْرَاضُهُمْ|فَاِنِ|اسْتَطَعْتَ|اَنْ|تَبْتَغِیَ|نَفَقًا|فِی|الْاَرْضِ|اَوْ|سُلَّمًا|فِی|السَّمَآءِ|فَتَاْتِیَهُمْ|بِاٰیَةٍ ؕ—|وَلَوْ|شَآءَ|اللّٰهُ|لَجَمَعَهُمْ|عَلَی|الْهُدٰی|فَلَا|تَكُوْنَنَّ|مِنَ|الْجٰهِلِیْنَ","u": "وَإِن|كَانَ|كَبُرَ|عَلَيۡكَ|إِعۡرَاضُهُمۡ|فَإِنِ|ٱسۡتَطَعۡتَ|أَن|تَبۡتَغِيَ|نَفَقٗا|فِي|ٱلۡأَرۡضِ|أَوۡ|سُلَّمٗا|فِي|ٱلسَّمَآءِ|فَتَأۡتِيَهُم|بِـَٔايَةٖۚ|وَلَوۡ|شَآءَ|ٱللَّهُ|لَجَمَعَهُمۡ|عَلَى|ٱلۡهُدَىٰۚ|فَلَا|تَكُونَنَّ|مِنَ|ٱلۡجَٰهِلِينَ","t": "wa-in|kana|kabura|alayka|i'raduhum|fa-ini|is'tata'ta|an|tabtaghiya|nafaqan|fi|al-ardi|aw|sullaman|fi|al-samai|fatatiyahum|biayatin|walaw|shaa|al-lahu|lajama'ahum|ala|al-huda|fala|takunanna|mina|al-jahilina","e": "۟/٣٥/."},"36": {"p": 132,"j": 7,"h": 53,"m": 2,"r": 105,"i": "اِنَّمَا|یَسْتَجِیْبُ|الَّذِیْنَ|یَسْمَعُوْنَ ؔؕ—|وَالْمَوْتٰی|یَبْعَثُهُمُ|اللّٰهُ|ثُمَّ|اِلَیْهِ|یُرْجَعُوْنَ","u": "۞إِنَّمَا|يَسۡتَجِيبُ|ٱلَّذِينَ|يَسۡمَعُونَۘ|وَٱلۡمَوۡتَىٰ|يَبۡعَثُهُمُ|ٱللَّهُ|ثُمَّ|إِلَيۡهِ|يُرۡجَعُونَ","t": "innama|yastajibu|alladhina|yasma'una|wal-mawta|yab'athuhumu|al-lahu|thumma|ilayhi|yur'ja'una","e": "۟/٣٦/."},"37": {"p": 132,"j": 7,"h": 53,"m": 2,"r": 105,"i": "وَقَالُوْا|لَوْلَا|نُزِّلَ|عَلَیْهِ|اٰیَةٌ|مِّنْ|رَّبِّهٖ ؕ—|قُلْ|اِنَّ|اللّٰهَ|قَادِرٌ|عَلٰۤی|اَنْ|یُّنَزِّلَ|اٰیَةً|وَّلٰكِنَّ|اَكْثَرَهُمْ|لَا|یَعْلَمُوْنَ","u": "وَقَالُواْ|لَوۡلَا|نُزِّلَ|عَلَيۡهِ|ءَايَةٞ|مِّن|رَّبِّهِۦۚ|قُلۡ|إِنَّ|ٱللَّهَ|قَادِرٌ|عَلَىٰٓ|أَن|يُنَزِّلَ|ءَايَةٗ|وَلَٰكِنَّ|أَكۡثَرَهُمۡ|لَا|يَعۡلَمُونَ","t": "waqalu|lawla|nuzzila|alayhi|ayatun|min|rabbihi|qul|inna|al-laha|qadirun|ala|an|yunazzila|ayatan|walakinna|aktharahum|la|ya'lamuna","e": "۟/٣٧/."},"38": {"p": 132,"j": 7,"h": 53,"m": 2,"r": 105,"i": "وَمَا|مِنْ|دَآبَّةٍ|فِی|الْاَرْضِ|وَلَا|طٰٓىِٕرٍ|یَّطِیْرُ|بِجَنَاحَیْهِ|اِلَّاۤ|اُمَمٌ|اَمْثَالُكُمْ ؕ—|مَا|فَرَّطْنَا|فِی|الْكِتٰبِ|مِنْ|شَیْءٍ|ثُمَّ|اِلٰی|رَبِّهِمْ|یُحْشَرُوْنَ","u": "وَمَا|مِن|دَآبَّةٖ|فِي|ٱلۡأَرۡضِ|وَلَا|طَٰٓئِرٖ|يَطِيرُ|بِجَنَاحَيۡهِ|إِلَّآ|أُمَمٌ|أَمۡثَالُكُمۚ|مَّا|فَرَّطۡنَا|فِي|ٱلۡكِتَٰبِ|مِن|شَيۡءٖۚ|ثُمَّ|إِلَىٰ|رَبِّهِمۡ|يُحۡشَرُونَ","t": "wama|min|dabbatin|fi|al-ardi|wala|tairin|yatiru|bijanahayhi|illa|umamun|amthalukum|ma|farratna|fi|al-kitabi|min|shayin|thumma|ila|rabbihim|yuh'sharuna","e": "۟/٣٨/."},"39": {"p": 132,"j": 7,"h": 53,"m": 2,"r": 105,"i": "وَالَّذِیْنَ|كَذَّبُوْا|بِاٰیٰتِنَا|صُمٌّ|وَّبُكْمٌ|فِی|الظُّلُمٰتِ ؕ—|مَنْ|یَّشَاِ|اللّٰهُ|یُضْلِلْهُ ؕ—|وَمَنْ|یَّشَاْ|یَجْعَلْهُ|عَلٰی|صِرَاطٍ|مُّسْتَقِیْمٍ","u": "وَٱلَّذِينَ|كَذَّبُواْ|بِـَٔايَٰتِنَا|صُمّٞ|وَبُكۡمٞ|فِي|ٱلظُّلُمَٰتِۗ|مَن|يَشَإِ|ٱللَّهُ|يُضۡلِلۡهُ|وَمَن|يَشَأۡ|يَجۡعَلۡهُ|عَلَىٰ|صِرَٰطٖ|مُّسۡتَقِيمٖ","t": "wa-alladhina|kadhabu|biayatina|summun|wabuk'mun|fi|al-zulumati|man|yasha-i|al-lahu|yud'lil'hu|waman|yasha|yaj'alhu|ala|siratin|mus'taqimin","e": "۟/٣٩/."},"40": {"p": 132,"j": 7,"h": 53,"m": 2,"r": 105,"i": "قُلْ|اَرَءَیْتَكُمْ|اِنْ|اَتٰىكُمْ|عَذَابُ|اللّٰهِ|اَوْ|اَتَتْكُمُ|السَّاعَةُ|اَغَیْرَ|اللّٰهِ|تَدْعُوْنَ ۚ—|اِنْ|كُنْتُمْ|صٰدِقِیْنَ","u": "قُلۡ|أَرَءَيۡتَكُمۡ|إِنۡ|أَتَىٰكُمۡ|عَذَابُ|ٱللَّهِ|أَوۡ|أَتَتۡكُمُ|ٱلسَّاعَةُ|أَغَيۡرَ|ٱللَّهِ|تَدۡعُونَ|إِن|كُنتُمۡ|صَٰدِقِينَ","t": "qul|ara-aytakum|in|atakum|adhabu|al-lahi|aw|atatkumu|al-sa'atu|aghayra|al-lahi|tad'una|in|kuntum|sadiqina","e": "۟/٤٠/."},"41": {"p": 132,"j": 7,"h": 53,"m": 2,"r": 105,"i": "بَلْ|اِیَّاهُ|تَدْعُوْنَ|فَیَكْشِفُ|مَا|تَدْعُوْنَ|اِلَیْهِ|اِنْ|شَآءَ|وَتَنْسَوْنَ|مَا|تُشْرِكُوْنَ","u": "بَلۡ|إِيَّاهُ|تَدۡعُونَ|فَيَكۡشِفُ|مَا|تَدۡعُونَ|إِلَيۡهِ|إِن|شَآءَ|وَتَنسَوۡنَ|مَا|تُشۡرِكُونَ","t": "bal|iyyahu|tad'una|fayakshifu|ma|tad'una|ilayhi|in|shaa|watansawna|ma|tush'rikuna","e": "۟۠/٤١/."},"42": {"p": 132,"j": 7,"h": 53,"m": 2,"r": 106,"i": "وَلَقَدْ|اَرْسَلْنَاۤ|اِلٰۤی|اُمَمٍ|مِّنْ|قَبْلِكَ|فَاَخَذْنٰهُمْ|بِالْبَاْسَآءِ|وَالضَّرَّآءِ|لَعَلَّهُمْ|یَتَضَرَّعُوْنَ","u": "وَلَقَدۡ|أَرۡسَلۡنَآ|إِلَىٰٓ|أُمَمٖ|مِّن|قَبۡلِكَ|فَأَخَذۡنَٰهُم|بِٱلۡبَأۡسَآءِ|وَٱلضَّرَّآءِ|لَعَلَّهُمۡ|يَتَضَرَّعُونَ","t": "walaqad|arsalna|ila|umamin|min|qablika|fa-akhadhnahum|bil-basai|wal-darai|la'allahum|yatadarra'una","e": "۟/٤٢/."},"43": {"p": 132,"j": 7,"h": 53,"m": 2,"r": 106,"i": "فَلَوْلَاۤ|اِذْ|جَآءَهُمْ|بَاْسُنَا|تَضَرَّعُوْا|وَلٰكِنْ|قَسَتْ|قُلُوْبُهُمْ|وَزَیَّنَ|لَهُمُ|الشَّیْطٰنُ|مَا|كَانُوْا|یَعْمَلُوْنَ","u": "فَلَوۡلَآ|إِذۡ|جَآءَهُم|بَأۡسُنَا|تَضَرَّعُواْ|وَلَٰكِن|قَسَتۡ|قُلُوبُهُمۡ|وَزَيَّنَ|لَهُمُ|ٱلشَّيۡطَٰنُ|مَا|كَانُواْ|يَعۡمَلُونَ","t": "falawla|idh|jaahum|basuna|tadarra'u|walakin|qasat|qulubuhum|wazayyana|lahumu|al-shaytanu|ma|kanu|ya'maluna","e": "۟/٤٣/."},"44": {"p": 132,"j": 7,"h": 53,"m": 2,"r": 106,"i": "فَلَمَّا|نَسُوْا|مَا|ذُكِّرُوْا|بِهٖ|فَتَحْنَا|عَلَیْهِمْ|اَبْوَابَ|كُلِّ|شَیْءٍ ؕ—|حَتّٰۤی|اِذَا|فَرِحُوْا|بِمَاۤ|اُوْتُوْۤا|اَخَذْنٰهُمْ|بَغْتَةً|فَاِذَا|هُمْ|مُّبْلِسُوْنَ","u": "فَلَمَّا|نَسُواْ|مَا|ذُكِّرُواْ|بِهِۦ|فَتَحۡنَا|عَلَيۡهِمۡ|أَبۡوَٰبَ|كُلِّ|شَيۡءٍ|حَتَّىٰٓ|إِذَا|فَرِحُواْ|بِمَآ|أُوتُوٓاْ|أَخَذۡنَٰهُم|بَغۡتَةٗ|فَإِذَا|هُم|مُّبۡلِسُونَ","t": "falamma|nasu|ma|dhukkiru|bihi|fatahna|alayhim|abwaba|kulli|shayin|hatta|idha|farihu|bima|utu|akhadhnahum|baghtatan|fa-idha|hum|mub'lisuna","e": "۟/٤٤/."},"45": {"p": 133,"j": 7,"h": 53,"m": 2,"r": 106,"i": "فَقُطِعَ|دَابِرُ|الْقَوْمِ|الَّذِیْنَ|ظَلَمُوْا ؕ—|وَالْحَمْدُ|لِلّٰهِ|رَبِّ|الْعٰلَمِیْنَ","u": "فَقُطِعَ|دَابِرُ|ٱلۡقَوۡمِ|ٱلَّذِينَ|ظَلَمُواْۚ|وَٱلۡحَمۡدُ|لِلَّهِ|رَبِّ|ٱلۡعَٰلَمِينَ","t": "faquti'a|dabiru|al-qawmi|alladhina|zalamu|wal-hamdu|lillahi|rabbi|al-'alamina","e": "۟/٤٥/."},"46": {"p": 133,"j": 7,"h": 53,"m": 2,"r": 106,"i": "قُلْ|اَرَءَیْتُمْ|اِنْ|اَخَذَ|اللّٰهُ|سَمْعَكُمْ|وَاَبْصَارَكُمْ|وَخَتَمَ|عَلٰی|قُلُوْبِكُمْ|مَّنْ|اِلٰهٌ|غَیْرُ|اللّٰهِ|یَاْتِیْكُمْ|بِهٖ ؕ—|اُنْظُرْ|كَیْفَ|نُصَرِّفُ|الْاٰیٰتِ|ثُمَّ|هُمْ|یَصْدِفُوْنَ","u": "قُلۡ|أَرَءَيۡتُمۡ|إِنۡ|أَخَذَ|ٱللَّهُ|سَمۡعَكُمۡ|وَأَبۡصَٰرَكُمۡ|وَخَتَمَ|عَلَىٰ|قُلُوبِكُم|مَّنۡ|إِلَٰهٌ|غَيۡرُ|ٱللَّهِ|يَأۡتِيكُم|بِهِۗ|ٱنظُرۡ|كَيۡفَ|نُصَرِّفُ|ٱلۡأٓيَٰتِ|ثُمَّ|هُمۡ|يَصۡدِفُونَ","t": "qul|ara-aytum|in|akhadha|al-lahu|sam'akum|wa-absarakum|wakhatama|ala|qulubikum|man|ilahun|ghayru|al-lahi|yatikum|bihi|unzur|kayfa|nusarrifu|al-ayati|thumma|hum|yasdifuna","e": "۟/٤٦/."},"47": {"p": 133,"j": 7,"h": 53,"m": 2,"r": 106,"i": "قُلْ|اَرَءَیْتَكُمْ|اِنْ|اَتٰىكُمْ|عَذَابُ|اللّٰهِ|بَغْتَةً|اَوْ|جَهْرَةً|هَلْ|یُهْلَكُ|اِلَّا|الْقَوْمُ|الظّٰلِمُوْنَ","u": "قُلۡ|أَرَءَيۡتَكُمۡ|إِنۡ|أَتَىٰكُمۡ|عَذَابُ|ٱللَّهِ|بَغۡتَةً|أَوۡ|جَهۡرَةً|هَلۡ|يُهۡلَكُ|إِلَّا|ٱلۡقَوۡمُ|ٱلظَّٰلِمُونَ","t": "qul|ara-aytakum|in|atakum|adhabu|al-lahi|baghtatan|aw|jahratan|hal|yuh'laku|illa|al-qawmu|al-zalimuna","e": "۟/٤٧/."},"48": {"p": 133,"j": 7,"h": 53,"m": 2,"r": 106,"i": "وَمَا|نُرْسِلُ|الْمُرْسَلِیْنَ|اِلَّا|مُبَشِّرِیْنَ|وَمُنْذِرِیْنَ ۚ—|فَمَنْ|اٰمَنَ|وَاَصْلَحَ|فَلَا|خَوْفٌ|عَلَیْهِمْ|وَلَا|هُمْ|یَحْزَنُوْنَ","u": "وَمَا|نُرۡسِلُ|ٱلۡمُرۡسَلِينَ|إِلَّا|مُبَشِّرِينَ|وَمُنذِرِينَۖ|فَمَنۡ|ءَامَنَ|وَأَصۡلَحَ|فَلَا|خَوۡفٌ|عَلَيۡهِمۡ|وَلَا|هُمۡ|يَحۡزَنُونَ","t": "wama|nur'silu|al-mur'salina|illa|mubashirina|wamundhirina|faman|amana|wa-aslaha|fala|khawfun|alayhim|wala|hum|yahzanuna","e": "۟/٤٨/."},"49": {"p": 133,"j": 7,"h": 53,"m": 2,"r": 106,"i": "وَالَّذِیْنَ|كَذَّبُوْا|بِاٰیٰتِنَا|یَمَسُّهُمُ|الْعَذَابُ|بِمَا|كَانُوْا|یَفْسُقُوْنَ","u": "وَٱلَّذِينَ|كَذَّبُواْ|بِـَٔايَٰتِنَا|يَمَسُّهُمُ|ٱلۡعَذَابُ|بِمَا|كَانُواْ|يَفۡسُقُونَ","t": "wa-alladhina|kadhabu|biayatina|yamassuhumu|al-'adhabu|bima|kanu|yafsuquna","e": "۟/٤٩/."},"50": {"p": 133,"j": 7,"h": 53,"m": 2,"r": 106,"i": "قُلْ|لَّاۤ|اَقُوْلُ|لَكُمْ|عِنْدِیْ|خَزَآىِٕنُ|اللّٰهِ|وَلَاۤ|اَعْلَمُ|الْغَیْبَ|وَلَاۤ|اَقُوْلُ|لَكُمْ|اِنِّیْ|مَلَكٌ ۚ—|اِنْ|اَتَّبِعُ|اِلَّا|مَا|یُوْحٰۤی|اِلَیَّ ؕ—|قُلْ|هَلْ|یَسْتَوِی|الْاَعْمٰی|وَالْبَصِیْرُ ؕ—|اَفَلَا|تَتَفَكَّرُوْنَ","u": "قُل|لَّآ|أَقُولُ|لَكُمۡ|عِندِي|خَزَآئِنُ|ٱللَّهِ|وَلَآ|أَعۡلَمُ|ٱلۡغَيۡبَ|وَلَآ|أَقُولُ|لَكُمۡ|إِنِّي|مَلَكٌۖ|إِنۡ|أَتَّبِعُ|إِلَّا|مَا|يُوحَىٰٓ|إِلَيَّۚ|قُلۡ|هَلۡ|يَسۡتَوِي|ٱلۡأَعۡمَىٰ|وَٱلۡبَصِيرُۚ|أَفَلَا|تَتَفَكَّرُونَ","t": "qul|la|aqulu|lakum|indi|khazainu|al-lahi|wala|a'lamu|al-ghayba|wala|aqulu|lakum|inni|malakun|in|attabi'u|illa|ma|yuha|ilayya|qul|hal|yastawi|al-a'ma|wal-basiru|afala|tatafakkaruna","e": "۟۠/٥٠/."},"51": {"p": 133,"j": 7,"h": 53,"m": 2,"r": 107,"i": "وَاَنْذِرْ|بِهِ|الَّذِیْنَ|یَخَافُوْنَ|اَنْ|یُّحْشَرُوْۤا|اِلٰی|رَبِّهِمْ|لَیْسَ|لَهُمْ|مِّنْ|دُوْنِهٖ|وَلِیٌّ|وَّلَا|شَفِیْعٌ|لَّعَلَّهُمْ|یَتَّقُوْنَ","u": "وَأَنذِرۡ|بِهِ|ٱلَّذِينَ|يَخَافُونَ|أَن|يُحۡشَرُوٓاْ|إِلَىٰ|رَبِّهِمۡ|لَيۡسَ|لَهُم|مِّن|دُونِهِۦ|وَلِيّٞ|وَلَا|شَفِيعٞ|لَّعَلَّهُمۡ|يَتَّقُونَ","t": "wa-andhir|bihi|alladhina|yakhafuna|an|yuh'sharu|ila|rabbihim|laysa|lahum|min|dunihi|waliyyun|wala|shafi'un|la'allahum|yattaquna","e": "۟/٥١/."},"52": {"p": 133,"j": 7,"h": 53,"m": 2,"r": 107,"i": "وَلَا|تَطْرُدِ|الَّذِیْنَ|یَدْعُوْنَ|رَبَّهُمْ|بِالْغَدٰوةِ|وَالْعَشِیِّ|یُرِیْدُوْنَ|وَجْهَهٗ ؕ—|مَا|عَلَیْكَ|مِنْ|حِسَابِهِمْ|مِّنْ|شَیْءٍ|وَّمَا|مِنْ|حِسَابِكَ|عَلَیْهِمْ|مِّنْ|شَیْءٍ|فَتَطْرُدَهُمْ|فَتَكُوْنَ|مِنَ|الظّٰلِمِیْنَ","u": "وَلَا|تَطۡرُدِ|ٱلَّذِينَ|يَدۡعُونَ|رَبَّهُم|بِٱلۡغَدَوٰةِ|وَٱلۡعَشِيِّ|يُرِيدُونَ|وَجۡهَهُۥۖ|مَا|عَلَيۡكَ|مِنۡ|حِسَابِهِم|مِّن|شَيۡءٖ|وَمَا|مِنۡ|حِسَابِكَ|عَلَيۡهِم|مِّن|شَيۡءٖ|فَتَطۡرُدَهُمۡ|فَتَكُونَ|مِنَ|ٱلظَّٰلِمِينَ","t": "wala|tatrudi|alladhina|yad'una|rabbahum|bil-ghadati|wal-'ashiyi|yuriduna|wajhahu|ma|alayka|min|hisabihim|min|shayin|wama|min|hisabika|alayhim|min|shayin|fatatrudahum|fatakuna|mina|al-zalimina","e": "۟/٥٢/."},"53": {"p": 134,"j": 7,"h": 53,"m": 2,"r": 107,"i": "وَكَذٰلِكَ|فَتَنَّا|بَعْضَهُمْ|بِبَعْضٍ|لِّیَقُوْلُوْۤا|اَهٰۤؤُلَآءِ|مَنَّ|اللّٰهُ|عَلَیْهِمْ|مِّنْ|بَیْنِنَا ؕ—|اَلَیْسَ|اللّٰهُ|بِاَعْلَمَ|بِالشّٰكِرِیْنَ","u": "وَكَذَٰلِكَ|فَتَنَّا|بَعۡضَهُم|بِبَعۡضٖ|لِّيَقُولُوٓاْ|أَهَٰٓؤُلَآءِ|مَنَّ|ٱللَّهُ|عَلَيۡهِم|مِّنۢ|بَيۡنِنَآۗ|أَلَيۡسَ|ٱللَّهُ|بِأَعۡلَمَ|بِٱلشَّٰكِرِينَ","t": "wakadhalika|fatanna|ba'dahum|biba'din|liyaqulu|ahaulai|manna|al-lahu|alayhim|min|baynina|alaysa|al-lahu|bi-a'lama|bil-shakirina","e": "۟/٥٣/."},"54": {"p": 134,"j": 7,"h": 53,"m": 2,"r": 107,"i": "وَاِذَا|جَآءَكَ|الَّذِیْنَ|یُؤْمِنُوْنَ|بِاٰیٰتِنَا|فَقُلْ|سَلٰمٌ|عَلَیْكُمْ|كَتَبَ|رَبُّكُمْ|عَلٰی|نَفْسِهِ|الرَّحْمَةَ ۙ—|اَنَّهٗ|مَنْ|عَمِلَ|مِنْكُمْ|سُوْٓءًا|بِجَهَالَةٍ|ثُمَّ|تَابَ|مِنْ|بَعْدِهٖ|وَاَصْلَحَ ۙ—|فَاَنَّهٗ|غَفُوْرٌ|رَّحِیْمٌ","u": "وَإِذَا|جَآءَكَ|ٱلَّذِينَ|يُؤۡمِنُونَ|بِـَٔايَٰتِنَا|فَقُلۡ|سَلَٰمٌ|عَلَيۡكُمۡۖ|كَتَبَ|رَبُّكُمۡ|عَلَىٰ|نَفۡسِهِ|ٱلرَّحۡمَةَ|أَنَّهُۥ|مَنۡ|عَمِلَ|مِنكُمۡ|سُوٓءَۢا|بِجَهَٰلَةٖ|ثُمَّ|تَابَ|مِنۢ|بَعۡدِهِۦ|وَأَصۡلَحَ|فَأَنَّهُۥ|غَفُورٞ|رَّحِيمٞ","t": "wa-idha|jaaka|alladhina|yu'minuna|biayatina|faqul|salamun|alaykum|kataba|rabbukum|ala|nafsihi|al-rahmata|annahu|man|amila|minkum|suan|bijahalatin|thumma|taba|min|ba'dihi|wa-aslaha|fa-annahu|ghafurun|rahimun","e": "۟/٥٤/."},"55": {"p": 134,"j": 7,"h": 53,"m": 2,"r": 107,"i": "وَكَذٰلِكَ|نُفَصِّلُ|الْاٰیٰتِ|وَلِتَسْتَبِیْنَ|سَبِیْلُ|الْمُجْرِمِیْنَ","u": "وَكَذَٰلِكَ|نُفَصِّلُ|ٱلۡأٓيَٰتِ|وَلِتَسۡتَبِينَ|سَبِيلُ|ٱلۡمُجۡرِمِينَ","t": "wakadhalika|nufassilu|al-ayati|walitastabina|sabilu|al-muj'rimina","e": "۟۠/٥٥/."},"56": {"p": 134,"j": 7,"h": 53,"m": 2,"r": 108,"i": "قُلْ|اِنِّیْ|نُهِیْتُ|اَنْ|اَعْبُدَ|الَّذِیْنَ|تَدْعُوْنَ|مِنْ|دُوْنِ|اللّٰهِ ؕ—|قُلْ|لَّاۤ|اَتَّبِعُ|اَهْوَآءَكُمْ ۙ—|قَدْ|ضَلَلْتُ|اِذًا|وَّمَاۤ|اَنَا|مِنَ|الْمُهْتَدِیْنَ","u": "قُلۡ|إِنِّي|نُهِيتُ|أَنۡ|أَعۡبُدَ|ٱلَّذِينَ|تَدۡعُونَ|مِن|دُونِ|ٱللَّهِۚ|قُل|لَّآ|أَتَّبِعُ|أَهۡوَآءَكُمۡ|قَدۡ|ضَلَلۡتُ|إِذٗا|وَمَآ|أَنَا۠|مِنَ|ٱلۡمُهۡتَدِينَ","t": "qul|inni|nuhitu|an|a'buda|alladhina|tad'una|min|duni|al-lahi|qul|la|attabi'u|ahwaakum|qad|dalaltu|idhan|wama|ana|mina|al-muh'tadina","e": "۟/٥٦/."},"57": {"p": 134,"j": 7,"h": 53,"m": 2,"r": 108,"i": "قُلْ|اِنِّیْ|عَلٰی|بَیِّنَةٍ|مِّنْ|رَّبِّیْ|وَكَذَّبْتُمْ|بِهٖ ؕ—|مَا|عِنْدِیْ|مَا|تَسْتَعْجِلُوْنَ|بِهٖ ؕ—|اِنِ|الْحُكْمُ|اِلَّا|لِلّٰهِ ؕ—|یَقُصُّ|الْحَقَّ|وَهُوَ|خَیْرُ|الْفٰصِلِیْنَ","u": "قُلۡ|إِنِّي|عَلَىٰ|بَيِّنَةٖ|مِّن|رَّبِّي|وَكَذَّبۡتُم|بِهِۦۚ|مَا|عِندِي|مَا|تَسۡتَعۡجِلُونَ|بِهِۦٓۚ|إِنِ|ٱلۡحُكۡمُ|إِلَّا|لِلَّهِۖ|يَقُصُّ|ٱلۡحَقَّۖ|وَهُوَ|خَيۡرُ|ٱلۡفَٰصِلِينَ","t": "qul|inni|ala|bayyinatin|min|rabbi|wakadhabtum|bihi|ma|indi|ma|tasta'jiluna|bihi|ini|al-huk'mu|illa|lillahi|yaqussu|al-haqa|wahuwa|khayru|al-fasilina","e": "۟/٥٧/."},"58": {"p": 134,"j": 7,"h": 53,"m": 2,"r": 108,"i": "قُلْ|لَّوْ|اَنَّ|عِنْدِیْ|مَا|تَسْتَعْجِلُوْنَ|بِهٖ|لَقُضِیَ|الْاَمْرُ|بَیْنِیْ|وَبَیْنَكُمْ ؕ—|وَاللّٰهُ|اَعْلَمُ|بِالظّٰلِمِیْنَ","u": "قُل|لَّوۡ|أَنَّ|عِندِي|مَا|تَسۡتَعۡجِلُونَ|بِهِۦ|لَقُضِيَ|ٱلۡأَمۡرُ|بَيۡنِي|وَبَيۡنَكُمۡۗ|وَٱللَّهُ|أَعۡلَمُ|بِٱلظَّٰلِمِينَ","t": "qul|law|anna|indi|ma|tasta'jiluna|bihi|laqudiya|al-amru|bayni|wabaynakum|wal-lahu|a'lamu|bil-zalimina","e": "۟/٥٨/."},"59": {"p": 134,"j": 7,"h": 54,"m": 2,"r": 108,"i": "وَعِنْدَهٗ|مَفَاتِحُ|الْغَیْبِ|لَا|یَعْلَمُهَاۤ|اِلَّا|هُوَ ؕ—|وَیَعْلَمُ|مَا|فِی|الْبَرِّ|وَالْبَحْرِ ؕ—|وَمَا|تَسْقُطُ|مِنْ|وَّرَقَةٍ|اِلَّا|یَعْلَمُهَا|وَلَا|حَبَّةٍ|فِیْ|ظُلُمٰتِ|الْاَرْضِ|وَلَا|رَطْبٍ|وَّلَا|یَابِسٍ|اِلَّا|فِیْ|كِتٰبٍ|مُّبِیْنٍ","u": "۞وَعِندَهُۥ|مَفَاتِحُ|ٱلۡغَيۡبِ|لَا|يَعۡلَمُهَآ|إِلَّا|هُوَۚ|وَيَعۡلَمُ|مَا|فِي|ٱلۡبَرِّ|وَٱلۡبَحۡرِۚ|وَمَا|تَسۡقُطُ|مِن|وَرَقَةٍ|إِلَّا|يَعۡلَمُهَا|وَلَا|حَبَّةٖ|فِي|ظُلُمَٰتِ|ٱلۡأَرۡضِ|وَلَا|رَطۡبٖ|وَلَا|يَابِسٍ|إِلَّا|فِي|كِتَٰبٖ|مُّبِينٖ","t": "wa'indahu|mafatihu|al-ghaybi|la|ya'lamuha|illa|huwa|waya'lamu|ma|fi|al-bari|wal-bahri|wama|tasqutu|min|waraqatin|illa|ya'lamuha|wala|habbatin|fi|zulumati|al-ardi|wala|ratbin|wala|yabisin|illa|fi|kitabin|mubinin","e": "۟/٥٩/."},"60": {"p": 135,"j": 7,"h": 54,"m": 2,"r": 108,"i": "وَهُوَ|الَّذِیْ|یَتَوَفّٰىكُمْ|بِالَّیْلِ|وَیَعْلَمُ|مَا|جَرَحْتُمْ|بِالنَّهَارِ|ثُمَّ|یَبْعَثُكُمْ|فِیْهِ|لِیُقْضٰۤی|اَجَلٌ|مُّسَمًّی ۚ—|ثُمَّ|اِلَیْهِ|مَرْجِعُكُمْ|ثُمَّ|یُنَبِّئُكُمْ|بِمَا|كُنْتُمْ|تَعْمَلُوْنَ","u": "وَهُوَ|ٱلَّذِي|يَتَوَفَّىٰكُم|بِٱلَّيۡلِ|وَيَعۡلَمُ|مَا|جَرَحۡتُم|بِٱلنَّهَارِ|ثُمَّ|يَبۡعَثُكُمۡ|فِيهِ|لِيُقۡضَىٰٓ|أَجَلٞ|مُّسَمّٗىۖ|ثُمَّ|إِلَيۡهِ|مَرۡجِعُكُمۡ|ثُمَّ|يُنَبِّئُكُم|بِمَا|كُنتُمۡ|تَعۡمَلُونَ","t": "wahuwa|alladhi|yatawaffakum|bi-al-layli|waya'lamu|ma|jarahtum|bil-nahari|thumma|yab'athukum|fihi|liyuq'da|ajalun|musamman|thumma|ilayhi|marji'ukum|thumma|yunabbi-ukum|bima|kuntum|ta'maluna","e": "۟۠/٦٠/."},"61": {"p": 135,"j": 7,"h": 54,"m": 2,"r": 109,"i": "وَهُوَ|الْقَاهِرُ|فَوْقَ|عِبَادِهٖ|وَیُرْسِلُ|عَلَیْكُمْ|حَفَظَةً ؕ—|حَتّٰۤی|اِذَا|جَآءَ|اَحَدَكُمُ|الْمَوْتُ|تَوَفَّتْهُ|رُسُلُنَا|وَهُمْ|لَا|یُفَرِّطُوْنَ","u": "وَهُوَ|ٱلۡقَاهِرُ|فَوۡقَ|عِبَادِهِۦۖ|وَيُرۡسِلُ|عَلَيۡكُمۡ|حَفَظَةً|حَتَّىٰٓ|إِذَا|جَآءَ|أَحَدَكُمُ|ٱلۡمَوۡتُ|تَوَفَّتۡهُ|رُسُلُنَا|وَهُمۡ|لَا|يُفَرِّطُونَ","t": "wahuwa|al-qahiru|fawqa|ibadihi|wayur'silu|alaykum|hafazatan|hatta|idha|jaa|ahadakumu|al-mawtu|tawaffathu|rusuluna|wahum|la|yufarrituna","e": "۟/٦١/."},"62": {"p": 135,"j": 7,"h": 54,"m": 2,"r": 109,"i": "ثُمَّ|رُدُّوْۤا|اِلَی|اللّٰهِ|مَوْلٰىهُمُ|الْحَقِّ ؕ—|اَلَا|لَهُ|الْحُكْمُ ۫—|وَهُوَ|اَسْرَعُ|الْحٰسِبِیْنَ","u": "ثُمَّ|رُدُّوٓاْ|إِلَى|ٱللَّهِ|مَوۡلَىٰهُمُ|ٱلۡحَقِّۚ|أَلَا|لَهُ|ٱلۡحُكۡمُ|وَهُوَ|أَسۡرَعُ|ٱلۡحَٰسِبِينَ","t": "thumma|ruddu|ila|al-lahi|mawlahumu|al-haqi|ala|lahu|al-huk'mu|wahuwa|asra'u|al-hasibina","e": "۟/٦٢/."},"63": {"p": 135,"j": 7,"h": 54,"m": 2,"r": 109,"i": "قُلْ|مَنْ|یُّنَجِّیْكُمْ|مِّنْ|ظُلُمٰتِ|الْبَرِّ|وَالْبَحْرِ|تَدْعُوْنَهٗ|تَضَرُّعًا|وَّخُفْیَةً ۚ—|لَىِٕنْ|اَنْجٰىنَا|مِنْ|هٰذِهٖ|لَنَكُوْنَنَّ|مِنَ|الشّٰكِرِیْنَ","u": "قُلۡ|مَن|يُنَجِّيكُم|مِّن|ظُلُمَٰتِ|ٱلۡبَرِّ|وَٱلۡبَحۡرِ|تَدۡعُونَهُۥ|تَضَرُّعٗا|وَخُفۡيَةٗ|لَّئِنۡ|أَنجَىٰنَا|مِنۡ|هَٰذِهِۦ|لَنَكُونَنَّ|مِنَ|ٱلشَّٰكِرِينَ","t": "qul|man|yunajjikum|min|zulumati|al-bari|wal-bahri|tad'unahu|tadarru'an|wakhuf'yatan|la-in|anjana|min|hadhihi|lanakunanna|mina|al-shakirina","e": "۟/٦٣/."},"64": {"p": 135,"j": 7,"h": 54,"m": 2,"r": 109,"i": "قُلِ|اللّٰهُ|یُنَجِّیْكُمْ|مِّنْهَا|وَمِنْ|كُلِّ|كَرْبٍ|ثُمَّ|اَنْتُمْ|تُشْرِكُوْنَ","u": "قُلِ|ٱللَّهُ|يُنَجِّيكُم|مِّنۡهَا|وَمِن|كُلِّ|كَرۡبٖ|ثُمَّ|أَنتُمۡ|تُشۡرِكُونَ","t": "quli|al-lahu|yunajjikum|min'ha|wamin|kulli|karbin|thumma|antum|tush'rikuna","e": "۟/٦٤/."},"65": {"p": 135,"j": 7,"h": 54,"m": 2,"r": 109,"i": "قُلْ|هُوَ|الْقَادِرُ|عَلٰۤی|اَنْ|یَّبْعَثَ|عَلَیْكُمْ|عَذَابًا|مِّنْ|فَوْقِكُمْ|اَوْ|مِنْ|تَحْتِ|اَرْجُلِكُمْ|اَوْ|یَلْبِسَكُمْ|شِیَعًا|وَّیُذِیْقَ|بَعْضَكُمْ|بَاْسَ|بَعْضٍ ؕ—|اُنْظُرْ|كَیْفَ|نُصَرِّفُ|الْاٰیٰتِ|لَعَلَّهُمْ|یَفْقَهُوْنَ","u": "قُلۡ|هُوَ|ٱلۡقَادِرُ|عَلَىٰٓ|أَن|يَبۡعَثَ|عَلَيۡكُمۡ|عَذَابٗا|مِّن|فَوۡقِكُمۡ|أَوۡ|مِن|تَحۡتِ|أَرۡجُلِكُمۡ|أَوۡ|يَلۡبِسَكُمۡ|شِيَعٗا|وَيُذِيقَ|بَعۡضَكُم|بَأۡسَ|بَعۡضٍۗ|ٱنظُرۡ|كَيۡفَ|نُصَرِّفُ|ٱلۡأٓيَٰتِ|لَعَلَّهُمۡ|يَفۡقَهُونَ","t": "qul|huwa|al-qadiru|ala|an|yab'atha|alaykum|adhaban|min|fawqikum|aw|min|tahti|arjulikum|aw|yalbisakum|shiya'an|wayudhiqa|ba'dakum|basa|ba'din|unzur|kayfa|nusarrifu|al-ayati|la'allahum|yafqahuna","e": "۟/٦٥/."},"66": {"p": 135,"j": 7,"h": 54,"m": 2,"r": 109,"i": "وَكَذَّبَ|بِهٖ|قَوْمُكَ|وَهُوَ|الْحَقُّ ؕ—|قُلْ|لَّسْتُ|عَلَیْكُمْ|بِوَكِیْلٍ","u": "وَكَذَّبَ|بِهِۦ|قَوۡمُكَ|وَهُوَ|ٱلۡحَقُّۚ|قُل|لَّسۡتُ|عَلَيۡكُم|بِوَكِيلٖ","t": "wakadhaba|bihi|qawmuka|wahuwa|al-haqu|qul|lastu|alaykum|biwakilin","e": "۟ؕ/٦٦/."},"67": {"p": 135,"j": 7,"h": 54,"m": 2,"r": 109,"i": "لِكُلِّ|نَبَاٍ|مُّسْتَقَرٌّ ؗ—|وَّسَوْفَ|تَعْلَمُوْنَ","u": "لِّكُلِّ|نَبَإٖ|مُّسۡتَقَرّٞۚ|وَسَوۡفَ|تَعۡلَمُونَ","t": "likulli|naba-in|mus'taqarrun|wasawfa|ta'lamuna","e": "۟/٦٧/."},"68": {"p": 135,"j": 7,"h": 54,"m": 2,"r": 109,"i": "وَاِذَا|رَاَیْتَ|الَّذِیْنَ|یَخُوْضُوْنَ|فِیْۤ|اٰیٰتِنَا|فَاَعْرِضْ|عَنْهُمْ|حَتّٰی|یَخُوْضُوْا|فِیْ|حَدِیْثٍ|غَیْرِهٖ ؕ—|وَاِمَّا|یُنْسِیَنَّكَ|الشَّیْطٰنُ|فَلَا|تَقْعُدْ|بَعْدَ|الذِّكْرٰی|مَعَ|الْقَوْمِ|الظّٰلِمِیْنَ","u": "وَإِذَا|رَأَيۡتَ|ٱلَّذِينَ|يَخُوضُونَ|فِيٓ|ءَايَٰتِنَا|فَأَعۡرِضۡ|عَنۡهُمۡ|حَتَّىٰ|يَخُوضُواْ|فِي|حَدِيثٍ|غَيۡرِهِۦۚ|وَإِمَّا|يُنسِيَنَّكَ|ٱلشَّيۡطَٰنُ|فَلَا|تَقۡعُدۡ|بَعۡدَ|ٱلذِّكۡرَىٰ|مَعَ|ٱلۡقَوۡمِ|ٱلظَّٰلِمِينَ","t": "wa-idha|ra-ayta|alladhina|yakhuduna|fi|ayatina|fa-a'rid|anhum|hatta|yakhudu|fi|hadithin|ghayrihi|wa-imma|yunsiyannaka|al-shaytanu|fala|taq'ud|ba'da|al-dhik'ra|ma'a|al-qawmi|al-zalimina","e": "۟/٦٨/."},"69": {"p": 136,"j": 7,"h": 54,"m": 2,"r": 109,"i": "وَمَا|عَلَی|الَّذِیْنَ|یَتَّقُوْنَ|مِنْ|حِسَابِهِمْ|مِّنْ|شَیْءٍ|وَّلٰكِنْ|ذِكْرٰی|لَعَلَّهُمْ|یَتَّقُوْنَ","u": "وَمَا|عَلَى|ٱلَّذِينَ|يَتَّقُونَ|مِنۡ|حِسَابِهِم|مِّن|شَيۡءٖ|وَلَٰكِن|ذِكۡرَىٰ|لَعَلَّهُمۡ|يَتَّقُونَ","t": "wama|ala|alladhina|yattaquna|min|hisabihim|min|shayin|walakin|dhik'ra|la'allahum|yattaquna","e": "۟/٦٩/."},"70": {"p": 136,"j": 7,"h": 54,"m": 2,"r": 109,"i": "وَذَرِ|الَّذِیْنَ|اتَّخَذُوْا|دِیْنَهُمْ|لَعِبًا|وَّلَهْوًا|وَّغَرَّتْهُمُ|الْحَیٰوةُ|الدُّنْیَا|وَذَكِّرْ|بِهٖۤ|اَنْ|تُبْسَلَ|نَفْسٌ|بِمَا|كَسَبَتْ ۖۗ—|لَیْسَ|لَهَا|مِنْ|دُوْنِ|اللّٰهِ|وَلِیٌّ|وَّلَا|شَفِیْعٌ ۚ—|وَاِنْ|تَعْدِلْ|كُلَّ|عَدْلٍ|لَّا|یُؤْخَذْ|مِنْهَا ؕ—|اُولٰٓىِٕكَ|الَّذِیْنَ|اُبْسِلُوْا|بِمَا|كَسَبُوْا ۚ—|لَهُمْ|شَرَابٌ|مِّنْ|حَمِیْمٍ|وَّعَذَابٌ|اَلِیْمٌ|بِمَا|كَانُوْا|یَكْفُرُوْنَ","u": "وَذَرِ|ٱلَّذِينَ|ٱتَّخَذُواْ|دِينَهُمۡ|لَعِبٗا|وَلَهۡوٗا|وَغَرَّتۡهُمُ|ٱلۡحَيَوٰةُ|ٱلدُّنۡيَاۚ|وَذَكِّرۡ|بِهِۦٓ|أَن|تُبۡسَلَ|نَفۡسُۢ|بِمَا|كَسَبَتۡ|لَيۡسَ|لَهَا|مِن|دُونِ|ٱللَّهِ|وَلِيّٞ|وَلَا|شَفِيعٞ|وَإِن|تَعۡدِلۡ|كُلَّ|عَدۡلٖ|لَّا|يُؤۡخَذۡ|مِنۡهَآۗ|أُوْلَٰٓئِكَ|ٱلَّذِينَ|أُبۡسِلُواْ|بِمَا|كَسَبُواْۖ|لَهُمۡ|شَرَابٞ|مِّنۡ|حَمِيمٖ|وَعَذَابٌ|أَلِيمُۢ|بِمَا|كَانُواْ|يَكۡفُرُونَ","t": "wadhari|alladhina|ittakhadhu|dinahum|la'iban|walahwan|wagharrathumu|al-hayatu|al-dun'ya|wadhakkir|bihi|an|tub'sala|nafsun|bima|kasabat|laysa|laha|min|duni|al-lahi|waliyyun|wala|shafi'un|wa-in|ta'dil|kulla|adlin|la|yu'khadh|min'ha|ulaika|alladhina|ub'silu|bima|kasabu|lahum|sharabun|min|hamimin|wa'adhabun|alimun|bima|kanu|yakfuruna","e": "۟۠/٧٠/."},"71": {"p": 136,"j": 7,"h": 54,"m": 2,"r": 110,"i": "قُلْ|اَنَدْعُوْا|مِنْ|دُوْنِ|اللّٰهِ|مَا|لَا|یَنْفَعُنَا|وَلَا|یَضُرُّنَا|وَنُرَدُّ|عَلٰۤی|اَعْقَابِنَا|بَعْدَ|اِذْ|هَدٰىنَا|اللّٰهُ|كَالَّذِی|اسْتَهْوَتْهُ|الشَّیٰطِیْنُ|فِی|الْاَرْضِ|حَیْرَانَ ۪—|لَهٗۤ|اَصْحٰبٌ|یَّدْعُوْنَهٗۤ|اِلَی|الْهُدَی|ائْتِنَا ؕ—|قُلْ|اِنَّ|هُدَی|اللّٰهِ|هُوَ|الْهُدٰی ؕ—|وَاُمِرْنَا|لِنُسْلِمَ|لِرَبِّ|الْعٰلَمِیْنَ","u": "قُلۡ|أَنَدۡعُواْ|مِن|دُونِ|ٱللَّهِ|مَا|لَا|يَنفَعُنَا|وَلَا|يَضُرُّنَا|وَنُرَدُّ|عَلَىٰٓ|أَعۡقَابِنَا|بَعۡدَ|إِذۡ|هَدَىٰنَا|ٱللَّهُ|كَٱلَّذِي|ٱسۡتَهۡوَتۡهُ|ٱلشَّيَٰطِينُ|فِي|ٱلۡأَرۡضِ|حَيۡرَانَ|لَهُۥٓ|أَصۡحَٰبٞ|يَدۡعُونَهُۥٓ|إِلَى|ٱلۡهُدَى|ٱئۡتِنَاۗ|قُلۡ|إِنَّ|هُدَى|ٱللَّهِ|هُوَ|ٱلۡهُدَىٰۖ|وَأُمِرۡنَا|لِنُسۡلِمَ|لِرَبِّ|ٱلۡعَٰلَمِينَ","t": "qul|anad'u|min|duni|al-lahi|ma|la|yanfa'una|wala|yadurruna|wanuraddu|ala|a'qabina|ba'da|idh|hadana|al-lahu|ka-alladhi|is'tahwathu|al-shayatinu|fi|al-ardi|hayrana|lahu|ashabun|yad'unahu|ila|al-huda|i'tina|qul|inna|huda|al-lahi|huwa|al-huda|wa-umir'na|linus'lima|lirabbi|al-'alamina","e": "۟ۙ/٧١/."},"72": {"p": 136,"j": 7,"h": 54,"m": 2,"r": 110,"i": "وَاَنْ|اَقِیْمُوا|الصَّلٰوةَ|وَاتَّقُوْهُ ؕ—|وَهُوَ|الَّذِیْۤ|اِلَیْهِ|تُحْشَرُوْنَ","u": "وَأَنۡ|أَقِيمُواْ|ٱلصَّلَوٰةَ|وَٱتَّقُوهُۚ|وَهُوَ|ٱلَّذِيٓ|إِلَيۡهِ|تُحۡشَرُونَ","t": "wa-an|aqimu|al-salata|wa-ittaquhu|wahuwa|alladhi|ilayhi|tuh'sharuna","e": "۟/٧٢/."},"73": {"p": 136,"j": 7,"h": 54,"m": 2,"r": 110,"i": "وَهُوَ|الَّذِیْ|خَلَقَ|السَّمٰوٰتِ|وَالْاَرْضَ|بِالْحَقِّ ؕ—|وَیَوْمَ|یَقُوْلُ|كُنْ|فَیَكُوْنُ ؕ۬—|قَوْلُهُ|الْحَقُّ ؕ—|وَلَهُ|الْمُلْكُ|یَوْمَ|یُنْفَخُ|فِی|الصُّوْرِ ؕ—|عٰلِمُ|الْغَیْبِ|وَالشَّهَادَةِ ؕ—|وَهُوَ|الْحَكِیْمُ|الْخَبِیْرُ","u": "وَهُوَ|ٱلَّذِي|خَلَقَ|ٱلسَّمَٰوَٰتِ|وَٱلۡأَرۡضَ|بِٱلۡحَقِّۖ|وَيَوۡمَ|يَقُولُ|كُن|فَيَكُونُۚ|قَوۡلُهُ|ٱلۡحَقُّۚ|وَلَهُ|ٱلۡمُلۡكُ|يَوۡمَ|يُنفَخُ|فِي|ٱلصُّورِۚ|عَٰلِمُ|ٱلۡغَيۡبِ|وَٱلشَّهَٰدَةِۚ|وَهُوَ|ٱلۡحَكِيمُ|ٱلۡخَبِيرُ","t": "wahuwa|alladhi|khalaqa|al-samawati|wal-arda|bil-haqi|wayawma|yaqulu|kun|fayakunu|qawluhu|al-haqu|walahu|al-mul'ku|yawma|yunfakhu|fi|al-suri|alimu|al-ghaybi|wal-shahadati|wahuwa|al-hakimu|al-khabiru","e": "۟/٧٣/."},"74": {"p": 137,"j": 7,"h": 55,"m": 2,"r": 110,"i": "وَاِذْ|قَالَ|اِبْرٰهِیْمُ|لِاَبِیْهِ|اٰزَرَ|اَتَتَّخِذُ|اَصْنَامًا|اٰلِهَةً ۚ—|اِنِّیْۤ|اَرٰىكَ|وَقَوْمَكَ|فِیْ|ضَلٰلٍ|مُّبِیْنٍ","u": "۞وَإِذۡ|قَالَ|إِبۡرَٰهِيمُ|لِأَبِيهِ|ءَازَرَ|أَتَتَّخِذُ|أَصۡنَامًا|ءَالِهَةً|إِنِّيٓ|أَرَىٰكَ|وَقَوۡمَكَ|فِي|ضَلَٰلٖ|مُّبِينٖ","t": "wa-idh|qala|ib'rahimu|li-abihi|azara|atattakhidhu|asnaman|alihatan|inni|araka|waqawmaka|fi|dalalin|mubinin","e": "۟/٧٤/."},"75": {"p": 137,"j": 7,"h": 55,"m": 2,"r": 110,"i": "وَكَذٰلِكَ|نُرِیْۤ|اِبْرٰهِیْمَ|مَلَكُوْتَ|السَّمٰوٰتِ|وَالْاَرْضِ|وَلِیَكُوْنَ|مِنَ|الْمُوْقِنِیْنَ","u": "وَكَذَٰلِكَ|نُرِيٓ|إِبۡرَٰهِيمَ|مَلَكُوتَ|ٱلسَّمَٰوَٰتِ|وَٱلۡأَرۡضِ|وَلِيَكُونَ|مِنَ|ٱلۡمُوقِنِينَ","t": "wakadhalika|nuri|ib'rahima|malakuta|al-samawati|wal-ardi|waliyakuna|mina|al-muqinina","e": "۟/٧٥/."},"76": {"p": 137,"j": 7,"h": 55,"m": 2,"r": 110,"i": "فَلَمَّا|جَنَّ|عَلَیْهِ|الَّیْلُ|رَاٰ|كَوْكَبًا ۚ—|قَالَ|هٰذَا|رَبِّیْ ۚ—|فَلَمَّاۤ|اَفَلَ|قَالَ|لَاۤ|اُحِبُّ|الْاٰفِلِیْنَ","u": "فَلَمَّا|جَنَّ|عَلَيۡهِ|ٱلَّيۡلُ|رَءَا|كَوۡكَبٗاۖ|قَالَ|هَٰذَا|رَبِّيۖ|فَلَمَّآ|أَفَلَ|قَالَ|لَآ|أُحِبُّ|ٱلۡأٓفِلِينَ","t": "falamma|janna|alayhi|al-laylu|raa|kawkaban|qala|hadha|rabbi|falamma|afala|qala|la|uhibbu|al-afilina","e": "۟/٧٦/."},"77": {"p": 137,"j": 7,"h": 55,"m": 2,"r": 110,"i": "فَلَمَّا|رَاَ|الْقَمَرَ|بَازِغًا|قَالَ|هٰذَا|رَبِّیْ ۚ—|فَلَمَّاۤ|اَفَلَ|قَالَ|لَىِٕنْ|لَّمْ|یَهْدِنِیْ|رَبِّیْ|لَاَكُوْنَنَّ|مِنَ|الْقَوْمِ|الضَّآلِّیْنَ","u": "فَلَمَّا|رَءَا|ٱلۡقَمَرَ|بَازِغٗا|قَالَ|هَٰذَا|رَبِّيۖ|فَلَمَّآ|أَفَلَ|قَالَ|لَئِن|لَّمۡ|يَهۡدِنِي|رَبِّي|لَأَكُونَنَّ|مِنَ|ٱلۡقَوۡمِ|ٱلضَّآلِّينَ","t": "falamma|raa|al-qamara|bazighan|qala|hadha|rabbi|falamma|afala|qala|la-in|lam|yahdini|rabbi|la-akunanna|mina|al-qawmi|al-dalina","e": "۟/٧٧/."},"78": {"p": 137,"j": 7,"h": 55,"m": 2,"r": 110,"i": "فَلَمَّا|رَاَ|الشَّمْسَ|بَازِغَةً|قَالَ|هٰذَا|رَبِّیْ|هٰذَاۤ|اَكْبَرُ ۚ—|فَلَمَّاۤ|اَفَلَتْ|قَالَ|یٰقَوْمِ|اِنِّیْ|بَرِیْٓءٌ|مِّمَّا|تُشْرِكُوْنَ","u": "فَلَمَّا|رَءَا|ٱلشَّمۡسَ|بَازِغَةٗ|قَالَ|هَٰذَا|رَبِّي|هَٰذَآ|أَكۡبَرُۖ|فَلَمَّآ|أَفَلَتۡ|قَالَ|يَٰقَوۡمِ|إِنِّي|بَرِيٓءٞ|مِّمَّا|تُشۡرِكُونَ","t": "falamma|raa|al-shamsa|bazighatan|qala|hadha|rabbi|hadha|akbaru|falamma|afalat|qala|yaqawmi|inni|barion|mimma|tush'rikuna","e": "۟/٧٨/."},"79": {"p": 137,"j": 7,"h": 55,"m": 2,"r": 110,"i": "اِنِّیْ|وَجَّهْتُ|وَجْهِیَ|لِلَّذِیْ|فَطَرَ|السَّمٰوٰتِ|وَالْاَرْضَ|حَنِیْفًا|وَّمَاۤ|اَنَا|مِنَ|الْمُشْرِكِیْنَ","u": "إِنِّي|وَجَّهۡتُ|وَجۡهِيَ|لِلَّذِي|فَطَرَ|ٱلسَّمَٰوَٰتِ|وَٱلۡأَرۡضَ|حَنِيفٗاۖ|وَمَآ|أَنَا۠|مِنَ|ٱلۡمُشۡرِكِينَ","t": "inni|wajjahtu|wajhiya|lilladhi|fatara|al-samawati|wal-arda|hanifan|wama|ana|mina|al-mush'rikina","e": "۟ۚ/٧٩/."},"80": {"p": 137,"j": 7,"h": 55,"m": 2,"r": 110,"i": "وَحَآجَّهٗ|قَوْمُهٗ ؕ—|قَالَ|اَتُحَآجُّوْٓنِّیْ|فِی|اللّٰهِ|وَقَدْ|هَدٰىنِ ؕ—|وَلَاۤ|اَخَافُ|مَا|تُشْرِكُوْنَ|بِهٖۤ|اِلَّاۤ|اَنْ|یَّشَآءَ|رَبِّیْ|شَیْـًٔا ؕ—|وَسِعَ|رَبِّیْ|كُلَّ|شَیْءٍ|عِلْمًا ؕ—|اَفَلَا|تَتَذَكَّرُوْنَ","u": "وَحَآجَّهُۥ|قَوۡمُهُۥۚ|قَالَ|أَتُحَٰٓجُّوٓنِّي|فِي|ٱللَّهِ|وَقَدۡ|هَدَىٰنِۚ|وَلَآ|أَخَافُ|مَا|تُشۡرِكُونَ|بِهِۦٓ|إِلَّآ|أَن|يَشَآءَ|رَبِّي|شَيۡـٔٗاۚ|وَسِعَ|رَبِّي|كُلَّ|شَيۡءٍ|عِلۡمًاۚ|أَفَلَا|تَتَذَكَّرُونَ","t": "wahajjahu|qawmuhu|qala|atuhajjunni|fi|al-lahi|waqad|hadani|wala|akhafu|ma|tush'rikuna|bihi|illa|an|yashaa|rabbi|shayan|wasi'a|rabbi|kulla|shayin|il'man|afala|tatadhakkaruna","e": "۟/٨٠/."},"81": {"p": 137,"j": 7,"h": 55,"m": 2,"r": 110,"i": "وَكَیْفَ|اَخَافُ|مَاۤ|اَشْرَكْتُمْ|وَلَا|تَخَافُوْنَ|اَنَّكُمْ|اَشْرَكْتُمْ|بِاللّٰهِ|مَا|لَمْ|یُنَزِّلْ|بِهٖ|عَلَیْكُمْ|سُلْطٰنًا ؕ—|فَاَیُّ|الْفَرِیْقَیْنِ|اَحَقُّ|بِالْاَمْنِ ۚ—|اِنْ|كُنْتُمْ|تَعْلَمُوْنَ","u": "وَكَيۡفَ|أَخَافُ|مَآ|أَشۡرَكۡتُمۡ|وَلَا|تَخَافُونَ|أَنَّكُمۡ|أَشۡرَكۡتُم|بِٱللَّهِ|مَا|لَمۡ|يُنَزِّلۡ|بِهِۦ|عَلَيۡكُمۡ|سُلۡطَٰنٗاۚ|فَأَيُّ|ٱلۡفَرِيقَيۡنِ|أَحَقُّ|بِٱلۡأَمۡنِۖ|إِن|كُنتُمۡ|تَعۡلَمُونَ","t": "wakayfa|akhafu|ma|ashraktum|wala|takhafuna|annakum|ashraktum|bil-lahi|ma|lam|yunazzil|bihi|alaykum|sul'tanan|fa-ayyu|al-fariqayni|ahaqqu|bil-amni|in|kuntum|ta'lamuna","e": "۟ۘ/٨١/."},"82": {"p": 138,"j": 7,"h": 55,"m": 2,"r": 110,"i": "اَلَّذِیْنَ|اٰمَنُوْا|وَلَمْ|یَلْبِسُوْۤا|اِیْمَانَهُمْ|بِظُلْمٍ|اُولٰٓىِٕكَ|لَهُمُ|الْاَمْنُ|وَهُمْ|مُّهْتَدُوْنَ","u": "ٱلَّذِينَ|ءَامَنُواْ|وَلَمۡ|يَلۡبِسُوٓاْ|إِيمَٰنَهُم|بِظُلۡمٍ|أُوْلَٰٓئِكَ|لَهُمُ|ٱلۡأَمۡنُ|وَهُم|مُّهۡتَدُونَ","t": "alladhina|amanu|walam|yalbisu|imanahum|bizul'min|ulaika|lahumu|al-amnu|wahum|muh'taduna","e": "۟۠/٨٢/."},"83": {"p": 138,"j": 7,"h": 55,"m": 2,"r": 111,"i": "وَتِلْكَ|حُجَّتُنَاۤ|اٰتَیْنٰهَاۤ|اِبْرٰهِیْمَ|عَلٰی|قَوْمِهٖ ؕ—|نَرْفَعُ|دَرَجٰتٍ|مَّنْ|نَّشَآءُ ؕ—|اِنَّ|رَبَّكَ|حَكِیْمٌ|عَلِیْمٌ","u": "وَتِلۡكَ|حُجَّتُنَآ|ءَاتَيۡنَٰهَآ|إِبۡرَٰهِيمَ|عَلَىٰ|قَوۡمِهِۦۚ|نَرۡفَعُ|دَرَجَٰتٖ|مَّن|نَّشَآءُۗ|إِنَّ|رَبَّكَ|حَكِيمٌ|عَلِيمٞ","t": "watil'ka|hujjatuna|ataynaha|ib'rahima|ala|qawmihi|narfa'u|darajatin|man|nashau|inna|rabbaka|hakimun|alimun","e": "۟/٨٣/."},"84": {"p": 138,"j": 7,"h": 55,"m": 2,"r": 111,"i": "وَوَهَبْنَا|لَهٗۤ|اِسْحٰقَ|وَیَعْقُوْبَ ؕ—|كُلًّا|هَدَیْنَا ۚ—|وَنُوْحًا|هَدَیْنَا|مِنْ|قَبْلُ|وَمِنْ|ذُرِّیَّتِهٖ|دَاوٗدَ|وَسُلَیْمٰنَ|وَاَیُّوْبَ|وَیُوْسُفَ|وَمُوْسٰی|وَهٰرُوْنَ ؕ—|وَكَذٰلِكَ|نَجْزِی|الْمُحْسِنِیْنَ","u": "وَوَهَبۡنَا|لَهُۥٓ|إِسۡحَٰقَ|وَيَعۡقُوبَۚ|كُلًّا|هَدَيۡنَاۚ|وَنُوحًا|هَدَيۡنَا|مِن|قَبۡلُۖ|وَمِن|ذُرِّيَّتِهِۦ|دَاوُۥدَ|وَسُلَيۡمَٰنَ|وَأَيُّوبَ|وَيُوسُفَ|وَمُوسَىٰ|وَهَٰرُونَۚ|وَكَذَٰلِكَ|نَجۡزِي|ٱلۡمُحۡسِنِينَ","t": "wawahabna|lahu|is'haqa|waya'quba|kullan|hadayna|wanuhan|hadayna|min|qablu|wamin|dhurriyyatihi|dawuda|wasulaymana|wa-ayyuba|wayusufa|wamusa|waharuna|wakadhalika|najzi|al-muh'sinina","e": "۟ۙ/٨٤/."},"85": {"p": 138,"j": 7,"h": 55,"m": 2,"r": 111,"i": "وَزَكَرِیَّا|وَیَحْیٰی|وَعِیْسٰی|وَاِلْیَاسَ ؕ—|كُلٌّ|مِّنَ|الصّٰلِحِیْنَ","u": "وَزَكَرِيَّا|وَيَحۡيَىٰ|وَعِيسَىٰ|وَإِلۡيَاسَۖ|كُلّٞ|مِّنَ|ٱلصَّٰلِحِينَ","t": "wazakariyya|wayahya|wa'isa|wa-il'yasa|kullun|mina|al-salihina","e": "۟ۙ/٨٥/."},"86": {"p": 138,"j": 7,"h": 55,"m": 2,"r": 111,"i": "وَاِسْمٰعِیْلَ|وَالْیَسَعَ|وَیُوْنُسَ|وَلُوْطًا ؕ—|وَكُلًّا|فَضَّلْنَا|عَلَی|الْعٰلَمِیْنَ","u": "وَإِسۡمَٰعِيلَ|وَٱلۡيَسَعَ|وَيُونُسَ|وَلُوطٗاۚ|وَكُلّٗا|فَضَّلۡنَا|عَلَى|ٱلۡعَٰلَمِينَ","t": "wa-is'ma'ila|wal-yasa'a|wayunusa|walutan|wakullan|faddalna|ala|al-'alamina","e": "۟ۙ/٨٦/."},"87": {"p": 138,"j": 7,"h": 55,"m": 2,"r": 111,"i": "وَمِنْ|اٰبَآىِٕهِمْ|وَذُرِّیّٰتِهِمْ|وَاِخْوَانِهِمْ ۚ—|وَاجْتَبَیْنٰهُمْ|وَهَدَیْنٰهُمْ|اِلٰی|صِرَاطٍ|مُّسْتَقِیْمٍ","u": "وَمِنۡ|ءَابَآئِهِمۡ|وَذُرِّيَّٰتِهِمۡ|وَإِخۡوَٰنِهِمۡۖ|وَٱجۡتَبَيۡنَٰهُمۡ|وَهَدَيۡنَٰهُمۡ|إِلَىٰ|صِرَٰطٖ|مُّسۡتَقِيمٖ","t": "wamin|abaihim|wadhurriyyatihim|wa-ikh'wanihim|wa-ij'tabaynahum|wahadaynahum|ila|siratin|mus'taqimin","e": "۟/٨٧/."},"88": {"p": 138,"j": 7,"h": 55,"m": 2,"r": 111,"i": "ذٰلِكَ|هُدَی|اللّٰهِ|یَهْدِیْ|بِهٖ|مَنْ|یَّشَآءُ|مِنْ|عِبَادِهٖ ؕ—|وَلَوْ|اَشْرَكُوْا|لَحَبِطَ|عَنْهُمْ|مَّا|كَانُوْا|یَعْمَلُوْنَ","u": "ذَٰلِكَ|هُدَى|ٱللَّهِ|يَهۡدِي|بِهِۦ|مَن|يَشَآءُ|مِنۡ|عِبَادِهِۦۚ|وَلَوۡ|أَشۡرَكُواْ|لَحَبِطَ|عَنۡهُم|مَّا|كَانُواْ|يَعۡمَلُونَ","t": "dhalika|huda|al-lahi|yahdi|bihi|man|yashau|min|ibadihi|walaw|ashraku|lahabita|anhum|ma|kanu|ya'maluna","e": "۟/٨٨/."},"89": {"p": 138,"j": 7,"h": 55,"m": 2,"r": 111,"i": "اُولٰٓىِٕكَ|الَّذِیْنَ|اٰتَیْنٰهُمُ|الْكِتٰبَ|وَالْحُكْمَ|وَالنُّبُوَّةَ ۚ—|فَاِنْ|یَّكْفُرْ|بِهَا|هٰۤؤُلَآءِ|فَقَدْ|وَكَّلْنَا|بِهَا|قَوْمًا|لَّیْسُوْا|بِهَا|بِكٰفِرِیْنَ","u": "أُوْلَٰٓئِكَ|ٱلَّذِينَ|ءَاتَيۡنَٰهُمُ|ٱلۡكِتَٰبَ|وَٱلۡحُكۡمَ|وَٱلنُّبُوَّةَۚ|فَإِن|يَكۡفُرۡ|بِهَا|هَٰٓؤُلَآءِ|فَقَدۡ|وَكَّلۡنَا|بِهَا|قَوۡمٗا|لَّيۡسُواْ|بِهَا|بِكَٰفِرِينَ","t": "ulaika|alladhina|ataynahumu|al-kitaba|wal-huk'ma|wal-nubuwata|fa-in|yakfur|biha|haulai|faqad|wakkalna|biha|qawman|laysu|biha|bikafirina","e": "۟/٨٩/."},"90": {"p": 138,"j": 7,"h": 55,"m": 2,"r": 111,"i": "اُولٰٓىِٕكَ|الَّذِیْنَ|هَدَی|اللّٰهُ|فَبِهُدٰىهُمُ|اقْتَدِهْ ؕ—|قُلْ|لَّاۤ|اَسْـَٔلُكُمْ|عَلَیْهِ|اَجْرًا ؕ—|اِنْ|هُوَ|اِلَّا|ذِكْرٰی|لِلْعٰلَمِیْنَ","u": "أُوْلَٰٓئِكَ|ٱلَّذِينَ|هَدَى|ٱللَّهُۖ|فَبِهُدَىٰهُمُ|ٱقۡتَدِهۡۗ|قُل|لَّآ|أَسۡـَٔلُكُمۡ|عَلَيۡهِ|أَجۡرًاۖ|إِنۡ|هُوَ|إِلَّا|ذِكۡرَىٰ|لِلۡعَٰلَمِينَ","t": "ulaika|alladhina|hada|al-lahu|fabihudahumu|iq'tadih|qul|la|asalukum|alayhi|ajran|in|huwa|illa|dhik'ra|lil'alamina","e": "۟۠/٩٠/."},"91": {"p": 139,"j": 7,"h": 55,"m": 2,"r": 112,"i": "وَمَا|قَدَرُوا|اللّٰهَ|حَقَّ|قَدْرِهٖۤ|اِذْ|قَالُوْا|مَاۤ|اَنْزَلَ|اللّٰهُ|عَلٰی|بَشَرٍ|مِّنْ|شَیْءٍ ؕ—|قُلْ|مَنْ|اَنْزَلَ|الْكِتٰبَ|الَّذِیْ|جَآءَ|بِهٖ|مُوْسٰی|نُوْرًا|وَّهُدًی|لِّلنَّاسِ|تَجْعَلُوْنَهٗ|قَرَاطِیْسَ|تُبْدُوْنَهَا|وَتُخْفُوْنَ|كَثِیْرًا ۚ—|وَعُلِّمْتُمْ|مَّا|لَمْ|تَعْلَمُوْۤا|اَنْتُمْ|وَلَاۤ|اٰبَآؤُكُمْ ؕ—|قُلِ|اللّٰهُ ۙ—|ثُمَّ|ذَرْهُمْ|فِیْ|خَوْضِهِمْ|یَلْعَبُوْنَ","u": "وَمَا|قَدَرُواْ|ٱللَّهَ|حَقَّ|قَدۡرِهِۦٓ|إِذۡ|قَالُواْ|مَآ|أَنزَلَ|ٱللَّهُ|عَلَىٰ|بَشَرٖ|مِّن|شَيۡءٖۗ|قُلۡ|مَنۡ|أَنزَلَ|ٱلۡكِتَٰبَ|ٱلَّذِي|جَآءَ|بِهِۦ|مُوسَىٰ|نُورٗا|وَهُدٗى|لِّلنَّاسِۖ|تَجۡعَلُونَهُۥ|قَرَاطِيسَ|تُبۡدُونَهَا|وَتُخۡفُونَ|كَثِيرٗاۖ|وَعُلِّمۡتُم|مَّا|لَمۡ|تَعۡلَمُوٓاْ|أَنتُمۡ|وَلَآ|ءَابَآؤُكُمۡۖ|قُلِ|ٱللَّهُۖ|ثُمَّ|ذَرۡهُمۡ|فِي|خَوۡضِهِمۡ|يَلۡعَبُونَ","t": "wama|qadaru|al-laha|haqqa|qadrihi|idh|qalu|ma|anzala|al-lahu|ala|basharin|min|shayin|qul|man|anzala|al-kitaba|alladhi|jaa|bihi|musa|nuran|wahudan|lilnnasi|taj'alunahu|qaratisa|tub'dunaha|watukh'funa|kathiran|wa'ullim'tum|ma|lam|ta'lamu|antum|wala|abaukum|quli|al-lahu|thumma|dharhum|fi|khawdihim|yal'abuna","e": "۟/٩١/."},"92": {"p": 139,"j": 7,"h": 55,"m": 2,"r": 112,"i": "وَهٰذَا|كِتٰبٌ|اَنْزَلْنٰهُ|مُبٰرَكٌ|مُّصَدِّقُ|الَّذِیْ|بَیْنَ|یَدَیْهِ|وَلِتُنْذِرَ|اُمَّ|الْقُرٰی|وَمَنْ|حَوْلَهَا ؕ—|وَالَّذِیْنَ|یُؤْمِنُوْنَ|بِالْاٰخِرَةِ|یُؤْمِنُوْنَ|بِهٖ|وَهُمْ|عَلٰی|صَلَاتِهِمْ|یُحَافِظُوْنَ","u": "وَهَٰذَا|كِتَٰبٌ|أَنزَلۡنَٰهُ|مُبَارَكٞ|مُّصَدِّقُ|ٱلَّذِي|بَيۡنَ|يَدَيۡهِ|وَلِتُنذِرَ|أُمَّ|ٱلۡقُرَىٰ|وَمَنۡ|حَوۡلَهَاۚ|وَٱلَّذِينَ|يُؤۡمِنُونَ|بِٱلۡأٓخِرَةِ|يُؤۡمِنُونَ|بِهِۦۖ|وَهُمۡ|عَلَىٰ|صَلَاتِهِمۡ|يُحَافِظُونَ","t": "wahadha|kitabun|anzalnahu|mubarakun|musaddiqu|alladhi|bayna|yadayhi|walitundhira|umma|al-qura|waman|hawlaha|wa-alladhina|yu'minuna|bil-akhirati|yu'minuna|bihi|wahum|ala|salatihim|yuhafizuna","e": "۟/٩٢/."},"93": {"p": 139,"j": 7,"h": 55,"m": 2,"r": 112,"i": "وَمَنْ|اَظْلَمُ|مِمَّنِ|افْتَرٰی|عَلَی|اللّٰهِ|كَذِبًا|اَوْ|قَالَ|اُوْحِیَ|اِلَیَّ|وَلَمْ|یُوْحَ|اِلَیْهِ|شَیْءٌ|وَّمَنْ|قَالَ|سَاُنْزِلُ|مِثْلَ|مَاۤ|اَنْزَلَ|اللّٰهُ ؕ—|وَلَوْ|تَرٰۤی|اِذِ|الظّٰلِمُوْنَ|فِیْ|غَمَرٰتِ|الْمَوْتِ|وَالْمَلٰٓىِٕكَةُ|بَاسِطُوْۤا|اَیْدِیْهِمْ ۚ—|اَخْرِجُوْۤا|اَنْفُسَكُمْ ؕ—|اَلْیَوْمَ|تُجْزَوْنَ|عَذَابَ|الْهُوْنِ|بِمَا|كُنْتُمْ|تَقُوْلُوْنَ|عَلَی|اللّٰهِ|غَیْرَ|الْحَقِّ|وَكُنْتُمْ|عَنْ|اٰیٰتِهٖ|تَسْتَكْبِرُوْنَ","u": "وَمَنۡ|أَظۡلَمُ|مِمَّنِ|ٱفۡتَرَىٰ|عَلَى|ٱللَّهِ|كَذِبًا|أَوۡ|قَالَ|أُوحِيَ|إِلَيَّ|وَلَمۡ|يُوحَ|إِلَيۡهِ|شَيۡءٞ|وَمَن|قَالَ|سَأُنزِلُ|مِثۡلَ|مَآ|أَنزَلَ|ٱللَّهُۗ|وَلَوۡ|تَرَىٰٓ|إِذِ|ٱلظَّٰلِمُونَ|فِي|غَمَرَٰتِ|ٱلۡمَوۡتِ|وَٱلۡمَلَٰٓئِكَةُ|بَاسِطُوٓاْ|أَيۡدِيهِمۡ|أَخۡرِجُوٓاْ|أَنفُسَكُمُۖ|ٱلۡيَوۡمَ|تُجۡزَوۡنَ|عَذَابَ|ٱلۡهُونِ|بِمَا|كُنتُمۡ|تَقُولُونَ|عَلَى|ٱللَّهِ|غَيۡرَ|ٱلۡحَقِّ|وَكُنتُمۡ|عَنۡ|ءَايَٰتِهِۦ|تَسۡتَكۡبِرُونَ","t": "waman|azlamu|mimmani|if'tara|ala|al-lahi|kadhiban|aw|qala|uhiya|ilayya|walam|yuha|ilayhi|shayon|waman|qala|sa-unzilu|mith'la|ma|anzala|al-lahu|walaw|tara|idhi|al-zalimuna|fi|ghamarati|al-mawti|wal-malaikatu|basitu|aydihim|akhriju|anfusakumu|al-yawma|tuj'zawna|adhaba|al-huni|bima|kuntum|taquluna|ala|al-lahi|ghayra|al-haqi|wakuntum|an|ayatihi|tastakbiruna","e": "۟/٩٣/."},"94": {"p": 139,"j": 7,"h": 55,"m": 2,"r": 112,"i": "وَلَقَدْ|جِئْتُمُوْنَا|فُرَادٰی|كَمَا|خَلَقْنٰكُمْ|اَوَّلَ|مَرَّةٍ|وَّتَرَكْتُمْ|مَّا|خَوَّلْنٰكُمْ|وَرَآءَ|ظُهُوْرِكُمْ ۚ—|وَمَا|نَرٰی|مَعَكُمْ|شُفَعَآءَكُمُ|الَّذِیْنَ|زَعَمْتُمْ|اَنَّهُمْ|فِیْكُمْ|شُرَكٰٓؤُا ؕ—|لَقَدْ|تَّقَطَّعَ|بَیْنَكُمْ|وَضَلَّ|عَنْكُمْ|مَّا|كُنْتُمْ|تَزْعُمُوْنَ","u": "وَلَقَدۡ|جِئۡتُمُونَا|فُرَٰدَىٰ|كَمَا|خَلَقۡنَٰكُمۡ|أَوَّلَ|مَرَّةٖ|وَتَرَكۡتُم|مَّا|خَوَّلۡنَٰكُمۡ|وَرَآءَ|ظُهُورِكُمۡۖ|وَمَا|نَرَىٰ|مَعَكُمۡ|شُفَعَآءَكُمُ|ٱلَّذِينَ|زَعَمۡتُمۡ|أَنَّهُمۡ|فِيكُمۡ|شُرَكَٰٓؤُاْۚ|لَقَد|تَّقَطَّعَ|بَيۡنَكُمۡ|وَضَلَّ|عَنكُم|مَّا|كُنتُمۡ|تَزۡعُمُونَ","t": "walaqad|ji'tumuna|furada|kama|khalaqnakum|awwala|marratin|wataraktum|ma|khawwalnakum|waraa|zuhurikum|wama|nara|ma'akum|shufa'aakumu|alladhina|za'amtum|annahum|fikum|shurakau|laqad|taqatta'a|baynakum|wadalla|ankum|ma|kuntum|taz'umuna","e": "۟۠/٩٤/."},"95": {"p": 140,"j": 7,"h": 56,"m": 2,"r": 113,"i": "اِنَّ|اللّٰهَ|فَالِقُ|الْحَبِّ|وَالنَّوٰی ؕ—|یُخْرِجُ|الْحَیَّ|مِنَ|الْمَیِّتِ|وَمُخْرِجُ|الْمَیِّتِ|مِنَ|الْحَیِّ ؕ—|ذٰلِكُمُ|اللّٰهُ|فَاَنّٰی|تُؤْفَكُوْنَ","u": "۞إِنَّ|ٱللَّهَ|فَالِقُ|ٱلۡحَبِّ|وَٱلنَّوَىٰۖ|يُخۡرِجُ|ٱلۡحَيَّ|مِنَ|ٱلۡمَيِّتِ|وَمُخۡرِجُ|ٱلۡمَيِّتِ|مِنَ|ٱلۡحَيِّۚ|ذَٰلِكُمُ|ٱللَّهُۖ|فَأَنَّىٰ|تُؤۡفَكُونَ","t": "inna|al-laha|faliqu|al-habi|wal-nawa|yukh'riju|al-haya|mina|al-mayiti|wamukh'riju|al-mayiti|mina|al-hayi|dhalikumu|al-lahu|fa-anna|tu'fakuna","e": "۟/٩٥/."},"96": {"p": 140,"j": 7,"h": 56,"m": 2,"r": 113,"i": "فَالِقُ|الْاِصْبَاحِ ۚ—|وَجَعَلَ|الَّیْلَ|سَكَنًا|وَّالشَّمْسَ|وَالْقَمَرَ|حُسْبَانًا ؕ—|ذٰلِكَ|تَقْدِیْرُ|الْعَزِیْزِ|الْعَلِیْمِ","u": "فَالِقُ|ٱلۡإِصۡبَاحِ|وَجَعَلَ|ٱلَّيۡلَ|سَكَنٗا|وَٱلشَّمۡسَ|وَٱلۡقَمَرَ|حُسۡبَانٗاۚ|ذَٰلِكَ|تَقۡدِيرُ|ٱلۡعَزِيزِ|ٱلۡعَلِيمِ","t": "faliqu|al-is'bahi|waja'ala|al-layla|sakanan|wal-shamsa|wal-qamara|hus'banan|dhalika|taqdiru|al-'azizi|al-'alimi","e": "۟/٩٦/."},"97": {"p": 140,"j": 7,"h": 56,"m": 2,"r": 113,"i": "وَهُوَ|الَّذِیْ|جَعَلَ|لَكُمُ|النُّجُوْمَ|لِتَهْتَدُوْا|بِهَا|فِیْ|ظُلُمٰتِ|الْبَرِّ|وَالْبَحْرِ ؕ—|قَدْ|فَصَّلْنَا|الْاٰیٰتِ|لِقَوْمٍ|یَّعْلَمُوْنَ","u": "وَهُوَ|ٱلَّذِي|جَعَلَ|لَكُمُ|ٱلنُّجُومَ|لِتَهۡتَدُواْ|بِهَا|فِي|ظُلُمَٰتِ|ٱلۡبَرِّ|وَٱلۡبَحۡرِۗ|قَدۡ|فَصَّلۡنَا|ٱلۡأٓيَٰتِ|لِقَوۡمٖ|يَعۡلَمُونَ","t": "wahuwa|alladhi|ja'ala|lakumu|al-nujuma|litahtadu|biha|fi|zulumati|al-bari|wal-bahri|qad|fassalna|al-ayati|liqawmin|ya'lamuna","e": "۟/٩٧/."},"98": {"p": 140,"j": 7,"h": 56,"m": 2,"r": 113,"i": "وَهُوَ|الَّذِیْۤ|اَنْشَاَكُمْ|مِّنْ|نَّفْسٍ|وَّاحِدَةٍ|فَمُسْتَقَرٌّ|وَّمُسْتَوْدَعٌ ؕ—|قَدْ|فَصَّلْنَا|الْاٰیٰتِ|لِقَوْمٍ|یَّفْقَهُوْنَ","u": "وَهُوَ|ٱلَّذِيٓ|أَنشَأَكُم|مِّن|نَّفۡسٖ|وَٰحِدَةٖ|فَمُسۡتَقَرّٞ|وَمُسۡتَوۡدَعٞۗ|قَدۡ|فَصَّلۡنَا|ٱلۡأٓيَٰتِ|لِقَوۡمٖ|يَفۡقَهُونَ","t": "wahuwa|alladhi|ansha-akum|min|nafsin|wahidatin|famus'taqarrun|wamus'tawda'un|qad|fassalna|al-ayati|liqawmin|yafqahuna","e": "۟/٩٨/."},"99": {"p": 140,"j": 7,"h": 56,"m": 2,"r": 113,"i": "وَهُوَ|الَّذِیْۤ|اَنْزَلَ|مِنَ|السَّمَآءِ|مَآءً ۚ—|فَاَخْرَجْنَا|بِهٖ|نَبَاتَ|كُلِّ|شَیْءٍ|فَاَخْرَجْنَا|مِنْهُ|خَضِرًا|نُّخْرِجُ|مِنْهُ|حَبًّا|مُّتَرَاكِبًا ۚ—|وَمِنَ|النَّخْلِ|مِنْ|طَلْعِهَا|قِنْوَانٌ|دَانِیَةٌ ۙ—|وَّجَنّٰتٍ|مِّنْ|اَعْنَابٍ|وَّالزَّیْتُوْنَ|وَالرُّمَّانَ|مُشْتَبِهًا|وَّغَیْرَ|مُتَشَابِهٍ ؕ—|اُنْظُرُوْۤا|اِلٰی|ثَمَرِهٖۤ|اِذَاۤ|اَثْمَرَ|وَیَنْعِهٖ ؕ—|اِنَّ|فِیْ|ذٰلِكُمْ|لَاٰیٰتٍ|لِّقَوْمٍ|یُّؤْمِنُوْنَ","u": "وَهُوَ|ٱلَّذِيٓ|أَنزَلَ|مِنَ|ٱلسَّمَآءِ|مَآءٗ|فَأَخۡرَجۡنَا|بِهِۦ|نَبَاتَ|كُلِّ|شَيۡءٖ|فَأَخۡرَجۡنَا|مِنۡهُ|خَضِرٗا|نُّخۡرِجُ|مِنۡهُ|حَبّٗا|مُّتَرَاكِبٗا|وَمِنَ|ٱلنَّخۡلِ|مِن|طَلۡعِهَا|قِنۡوَانٞ|دَانِيَةٞ|وَجَنَّٰتٖ|مِّنۡ|أَعۡنَابٖ|وَٱلزَّيۡتُونَ|وَٱلرُّمَّانَ|مُشۡتَبِهٗا|وَغَيۡرَ|مُتَشَٰبِهٍۗ|ٱنظُرُوٓاْ|إِلَىٰ|ثَمَرِهِۦٓ|إِذَآ|أَثۡمَرَ|وَيَنۡعِهِۦٓۚ|إِنَّ|فِي|ذَٰلِكُمۡ|لَأٓيَٰتٖ|لِّقَوۡمٖ|يُؤۡمِنُونَ","t": "wahuwa|alladhi|anzala|mina|al-samai|maan|fa-akhrajna|bihi|nabata|kulli|shayin|fa-akhrajna|min'hu|khadiran|nukh'riju|min'hu|habban|mutarakiban|wamina|al-nakhli|min|tal'iha|qin'wanun|daniyatun|wajannatin|min|a'nabin|wal-zaytuna|wal-rumana|mush'tabihan|waghayra|mutashabihin|unzuru|ila|thamarihi|idha|athmara|wayan'ihi|inna|fi|dhalikum|laayatin|liqawmin|yu'minuna","e": "۟/٩٩/."},"100": {"p": 140,"j": 7,"h": 56,"m": 2,"r": 113,"i": "وَجَعَلُوْا|لِلّٰهِ|شُرَكَآءَ|الْجِنَّ|وَخَلَقَهُمْ|وَخَرَقُوْا|لَهٗ|بَنِیْنَ|وَبَنٰتٍ|بِغَیْرِ|عِلْمٍ ؕ—|سُبْحٰنَهٗ|وَتَعٰلٰی|عَمَّا|یَصِفُوْنَ","u": "وَجَعَلُواْ|لِلَّهِ|شُرَكَآءَ|ٱلۡجِنَّ|وَخَلَقَهُمۡۖ|وَخَرَقُواْ|لَهُۥ|بَنِينَ|وَبَنَٰتِۭ|بِغَيۡرِ|عِلۡمٖۚ|سُبۡحَٰنَهُۥ|وَتَعَٰلَىٰ|عَمَّا|يَصِفُونَ","t": "waja'alu|lillahi|shurakaa|al-jina|wakhalaqahum|wakharaqu|lahu|banina|wabanatin|bighayri|il'min|sub'hanahu|wata'ala|amma|yasifuna","e": "۟۠/١٠٠/."},"101": {"p": 140,"j": 7,"h": 56,"m": 2,"r": 114,"i": "بَدِیْعُ|السَّمٰوٰتِ|وَالْاَرْضِ ؕ—|اَنّٰی|یَكُوْنُ|لَهٗ|وَلَدٌ|وَّلَمْ|تَكُنْ|لَّهٗ|صَاحِبَةٌ ؕ—|وَخَلَقَ|كُلَّ|شَیْءٍ ۚ—|وَهُوَ|بِكُلِّ|شَیْءٍ|عَلِیْمٌ","u": "بَدِيعُ|ٱلسَّمَٰوَٰتِ|وَٱلۡأَرۡضِۖ|أَنَّىٰ|يَكُونُ|لَهُۥ|وَلَدٞ|وَلَمۡ|تَكُن|لَّهُۥ|صَٰحِبَةٞۖ|وَخَلَقَ|كُلَّ|شَيۡءٖۖ|وَهُوَ|بِكُلِّ|شَيۡءٍ|عَلِيمٞ","t": "badi'u|al-samawati|wal-ardi|anna|yakunu|lahu|waladun|walam|takun|lahu|sahibatun|wakhalaqa|kulla|shayin|wahuwa|bikulli|shayin|alimun","e": "۟/١٠١/."},"102": {"p": 141,"j": 7,"h": 56,"m": 2,"r": 114,"i": "ذٰلِكُمُ|اللّٰهُ|رَبُّكُمْ ۚ—|لَاۤ|اِلٰهَ|اِلَّا|هُوَ ۚ—|خَالِقُ|كُلِّ|شَیْءٍ|فَاعْبُدُوْهُ ۚ—|وَهُوَ|عَلٰی|كُلِّ|شَیْءٍ|وَّكِیْلٌ","u": "ذَٰلِكُمُ|ٱللَّهُ|رَبُّكُمۡۖ|لَآ|إِلَٰهَ|إِلَّا|هُوَۖ|خَٰلِقُ|كُلِّ|شَيۡءٖ|فَٱعۡبُدُوهُۚ|وَهُوَ|عَلَىٰ|كُلِّ|شَيۡءٖ|وَكِيلٞ","t": "dhalikumu|al-lahu|rabbukum|la|ilaha|illa|huwa|khaliqu|kulli|shayin|fa-u'buduhu|wahuwa|ala|kulli|shayin|wakilun","e": "۟/١٠٢/."},"103": {"p": 141,"j": 7,"h": 56,"m": 2,"r": 114,"i": "لَا|تُدْرِكُهُ|الْاَبْصَارُ ؗ—|وَهُوَ|یُدْرِكُ|الْاَبْصَارَ ۚ—|وَهُوَ|اللَّطِیْفُ|الْخَبِیْرُ","u": "لَّا|تُدۡرِكُهُ|ٱلۡأَبۡصَٰرُ|وَهُوَ|يُدۡرِكُ|ٱلۡأَبۡصَٰرَۖ|وَهُوَ|ٱللَّطِيفُ|ٱلۡخَبِيرُ","t": "la|tud'rikuhu|al-absaru|wahuwa|yud'riku|al-absara|wahuwa|al-latifu|al-khabiru","e": "۟/١٠٣/."},"104": {"p": 141,"j": 7,"h": 56,"m": 2,"r": 114,"i": "قَدْ|جَآءَكُمْ|بَصَآىِٕرُ|مِنْ|رَّبِّكُمْ ۚ—|فَمَنْ|اَبْصَرَ|فَلِنَفْسِهٖ ۚ—|وَمَنْ|عَمِیَ|فَعَلَیْهَا ؕ—|وَمَاۤ|اَنَا|عَلَیْكُمْ|بِحَفِیْظٍ","u": "قَدۡ|جَآءَكُم|بَصَآئِرُ|مِن|رَّبِّكُمۡۖ|فَمَنۡ|أَبۡصَرَ|فَلِنَفۡسِهِۦۖ|وَمَنۡ|عَمِيَ|فَعَلَيۡهَاۚ|وَمَآ|أَنَا۠|عَلَيۡكُم|بِحَفِيظٖ","t": "qad|jaakum|basairu|min|rabbikum|faman|absara|falinafsihi|waman|amiya|fa'alayha|wama|ana|alaykum|bihafizin","e": "۟/١٠٤/."},"105": {"p": 141,"j": 7,"h": 56,"m": 2,"r": 114,"i": "وَكَذٰلِكَ|نُصَرِّفُ|الْاٰیٰتِ|وَلِیَقُوْلُوْا|دَرَسْتَ|وَلِنُبَیِّنَهٗ|لِقَوْمٍ|یَّعْلَمُوْنَ","u": "وَكَذَٰلِكَ|نُصَرِّفُ|ٱلۡأٓيَٰتِ|وَلِيَقُولُواْ|دَرَسۡتَ|وَلِنُبَيِّنَهُۥ|لِقَوۡمٖ|يَعۡلَمُونَ","t": "wakadhalika|nusarrifu|al-ayati|waliyaqulu|darasta|walinubayyinahu|liqawmin|ya'lamuna","e": "۟/١٠٥/."},"106": {"p": 141,"j": 7,"h": 56,"m": 2,"r": 114,"i": "اِتَّبِعْ|مَاۤ|اُوْحِیَ|اِلَیْكَ|مِنْ|رَّبِّكَ ۚ—|لَاۤ|اِلٰهَ|اِلَّا|هُوَ ۚ—|وَاَعْرِضْ|عَنِ|الْمُشْرِكِیْنَ","u": "ٱتَّبِعۡ|مَآ|أُوحِيَ|إِلَيۡكَ|مِن|رَّبِّكَۖ|لَآ|إِلَٰهَ|إِلَّا|هُوَۖ|وَأَعۡرِضۡ|عَنِ|ٱلۡمُشۡرِكِينَ","t": "ittabi'|ma|uhiya|ilayka|min|rabbika|la|ilaha|illa|huwa|wa-a'rid|ani|al-mush'rikina","e": "۟/١٠٦/."},"107": {"p": 141,"j": 7,"h": 56,"m": 2,"r": 114,"i": "وَلَوْ|شَآءَ|اللّٰهُ|مَاۤ|اَشْرَكُوْا ؕ—|وَمَا|جَعَلْنٰكَ|عَلَیْهِمْ|حَفِیْظًا ۚ—|وَمَاۤ|اَنْتَ|عَلَیْهِمْ|بِوَكِیْلٍ","u": "وَلَوۡ|شَآءَ|ٱللَّهُ|مَآ|أَشۡرَكُواْۗ|وَمَا|جَعَلۡنَٰكَ|عَلَيۡهِمۡ|حَفِيظٗاۖ|وَمَآ|أَنتَ|عَلَيۡهِم|بِوَكِيلٖ","t": "walaw|shaa|al-lahu|ma|ashraku|wama|ja'alnaka|alayhim|hafizan|wama|anta|alayhim|biwakilin","e": "۟/١٠٧/."},"108": {"p": 141,"j": 7,"h": 56,"m": 2,"r": 114,"i": "وَلَا|تَسُبُّوا|الَّذِیْنَ|یَدْعُوْنَ|مِنْ|دُوْنِ|اللّٰهِ|فَیَسُبُّوا|اللّٰهَ|عَدْوًا|بِغَیْرِ|عِلْمٍ ؕ—|كَذٰلِكَ|زَیَّنَّا|لِكُلِّ|اُمَّةٍ|عَمَلَهُمْ ۪—|ثُمَّ|اِلٰی|رَبِّهِمْ|مَّرْجِعُهُمْ|فَیُنَبِّئُهُمْ|بِمَا|كَانُوْا|یَعْمَلُوْنَ","u": "وَلَا|تَسُبُّواْ|ٱلَّذِينَ|يَدۡعُونَ|مِن|دُونِ|ٱللَّهِ|فَيَسُبُّواْ|ٱللَّهَ|عَدۡوَۢا|بِغَيۡرِ|عِلۡمٖۗ|كَذَٰلِكَ|زَيَّنَّا|لِكُلِّ|أُمَّةٍ|عَمَلَهُمۡ|ثُمَّ|إِلَىٰ|رَبِّهِم|مَّرۡجِعُهُمۡ|فَيُنَبِّئُهُم|بِمَا|كَانُواْ|يَعۡمَلُونَ","t": "wala|tasubbu|alladhina|yad'una|min|duni|al-lahi|fayasubbu|al-laha|adwan|bighayri|il'min|kadhalika|zayyanna|likulli|ummatin|amalahum|thumma|ila|rabbihim|marji'uhum|fayunabbi-uhum|bima|kanu|ya'maluna","e": "۟/١٠٨/."},"109": {"p": 141,"j": 7,"h": 56,"m": 2,"r": 114,"i": "وَاَقْسَمُوْا|بِاللّٰهِ|جَهْدَ|اَیْمَانِهِمْ|لَىِٕنْ|جَآءَتْهُمْ|اٰیَةٌ|لَّیُؤْمِنُنَّ|بِهَا ؕ—|قُلْ|اِنَّمَا|الْاٰیٰتُ|عِنْدَ|اللّٰهِ|وَمَا|یُشْعِرُكُمْ ۙ—|اَنَّهَاۤ|اِذَا|جَآءَتْ|لَا|یُؤْمِنُوْنَ","u": "وَأَقۡسَمُواْ|بِٱللَّهِ|جَهۡدَ|أَيۡمَٰنِهِمۡ|لَئِن|جَآءَتۡهُمۡ|ءَايَةٞ|لَّيُؤۡمِنُنَّ|بِهَاۚ|قُلۡ|إِنَّمَا|ٱلۡأٓيَٰتُ|عِندَ|ٱللَّهِۖ|وَمَا|يُشۡعِرُكُمۡ|أَنَّهَآ|إِذَا|جَآءَتۡ|لَا|يُؤۡمِنُونَ","t": "wa-aqsamu|bil-lahi|jahda|aymanihim|la-in|jaathum|ayatun|layu'minunna|biha|qul|innama|al-ayatu|inda|al-lahi|wama|yush'irukum|annaha|idha|jaat|la|yu'minuna","e": "۟/١٠٩/."},"110": {"p": 141,"j": 7,"h": 56,"m": 2,"r": 114,"i": "وَنُقَلِّبُ|اَفْـِٕدَتَهُمْ|وَاَبْصَارَهُمْ|كَمَا|لَمْ|یُؤْمِنُوْا|بِهٖۤ|اَوَّلَ|مَرَّةٍ|وَّنَذَرُهُمْ|فِیْ|طُغْیَانِهِمْ|یَعْمَهُوْنَ","u": "وَنُقَلِّبُ|أَفۡـِٔدَتَهُمۡ|وَأَبۡصَٰرَهُمۡ|كَمَا|لَمۡ|يُؤۡمِنُواْ|بِهِۦٓ|أَوَّلَ|مَرَّةٖ|وَنَذَرُهُمۡ|فِي|طُغۡيَٰنِهِمۡ|يَعۡمَهُونَ","t": "wanuqallibu|afidatahum|wa-absarahum|kama|lam|yu'minu|bihi|awwala|marratin|wanadharuhum|fi|tugh'yanihim|ya'mahuna","e": "۟۠/١١٠/."},"111": {"p": 142,"j": 8,"h": 57,"m": 2,"r": 115,"i": "وَلَوْ|اَنَّنَا|نَزَّلْنَاۤ|اِلَیْهِمُ|الْمَلٰٓىِٕكَةَ|وَكَلَّمَهُمُ|الْمَوْتٰی|وَحَشَرْنَا|عَلَیْهِمْ|كُلَّ|شَیْءٍ|قُبُلًا|مَّا|كَانُوْا|لِیُؤْمِنُوْۤا|اِلَّاۤ|اَنْ|یَّشَآءَ|اللّٰهُ|وَلٰكِنَّ|اَكْثَرَهُمْ|یَجْهَلُوْنَ","u": "۞وَلَوۡ|أَنَّنَا|نَزَّلۡنَآ|إِلَيۡهِمُ|ٱلۡمَلَٰٓئِكَةَ|وَكَلَّمَهُمُ|ٱلۡمَوۡتَىٰ|وَحَشَرۡنَا|عَلَيۡهِمۡ|كُلَّ|شَيۡءٖ|قُبُلٗا|مَّا|كَانُواْ|لِيُؤۡمِنُوٓاْ|إِلَّآ|أَن|يَشَآءَ|ٱللَّهُ|وَلَٰكِنَّ|أَكۡثَرَهُمۡ|يَجۡهَلُونَ","t": "walaw|annana|nazzalna|ilayhimu|al-malaikata|wakallamahumu|al-mawta|wahasharna|alayhim|kulla|shayin|qubulan|ma|kanu|liyu'minu|illa|an|yashaa|al-lahu|walakinna|aktharahum|yajhaluna","e": "۟/١١١/."},"112": {"p": 142,"j": 8,"h": 57,"m": 2,"r": 115,"i": "وَكَذٰلِكَ|جَعَلْنَا|لِكُلِّ|نَبِیٍّ|عَدُوًّا|شَیٰطِیْنَ|الْاِنْسِ|وَالْجِنِّ|یُوْحِیْ|بَعْضُهُمْ|اِلٰی|بَعْضٍ|زُخْرُفَ|الْقَوْلِ|غُرُوْرًا ؕ—|وَلَوْ|شَآءَ|رَبُّكَ|مَا|فَعَلُوْهُ|فَذَرْهُمْ|وَمَا|یَفْتَرُوْنَ","u": "وَكَذَٰلِكَ|جَعَلۡنَا|لِكُلِّ|نَبِيٍّ|عَدُوّٗا|شَيَٰطِينَ|ٱلۡإِنسِ|وَٱلۡجِنِّ|يُوحِي|بَعۡضُهُمۡ|إِلَىٰ|بَعۡضٖ|زُخۡرُفَ|ٱلۡقَوۡلِ|غُرُورٗاۚ|وَلَوۡ|شَآءَ|رَبُّكَ|مَا|فَعَلُوهُۖ|فَذَرۡهُمۡ|وَمَا|يَفۡتَرُونَ","t": "wakadhalika|ja'alna|likulli|nabiyyin|aduwwan|shayatina|al-insi|wal-jini|yuhi|ba'duhum|ila|ba'din|zukh'rufa|al-qawli|ghururan|walaw|shaa|rabbuka|ma|fa'aluhu|fadharhum|wama|yaftaruna","e": "۟/١١٢/."},"113": {"p": 142,"j": 8,"h": 57,"m": 2,"r": 115,"i": "وَلِتَصْغٰۤی|اِلَیْهِ|اَفْـِٕدَةُ|الَّذِیْنَ|لَا|یُؤْمِنُوْنَ|بِالْاٰخِرَةِ|وَلِیَرْضَوْهُ|وَلِیَقْتَرِفُوْا|مَا|هُمْ|مُّقْتَرِفُوْنَ","u": "وَلِتَصۡغَىٰٓ|إِلَيۡهِ|أَفۡـِٔدَةُ|ٱلَّذِينَ|لَا|يُؤۡمِنُونَ|بِٱلۡأٓخِرَةِ|وَلِيَرۡضَوۡهُ|وَلِيَقۡتَرِفُواْ|مَا|هُم|مُّقۡتَرِفُونَ","t": "walitasgha|ilayhi|afidatu|alladhina|la|yu'minuna|bil-akhirati|waliyardawhu|waliyaqtarifu|ma|hum|muq'tarifuna","e": "۟/١١٣/."},"114": {"p": 142,"j": 8,"h": 57,"m": 2,"r": 115,"i": "اَفَغَیْرَ|اللّٰهِ|اَبْتَغِیْ|حَكَمًا|وَّهُوَ|الَّذِیْۤ|اَنْزَلَ|اِلَیْكُمُ|الْكِتٰبَ|مُفَصَّلًا ؕ—|وَالَّذِیْنَ|اٰتَیْنٰهُمُ|الْكِتٰبَ|یَعْلَمُوْنَ|اَنَّهٗ|مُنَزَّلٌ|مِّنْ|رَّبِّكَ|بِالْحَقِّ|فَلَا|تَكُوْنَنَّ|مِنَ|الْمُمْتَرِیْنَ","u": "أَفَغَيۡرَ|ٱللَّهِ|أَبۡتَغِي|حَكَمٗا|وَهُوَ|ٱلَّذِيٓ|أَنزَلَ|إِلَيۡكُمُ|ٱلۡكِتَٰبَ|مُفَصَّلٗاۚ|وَٱلَّذِينَ|ءَاتَيۡنَٰهُمُ|ٱلۡكِتَٰبَ|يَعۡلَمُونَ|أَنَّهُۥ|مُنَزَّلٞ|مِّن|رَّبِّكَ|بِٱلۡحَقِّۖ|فَلَا|تَكُونَنَّ|مِنَ|ٱلۡمُمۡتَرِينَ","t": "afaghayra|al-lahi|abtaghi|hakaman|wahuwa|alladhi|anzala|ilaykumu|al-kitaba|mufassalan|wa-alladhina|ataynahumu|al-kitaba|ya'lamuna|annahu|munazzalun|min|rabbika|bil-haqi|fala|takunanna|mina|al-mum'tarina","e": "۟/١١٤/."},"115": {"p": 142,"j": 8,"h": 57,"m": 2,"r": 115,"i": "وَتَمَّتْ|كَلِمَتُ|رَبِّكَ|صِدْقًا|وَّعَدْلًا ؕ—|لَا|مُبَدِّلَ|لِكَلِمٰتِهٖ ۚ—|وَهُوَ|السَّمِیْعُ|الْعَلِیْمُ","u": "وَتَمَّتۡ|كَلِمَتُ|رَبِّكَ|صِدۡقٗا|وَعَدۡلٗاۚ|لَّا|مُبَدِّلَ|لِكَلِمَٰتِهِۦۚ|وَهُوَ|ٱلسَّمِيعُ|ٱلۡعَلِيمُ","t": "watammat|kalimatu|rabbika|sid'qan|wa'adlan|la|mubaddila|likalimatihi|wahuwa|al-sami'u|al-'alimu","e": "۟/١١٥/."},"116": {"p": 142,"j": 8,"h": 57,"m": 2,"r": 115,"i": "وَاِنْ|تُطِعْ|اَكْثَرَ|مَنْ|فِی|الْاَرْضِ|یُضِلُّوْكَ|عَنْ|سَبِیْلِ|اللّٰهِ ؕ—|اِنْ|یَّتَّبِعُوْنَ|اِلَّا|الظَّنَّ|وَاِنْ|هُمْ|اِلَّا|یَخْرُصُوْنَ","u": "وَإِن|تُطِعۡ|أَكۡثَرَ|مَن|فِي|ٱلۡأَرۡضِ|يُضِلُّوكَ|عَن|سَبِيلِ|ٱللَّهِۚ|إِن|يَتَّبِعُونَ|إِلَّا|ٱلظَّنَّ|وَإِنۡ|هُمۡ|إِلَّا|يَخۡرُصُونَ","t": "wa-in|tuti'|akthara|man|fi|al-ardi|yudilluka|an|sabili|al-lahi|in|yattabi'una|illa|al-zana|wa-in|hum|illa|yakhrusuna","e": "۟/١١٦/."},"117": {"p": 142,"j": 8,"h": 57,"m": 2,"r": 115,"i": "اِنَّ|رَبَّكَ|هُوَ|اَعْلَمُ|مَنْ|یَّضِلُّ|عَنْ|سَبِیْلِهٖ ۚ—|وَهُوَ|اَعْلَمُ|بِالْمُهْتَدِیْنَ","u": "إِنَّ|رَبَّكَ|هُوَ|أَعۡلَمُ|مَن|يَضِلُّ|عَن|سَبِيلِهِۦۖ|وَهُوَ|أَعۡلَمُ|بِٱلۡمُهۡتَدِينَ","t": "inna|rabbaka|huwa|a'lamu|man|yadillu|an|sabilihi|wahuwa|a'lamu|bil-muh'tadina","e": "۟/١١٧/."},"118": {"p": 142,"j": 8,"h": 57,"m": 2,"r": 115,"i": "فَكُلُوْا|مِمَّا|ذُكِرَ|اسْمُ|اللّٰهِ|عَلَیْهِ|اِنْ|كُنْتُمْ|بِاٰیٰتِهٖ|مُؤْمِنِیْنَ","u": "فَكُلُواْ|مِمَّا|ذُكِرَ|ٱسۡمُ|ٱللَّهِ|عَلَيۡهِ|إِن|كُنتُم|بِـَٔايَٰتِهِۦ|مُؤۡمِنِينَ","t": "fakulu|mimma|dhukira|us'mu|al-lahi|alayhi|in|kuntum|biayatihi|mu'minina","e": "۟/١١٨/."},"119": {"p": 143,"j": 8,"h": 57,"m": 2,"r": 115,"i": "وَمَا|لَكُمْ|اَلَّا|تَاْكُلُوْا|مِمَّا|ذُكِرَ|اسْمُ|اللّٰهِ|عَلَیْهِ|وَقَدْ|فَصَّلَ|لَكُمْ|مَّا|حَرَّمَ|عَلَیْكُمْ|اِلَّا|مَا|اضْطُرِرْتُمْ|اِلَیْهِ ؕ—|وَاِنَّ|كَثِیْرًا|لَّیُضِلُّوْنَ|بِاَهْوَآىِٕهِمْ|بِغَیْرِ|عِلْمٍ ؕ—|اِنَّ|رَبَّكَ|هُوَ|اَعْلَمُ|بِالْمُعْتَدِیْنَ","u": "وَمَا|لَكُمۡ|أَلَّا|تَأۡكُلُواْ|مِمَّا|ذُكِرَ|ٱسۡمُ|ٱللَّهِ|عَلَيۡهِ|وَقَدۡ|فَصَّلَ|لَكُم|مَّا|حَرَّمَ|عَلَيۡكُمۡ|إِلَّا|مَا|ٱضۡطُرِرۡتُمۡ|إِلَيۡهِۗ|وَإِنَّ|كَثِيرٗا|لَّيُضِلُّونَ|بِأَهۡوَآئِهِم|بِغَيۡرِ|عِلۡمٍۚ|إِنَّ|رَبَّكَ|هُوَ|أَعۡلَمُ|بِٱلۡمُعۡتَدِينَ","t": "wama|lakum|alla|takulu|mimma|dhukira|us'mu|al-lahi|alayhi|waqad|fassala|lakum|ma|harrama|alaykum|illa|ma|ud'turir'tum|ilayhi|wa-inna|kathiran|layudilluna|bi-ahwaihim|bighayri|il'min|inna|rabbaka|huwa|a'lamu|bil-mu'tadina","e": "۟/١١٩/."},"120": {"p": 143,"j": 8,"h": 57,"m": 2,"r": 115,"i": "وَذَرُوْا|ظَاهِرَ|الْاِثْمِ|وَبَاطِنَهٗ ؕ—|اِنَّ|الَّذِیْنَ|یَكْسِبُوْنَ|الْاِثْمَ|سَیُجْزَوْنَ|بِمَا|كَانُوْا|یَقْتَرِفُوْنَ","u": "وَذَرُواْ|ظَٰهِرَ|ٱلۡإِثۡمِ|وَبَاطِنَهُۥٓۚ|إِنَّ|ٱلَّذِينَ|يَكۡسِبُونَ|ٱلۡإِثۡمَ|سَيُجۡزَوۡنَ|بِمَا|كَانُواْ|يَقۡتَرِفُونَ","t": "wadharu|zahira|al-ith'mi|wabatinahu|inna|alladhina|yaksibuna|al-ith'ma|sayuj'zawna|bima|kanu|yaqtarifuna","e": "۟/١٢٠/."},"121": {"p": 143,"j": 8,"h": 57,"m": 2,"r": 115,"i": "وَلَا|تَاْكُلُوْا|مِمَّا|لَمْ|یُذْكَرِ|اسْمُ|اللّٰهِ|عَلَیْهِ|وَاِنَّهٗ|لَفِسْقٌ ؕ—|وَاِنَّ|الشَّیٰطِیْنَ|لَیُوْحُوْنَ|اِلٰۤی|اَوْلِیٰٓـِٕهِمْ|لِیُجَادِلُوْكُمْ ۚ—|وَاِنْ|اَطَعْتُمُوْهُمْ|اِنَّكُمْ|لَمُشْرِكُوْنَ","u": "وَلَا|تَأۡكُلُواْ|مِمَّا|لَمۡ|يُذۡكَرِ|ٱسۡمُ|ٱللَّهِ|عَلَيۡهِ|وَإِنَّهُۥ|لَفِسۡقٞۗ|وَإِنَّ|ٱلشَّيَٰطِينَ|لَيُوحُونَ|إِلَىٰٓ|أَوۡلِيَآئِهِمۡ|لِيُجَٰدِلُوكُمۡۖ|وَإِنۡ|أَطَعۡتُمُوهُمۡ|إِنَّكُمۡ|لَمُشۡرِكُونَ","t": "wala|takulu|mimma|lam|yudh'kari|us'mu|al-lahi|alayhi|wa-innahu|lafis'qun|wa-inna|al-shayatina|layuhuna|ila|awliyaihim|liyujadilukum|wa-in|ata'tumuhum|innakum|lamush'rikuna","e": "۟۠/١٢١/."},"122": {"p": 143,"j": 8,"h": 57,"m": 2,"r": 116,"i": "اَوَمَنْ|كَانَ|مَیْتًا|فَاَحْیَیْنٰهُ|وَجَعَلْنَا|لَهٗ|نُوْرًا|یَّمْشِیْ|بِهٖ|فِی|النَّاسِ|كَمَنْ|مَّثَلُهٗ|فِی|الظُّلُمٰتِ|لَیْسَ|بِخَارِجٍ|مِّنْهَا ؕ—|كَذٰلِكَ|زُیِّنَ|لِلْكٰفِرِیْنَ|مَا|كَانُوْا|یَعْمَلُوْنَ","u": "أَوَمَن|كَانَ|مَيۡتٗا|فَأَحۡيَيۡنَٰهُ|وَجَعَلۡنَا|لَهُۥ|نُورٗا|يَمۡشِي|بِهِۦ|فِي|ٱلنَّاسِ|كَمَن|مَّثَلُهُۥ|فِي|ٱلظُّلُمَٰتِ|لَيۡسَ|بِخَارِجٖ|مِّنۡهَاۚ|كَذَٰلِكَ|زُيِّنَ|لِلۡكَٰفِرِينَ|مَا|كَانُواْ|يَعۡمَلُونَ","t": "awaman|kana|maytan|fa-ahyaynahu|waja'alna|lahu|nuran|yamshi|bihi|fi|al-nasi|kaman|mathaluhu|fi|al-zulumati|laysa|bikharijin|min'ha|kadhalika|zuyyina|lil'kafirina|ma|kanu|ya'maluna","e": "۟/١٢٢/."},"123": {"p": 143,"j": 8,"h": 57,"m": 2,"r": 116,"i": "وَكَذٰلِكَ|جَعَلْنَا|فِیْ|كُلِّ|قَرْیَةٍ|اَكٰبِرَ|مُجْرِمِیْهَا|لِیَمْكُرُوْا|فِیْهَا ؕ—|وَمَا|یَمْكُرُوْنَ|اِلَّا|بِاَنْفُسِهِمْ|وَمَا|یَشْعُرُوْنَ","u": "وَكَذَٰلِكَ|جَعَلۡنَا|فِي|كُلِّ|قَرۡيَةٍ|أَكَٰبِرَ|مُجۡرِمِيهَا|لِيَمۡكُرُواْ|فِيهَاۖ|وَمَا|يَمۡكُرُونَ|إِلَّا|بِأَنفُسِهِمۡ|وَمَا|يَشۡعُرُونَ","t": "wakadhalika|ja'alna|fi|kulli|qaryatin|akabira|muj'rimiha|liyamkuru|fiha|wama|yamkuruna|illa|bi-anfusihim|wama|yash'uruna","e": "۟/١٢٣/."},"124": {"p": 143,"j": 8,"h": 57,"m": 2,"r": 116,"i": "وَاِذَا|جَآءَتْهُمْ|اٰیَةٌ|قَالُوْا|لَنْ|نُّؤْمِنَ|حَتّٰی|نُؤْتٰی|مِثْلَ|مَاۤ|اُوْتِیَ|رُسُلُ|اللّٰهِ ؔۘؕ—|اَللّٰهُ|اَعْلَمُ|حَیْثُ|یَجْعَلُ|رِسَالَتَهٗ ؕ—|سَیُصِیْبُ|الَّذِیْنَ|اَجْرَمُوْا|صَغَارٌ|عِنْدَ|اللّٰهِ|وَعَذَابٌ|شَدِیْدٌۢ|بِمَا|كَانُوْا|یَمْكُرُوْنَ","u": "وَإِذَا|جَآءَتۡهُمۡ|ءَايَةٞ|قَالُواْ|لَن|نُّؤۡمِنَ|حَتَّىٰ|نُؤۡتَىٰ|مِثۡلَ|مَآ|أُوتِيَ|رُسُلُ|ٱللَّهِۘ|ٱللَّهُ|أَعۡلَمُ|حَيۡثُ|يَجۡعَلُ|رِسَالَتَهُۥۗ|سَيُصِيبُ|ٱلَّذِينَ|أَجۡرَمُواْ|صَغَارٌ|عِندَ|ٱللَّهِ|وَعَذَابٞ|شَدِيدُۢ|بِمَا|كَانُواْ|يَمۡكُرُونَ","t": "wa-idha|jaathum|ayatun|qalu|lan|nu'mina|hatta|nu'ta|mith'la|ma|utiya|rusulu|al-lahi|al-lahu|a'lamu|haythu|yaj'alu|risalatahu|sayusibu|alladhina|ajramu|sagharun|inda|al-lahi|wa'adhabun|shadidun|bima|kanu|yamkuruna","e": "۟/١٢٤/."},"125": {"p": 144,"j": 8,"h": 57,"m": 2,"r": 116,"i": "فَمَنْ|یُّرِدِ|اللّٰهُ|اَنْ|یَّهْدِیَهٗ|یَشْرَحْ|صَدْرَهٗ|لِلْاِسْلَامِ ۚ—|وَمَنْ|یُّرِدْ|اَنْ|یُّضِلَّهٗ|یَجْعَلْ|صَدْرَهٗ|ضَیِّقًا|حَرَجًا|كَاَنَّمَا|یَصَّعَّدُ|فِی|السَّمَآءِ ؕ—|كَذٰلِكَ|یَجْعَلُ|اللّٰهُ|الرِّجْسَ|عَلَی|الَّذِیْنَ|لَا|یُؤْمِنُوْنَ","u": "فَمَن|يُرِدِ|ٱللَّهُ|أَن|يَهۡدِيَهُۥ|يَشۡرَحۡ|صَدۡرَهُۥ|لِلۡإِسۡلَٰمِۖ|وَمَن|يُرِدۡ|أَن|يُضِلَّهُۥ|يَجۡعَلۡ|صَدۡرَهُۥ|ضَيِّقًا|حَرَجٗا|كَأَنَّمَا|يَصَّعَّدُ|فِي|ٱلسَّمَآءِۚ|كَذَٰلِكَ|يَجۡعَلُ|ٱللَّهُ|ٱلرِّجۡسَ|عَلَى|ٱلَّذِينَ|لَا|يُؤۡمِنُونَ","t": "faman|yuridi|al-lahu|an|yahdiyahu|yashrah|sadrahu|lil'is'lami|waman|yurid|an|yudillahu|yaj'al|sadrahu|dayyiqan|harajan|ka-annama|yassa'adu|fi|al-samai|kadhalika|yaj'alu|al-lahu|al-rij'sa|ala|alladhina|la|yu'minuna","e": "۟/١٢٥/."},"126": {"p": 144,"j": 8,"h": 57,"m": 2,"r": 116,"i": "وَهٰذَا|صِرَاطُ|رَبِّكَ|مُسْتَقِیْمًا ؕ—|قَدْ|فَصَّلْنَا|الْاٰیٰتِ|لِقَوْمٍ|یَّذَّكَّرُوْنَ","u": "وَهَٰذَا|صِرَٰطُ|رَبِّكَ|مُسۡتَقِيمٗاۗ|قَدۡ|فَصَّلۡنَا|ٱلۡأٓيَٰتِ|لِقَوۡمٖ|يَذَّكَّرُونَ","t": "wahadha|siratu|rabbika|mus'taqiman|qad|fassalna|al-ayati|liqawmin|yadhakkaruna","e": "۟/١٢٦/."},"127": {"p": 144,"j": 8,"h": 58,"m": 2,"r": 116,"i": "لَهُمْ|دَارُ|السَّلٰمِ|عِنْدَ|رَبِّهِمْ|وَهُوَ|وَلِیُّهُمْ|بِمَا|كَانُوْا|یَعْمَلُوْنَ","u": "۞لَهُمۡ|دَارُ|ٱلسَّلَٰمِ|عِندَ|رَبِّهِمۡۖ|وَهُوَ|وَلِيُّهُم|بِمَا|كَانُواْ|يَعۡمَلُونَ","t": "lahum|daru|al-salami|inda|rabbihim|wahuwa|waliyyuhum|bima|kanu|ya'maluna","e": "۟/١٢٧/."},"128": {"p": 144,"j": 8,"h": 58,"m": 2,"r": 116,"i": "وَیَوْمَ|یَحْشُرُهُمْ|جَمِیْعًا ۚ—|یٰمَعْشَرَ|الْجِنِّ|قَدِ|اسْتَكْثَرْتُمْ|مِّنَ|الْاِنْسِ ۚ—|وَقَالَ|اَوْلِیٰٓؤُهُمْ|مِّنَ|الْاِنْسِ|رَبَّنَا|اسْتَمْتَعَ|بَعْضُنَا|بِبَعْضٍ|وَّبَلَغْنَاۤ|اَجَلَنَا|الَّذِیْۤ|اَجَّلْتَ|لَنَا ؕ—|قَالَ|النَّارُ|مَثْوٰىكُمْ|خٰلِدِیْنَ|فِیْهَاۤ|اِلَّا|مَا|شَآءَ|اللّٰهُ ؕ—|اِنَّ|رَبَّكَ|حَكِیْمٌ|عَلِیْمٌ","u": "وَيَوۡمَ|يَحۡشُرُهُمۡ|جَمِيعٗا|يَٰمَعۡشَرَ|ٱلۡجِنِّ|قَدِ|ٱسۡتَكۡثَرۡتُم|مِّنَ|ٱلۡإِنسِۖ|وَقَالَ|أَوۡلِيَآؤُهُم|مِّنَ|ٱلۡإِنسِ|رَبَّنَا|ٱسۡتَمۡتَعَ|بَعۡضُنَا|بِبَعۡضٖ|وَبَلَغۡنَآ|أَجَلَنَا|ٱلَّذِيٓ|أَجَّلۡتَ|لَنَاۚ|قَالَ|ٱلنَّارُ|مَثۡوَىٰكُمۡ|خَٰلِدِينَ|فِيهَآ|إِلَّا|مَا|شَآءَ|ٱللَّهُۚ|إِنَّ|رَبَّكَ|حَكِيمٌ|عَلِيمٞ","t": "wayawma|yahshuruhum|jami'an|yama'shara|al-jini|qadi|is'takthartum|mina|al-insi|waqala|awliyauhum|mina|al-insi|rabbana|is'tamta'a|ba'duna|biba'din|wabalaghna|ajalana|alladhi|ajjalta|lana|qala|al-naru|mathwakum|khalidina|fiha|illa|ma|shaa|al-lahu|inna|rabbaka|hakimun|alimun","e": "۟/١٢٨/."},"129": {"p": 144,"j": 8,"h": 58,"m": 2,"r": 116,"i": "وَكَذٰلِكَ|نُوَلِّیْ|بَعْضَ|الظّٰلِمِیْنَ|بَعْضًا|بِمَا|كَانُوْا|یَكْسِبُوْنَ","u": "وَكَذَٰلِكَ|نُوَلِّي|بَعۡضَ|ٱلظَّٰلِمِينَ|بَعۡضَۢا|بِمَا|كَانُواْ|يَكۡسِبُونَ","t": "wakadhalika|nuwalli|ba'da|al-zalimina|ba'dan|bima|kanu|yaksibuna","e": "۟۠/١٢٩/."},"130": {"p": 144,"j": 8,"h": 58,"m": 2,"r": 117,"i": "یٰمَعْشَرَ|الْجِنِّ|وَالْاِنْسِ|اَلَمْ|یَاْتِكُمْ|رُسُلٌ|مِّنْكُمْ|یَقُصُّوْنَ|عَلَیْكُمْ|اٰیٰتِیْ|وَیُنْذِرُوْنَكُمْ|لِقَآءَ|یَوْمِكُمْ|هٰذَا ؕ—|قَالُوْا|شَهِدْنَا|عَلٰۤی|اَنْفُسِنَا|وَغَرَّتْهُمُ|الْحَیٰوةُ|الدُّنْیَا|وَشَهِدُوْا|عَلٰۤی|اَنْفُسِهِمْ|اَنَّهُمْ|كَانُوْا|كٰفِرِیْنَ","u": "يَٰمَعۡشَرَ|ٱلۡجِنِّ|وَٱلۡإِنسِ|أَلَمۡ|يَأۡتِكُمۡ|رُسُلٞ|مِّنكُمۡ|يَقُصُّونَ|عَلَيۡكُمۡ|ءَايَٰتِي|وَيُنذِرُونَكُمۡ|لِقَآءَ|يَوۡمِكُمۡ|هَٰذَاۚ|قَالُواْ|شَهِدۡنَا|عَلَىٰٓ|أَنفُسِنَاۖ|وَغَرَّتۡهُمُ|ٱلۡحَيَوٰةُ|ٱلدُّنۡيَا|وَشَهِدُواْ|عَلَىٰٓ|أَنفُسِهِمۡ|أَنَّهُمۡ|كَانُواْ|كَٰفِرِينَ","t": "yama'shara|al-jini|wal-insi|alam|yatikum|rusulun|minkum|yaqussuna|alaykum|ayati|wayundhirunakum|liqaa|yawmikum|hadha|qalu|shahid'na|ala|anfusina|wagharrathumu|al-hayatu|al-dun'ya|washahidu|ala|anfusihim|annahum|kanu|kafirina","e": "۟/١٣٠/."},"131": {"p": 144,"j": 8,"h": 58,"m": 2,"r": 117,"i": "ذٰلِكَ|اَنْ|لَّمْ|یَكُنْ|رَّبُّكَ|مُهْلِكَ|الْقُرٰی|بِظُلْمٍ|وَّاَهْلُهَا|غٰفِلُوْنَ","u": "ذَٰلِكَ|أَن|لَّمۡ|يَكُن|رَّبُّكَ|مُهۡلِكَ|ٱلۡقُرَىٰ|بِظُلۡمٖ|وَأَهۡلُهَا|غَٰفِلُونَ","t": "dhalika|an|lam|yakun|rabbuka|muh'lika|al-qura|bizul'min|wa-ahluha|ghafiluna","e": "۟/١٣١/."},"132": {"p": 145,"j": 8,"h": 58,"m": 2,"r": 117,"i": "وَلِكُلٍّ|دَرَجٰتٌ|مِّمَّا|عَمِلُوْا ؕ—|وَمَا|رَبُّكَ|بِغَافِلٍ|عَمَّا|یَعْمَلُوْنَ","u": "وَلِكُلّٖ|دَرَجَٰتٞ|مِّمَّا|عَمِلُواْۚ|وَمَا|رَبُّكَ|بِغَٰفِلٍ|عَمَّا|يَعۡمَلُونَ","t": "walikullin|darajatun|mimma|amilu|wama|rabbuka|bighafilin|amma|ya'maluna","e": "۟/١٣٢/."},"133": {"p": 145,"j": 8,"h": 58,"m": 2,"r": 117,"i": "وَرَبُّكَ|الْغَنِیُّ|ذُو|الرَّحْمَةِ ؕ—|اِنْ|یَّشَاْ|یُذْهِبْكُمْ|وَیَسْتَخْلِفْ|مِنْ|بَعْدِكُمْ|مَّا|یَشَآءُ|كَمَاۤ|اَنْشَاَكُمْ|مِّنْ|ذُرِّیَّةِ|قَوْمٍ|اٰخَرِیْنَ","u": "وَرَبُّكَ|ٱلۡغَنِيُّ|ذُو|ٱلرَّحۡمَةِۚ|إِن|يَشَأۡ|يُذۡهِبۡكُمۡ|وَيَسۡتَخۡلِفۡ|مِنۢ|بَعۡدِكُم|مَّا|يَشَآءُ|كَمَآ|أَنشَأَكُم|مِّن|ذُرِّيَّةِ|قَوۡمٍ|ءَاخَرِينَ","t": "warabbuka|al-ghaniyu|dhu|al-rahmati|in|yasha|yudh'hib'kum|wayastakhlif|min|ba'dikum|ma|yashau|kama|ansha-akum|min|dhurriyyati|qawmin|akharina","e": "۟ؕ/١٣٣/."},"134": {"p": 145,"j": 8,"h": 58,"m": 2,"r": 117,"i": "اِنَّ|مَا|تُوْعَدُوْنَ|لَاٰتٍ ۙ—|وَّمَاۤ|اَنْتُمْ|بِمُعْجِزِیْنَ","u": "إِنَّ|مَا|تُوعَدُونَ|لَأٓتٖۖ|وَمَآ|أَنتُم|بِمُعۡجِزِينَ","t": "inna|ma|tu'aduna|laatin|wama|antum|bimu'jizina","e": "۟/١٣٤/."},"135": {"p": 145,"j": 8,"h": 58,"m": 2,"r": 117,"i": "قُلْ|یٰقَوْمِ|اعْمَلُوْا|عَلٰی|مَكَانَتِكُمْ|اِنِّیْ|عَامِلٌ ۚ—|فَسَوْفَ|تَعْلَمُوْنَ ۙ—|مَنْ|تَكُوْنُ|لَهٗ|عَاقِبَةُ|الدَّارِ ؕ—|اِنَّهٗ|لَا|یُفْلِحُ|الظّٰلِمُوْنَ","u": "قُلۡ|يَٰقَوۡمِ|ٱعۡمَلُواْ|عَلَىٰ|مَكَانَتِكُمۡ|إِنِّي|عَامِلٞۖ|فَسَوۡفَ|تَعۡلَمُونَ|مَن|تَكُونُ|لَهُۥ|عَٰقِبَةُ|ٱلدَّارِۚ|إِنَّهُۥ|لَا|يُفۡلِحُ|ٱلظَّٰلِمُونَ","t": "qul|yaqawmi|i'malu|ala|makanatikum|inni|amilun|fasawfa|ta'lamuna|man|takunu|lahu|aqibatu|al-dari|innahu|la|yuf'lihu|al-zalimuna","e": "۟/١٣٥/."},"136": {"p": 145,"j": 8,"h": 58,"m": 2,"r": 117,"i": "وَجَعَلُوْا|لِلّٰهِ|مِمَّا|ذَرَاَ|مِنَ|الْحَرْثِ|وَالْاَنْعَامِ|نَصِیْبًا|فَقَالُوْا|هٰذَا|لِلّٰهِ|بِزَعْمِهِمْ|وَهٰذَا|لِشُرَكَآىِٕنَا ۚ—|فَمَا|كَانَ|لِشُرَكَآىِٕهِمْ|فَلَا|یَصِلُ|اِلَی|اللّٰهِ ۚ—|وَمَا|كَانَ|لِلّٰهِ|فَهُوَ|یَصِلُ|اِلٰی|شُرَكَآىِٕهِمْ ؕ—|سَآءَ|مَا|یَحْكُمُوْنَ","u": "وَجَعَلُواْ|لِلَّهِ|مِمَّا|ذَرَأَ|مِنَ|ٱلۡحَرۡثِ|وَٱلۡأَنۡعَٰمِ|نَصِيبٗا|فَقَالُواْ|هَٰذَا|لِلَّهِ|بِزَعۡمِهِمۡ|وَهَٰذَا|لِشُرَكَآئِنَاۖ|فَمَا|كَانَ|لِشُرَكَآئِهِمۡ|فَلَا|يَصِلُ|إِلَى|ٱللَّهِۖ|وَمَا|كَانَ|لِلَّهِ|فَهُوَ|يَصِلُ|إِلَىٰ|شُرَكَآئِهِمۡۗ|سَآءَ|مَا|يَحۡكُمُونَ","t": "waja'alu|lillahi|mimma|dhara-a|mina|al-harthi|wal-an'ami|nasiban|faqalu|hadha|lillahi|biza'mihim|wahadha|lishurakaina|fama|kana|lishurakaihim|fala|yasilu|ila|al-lahi|wama|kana|lillahi|fahuwa|yasilu|ila|shurakaihim|saa|ma|yahkumuna","e": "۟/١٣٦/."},"137": {"p": 145,"j": 8,"h": 58,"m": 2,"r": 117,"i": "وَكَذٰلِكَ|زَیَّنَ|لِكَثِیْرٍ|مِّنَ|الْمُشْرِكِیْنَ|قَتْلَ|اَوْلَادِهِمْ|شُرَكَآؤُهُمْ|لِیُرْدُوْهُمْ|وَلِیَلْبِسُوْا|عَلَیْهِمْ|دِیْنَهُمْ ؕ—|وَلَوْ|شَآءَ|اللّٰهُ|مَا|فَعَلُوْهُ|فَذَرْهُمْ|وَمَا|یَفْتَرُوْنَ","u": "وَكَذَٰلِكَ|زَيَّنَ|لِكَثِيرٖ|مِّنَ|ٱلۡمُشۡرِكِينَ|قَتۡلَ|أَوۡلَٰدِهِمۡ|شُرَكَآؤُهُمۡ|لِيُرۡدُوهُمۡ|وَلِيَلۡبِسُواْ|عَلَيۡهِمۡ|دِينَهُمۡۖ|وَلَوۡ|شَآءَ|ٱللَّهُ|مَا|فَعَلُوهُۖ|فَذَرۡهُمۡ|وَمَا|يَفۡتَرُونَ","t": "wakadhalika|zayyana|likathirin|mina|al-mush'rikina|qatla|awladihim|shurakauhum|liyur'duhum|waliyalbisu|alayhim|dinahum|walaw|shaa|al-lahu|ma|fa'aluhu|fadharhum|wama|yaftaruna","e": "۟/١٣٧/."},"138": {"p": 146,"j": 8,"h": 58,"m": 2,"r": 117,"i": "وَقَالُوْا|هٰذِهٖۤ|اَنْعَامٌ|وَّحَرْثٌ|حِجْرٌ ۖۗ—|لَّا|یَطْعَمُهَاۤ|اِلَّا|مَنْ|نَّشَآءُ|بِزَعْمِهِمْ|وَاَنْعَامٌ|حُرِّمَتْ|ظُهُوْرُهَا|وَاَنْعَامٌ|لَّا|یَذْكُرُوْنَ|اسْمَ|اللّٰهِ|عَلَیْهَا|افْتِرَآءً|عَلَیْهِ ؕ—|سَیَجْزِیْهِمْ|بِمَا|كَانُوْا|یَفْتَرُوْنَ","u": "وَقَالُواْ|هَٰذِهِۦٓ|أَنۡعَٰمٞ|وَحَرۡثٌ|حِجۡرٞ|لَّا|يَطۡعَمُهَآ|إِلَّا|مَن|نَّشَآءُ|بِزَعۡمِهِمۡ|وَأَنۡعَٰمٌ|حُرِّمَتۡ|ظُهُورُهَا|وَأَنۡعَٰمٞ|لَّا|يَذۡكُرُونَ|ٱسۡمَ|ٱللَّهِ|عَلَيۡهَا|ٱفۡتِرَآءً|عَلَيۡهِۚ|سَيَجۡزِيهِم|بِمَا|كَانُواْ|يَفۡتَرُونَ","t": "waqalu|hadhihi|an'amun|waharthun|hij'run|la|yat'amuha|illa|man|nashau|biza'mihim|wa-an'amun|hurrimat|zuhuruha|wa-an'amun|la|yadhkuruna|is'ma|al-lahi|alayha|if'tiraan|alayhi|sayajzihim|bima|kanu|yaftaruna","e": "۟/١٣٨/."},"139": {"p": 146,"j": 8,"h": 58,"m": 2,"r": 117,"i": "وَقَالُوْا|مَا|فِیْ|بُطُوْنِ|هٰذِهِ|الْاَنْعَامِ|خَالِصَةٌ|لِّذُكُوْرِنَا|وَمُحَرَّمٌ|عَلٰۤی|اَزْوَاجِنَا ۚ—|وَاِنْ|یَّكُنْ|مَّیْتَةً|فَهُمْ|فِیْهِ|شُرَكَآءُ ؕ—|سَیَجْزِیْهِمْ|وَصْفَهُمْ ؕ—|اِنَّهٗ|حَكِیْمٌ|عَلِیْمٌ","u": "وَقَالُواْ|مَا|فِي|بُطُونِ|هَٰذِهِ|ٱلۡأَنۡعَٰمِ|خَالِصَةٞ|لِّذُكُورِنَا|وَمُحَرَّمٌ|عَلَىٰٓ|أَزۡوَٰجِنَاۖ|وَإِن|يَكُن|مَّيۡتَةٗ|فَهُمۡ|فِيهِ|شُرَكَآءُۚ|سَيَجۡزِيهِمۡ|وَصۡفَهُمۡۚ|إِنَّهُۥ|حَكِيمٌ|عَلِيمٞ","t": "waqalu|ma|fi|butuni|hadhihi|al-an'ami|khalisatun|lidhukurina|wamuharramun|ala|azwajina|wa-in|yakun|maytatan|fahum|fihi|shurakau|sayajzihim|wasfahum|innahu|hakimun|alimun","e": "۟/١٣٩/."},"140": {"p": 146,"j": 8,"h": 58,"m": 2,"r": 117,"i": "قَدْ|خَسِرَ|الَّذِیْنَ|قَتَلُوْۤا|اَوْلَادَهُمْ|سَفَهًا|بِغَیْرِ|عِلْمٍ|وَّحَرَّمُوْا|مَا|رَزَقَهُمُ|اللّٰهُ|افْتِرَآءً|عَلَی|اللّٰهِ ؕ—|قَدْ|ضَلُّوْا|وَمَا|كَانُوْا|مُهْتَدِیْنَ","u": "قَدۡ|خَسِرَ|ٱلَّذِينَ|قَتَلُوٓاْ|أَوۡلَٰدَهُمۡ|سَفَهَۢا|بِغَيۡرِ|عِلۡمٖ|وَحَرَّمُواْ|مَا|رَزَقَهُمُ|ٱللَّهُ|ٱفۡتِرَآءً|عَلَى|ٱللَّهِۚ|قَدۡ|ضَلُّواْ|وَمَا|كَانُواْ|مُهۡتَدِينَ","t": "qad|khasira|alladhina|qatalu|awladahum|safahan|bighayri|il'min|waharramu|ma|razaqahumu|al-lahu|if'tiraan|ala|al-lahi|qad|dallu|wama|kanu|muh'tadina","e": "۟۠/١٤٠/."},"141": {"p": 146,"j": 8,"h": 59,"m": 2,"r": 118,"i": "وَهُوَ|الَّذِیْۤ|اَنْشَاَ|جَنّٰتٍ|مَّعْرُوْشٰتٍ|وَّغَیْرَ|مَعْرُوْشٰتٍ|وَّالنَّخْلَ|وَالزَّرْعَ|مُخْتَلِفًا|اُكُلُهٗ|وَالزَّیْتُوْنَ|وَالرُّمَّانَ|مُتَشَابِهًا|وَّغَیْرَ|مُتَشَابِهٍ ؕ—|كُلُوْا|مِنْ|ثَمَرِهٖۤ|اِذَاۤ|اَثْمَرَ|وَاٰتُوْا|حَقَّهٗ|یَوْمَ|حَصَادِهٖ ۖؗ—|وَلَا|تُسْرِفُوْا ؕ—|اِنَّهٗ|لَا|یُحِبُّ|الْمُسْرِفِیْنَ","u": "۞وَهُوَ|ٱلَّذِيٓ|أَنشَأَ|جَنَّٰتٖ|مَّعۡرُوشَٰتٖ|وَغَيۡرَ|مَعۡرُوشَٰتٖ|وَٱلنَّخۡلَ|وَٱلزَّرۡعَ|مُخۡتَلِفًا|أُكُلُهُۥ|وَٱلزَّيۡتُونَ|وَٱلرُّمَّانَ|مُتَشَٰبِهٗا|وَغَيۡرَ|مُتَشَٰبِهٖۚ|كُلُواْ|مِن|ثَمَرِهِۦٓ|إِذَآ|أَثۡمَرَ|وَءَاتُواْ|حَقَّهُۥ|يَوۡمَ|حَصَادِهِۦۖ|وَلَا|تُسۡرِفُوٓاْۚ|إِنَّهُۥ|لَا|يُحِبُّ|ٱلۡمُسۡرِفِينَ","t": "wahuwa|alladhi|ansha-a|jannatin|ma'rushatin|waghayra|ma'rushatin|wal-nakhla|wal-zar'a|mukh'talifan|ukuluhu|wal-zaytuna|wal-rumana|mutashabihan|waghayra|mutashabihin|kulu|min|thamarihi|idha|athmara|waatu|haqqahu|yawma|hasadihi|wala|tus'rifu|innahu|la|yuhibbu|al-mus'rifina","e": "۟ۙ/١٤١/."},"142": {"p": 146,"j": 8,"h": 59,"m": 2,"r": 118,"i": "وَمِنَ|الْاَنْعَامِ|حَمُوْلَةً|وَّفَرْشًا ؕ—|كُلُوْا|مِمَّا|رَزَقَكُمُ|اللّٰهُ|وَلَا|تَتَّبِعُوْا|خُطُوٰتِ|الشَّیْطٰنِ ؕ—|اِنَّهٗ|لَكُمْ|عَدُوٌّ|مُّبِیْنٌ","u": "وَمِنَ|ٱلۡأَنۡعَٰمِ|حَمُولَةٗ|وَفَرۡشٗاۚ|كُلُواْ|مِمَّا|رَزَقَكُمُ|ٱللَّهُ|وَلَا|تَتَّبِعُواْ|خُطُوَٰتِ|ٱلشَّيۡطَٰنِۚ|إِنَّهُۥ|لَكُمۡ|عَدُوّٞ|مُّبِينٞ","t": "wamina|al-an'ami|hamulatan|wafarshan|kulu|mimma|razaqakumu|al-lahu|wala|tattabi'u|khutuwati|al-shaytani|innahu|lakum|aduwwun|mubinun","e": "۟ۙ/١٤٢/."},"143": {"p": 147,"j": 8,"h": 59,"m": 2,"r": 118,"i": "ثَمٰنِیَةَ|اَزْوَاجٍ ۚ—|مِنَ|الضَّاْنِ|اثْنَیْنِ|وَمِنَ|الْمَعْزِ|اثْنَیْنِ ؕ—|قُلْ|ءٰٓالذَّكَرَیْنِ|حَرَّمَ|اَمِ|الْاُنْثَیَیْنِ|اَمَّا|اشْتَمَلَتْ|عَلَیْهِ|اَرْحَامُ|الْاُنْثَیَیْنِ ؕ—|نَبِّـُٔوْنِیْ|بِعِلْمٍ|اِنْ|كُنْتُمْ|صٰدِقِیْنَ","u": "ثَمَٰنِيَةَ|أَزۡوَٰجٖۖ|مِّنَ|ٱلضَّأۡنِ|ٱثۡنَيۡنِ|وَمِنَ|ٱلۡمَعۡزِ|ٱثۡنَيۡنِۗ|قُلۡ|ءَآلذَّكَرَيۡنِ|حَرَّمَ|أَمِ|ٱلۡأُنثَيَيۡنِ|أَمَّا|ٱشۡتَمَلَتۡ|عَلَيۡهِ|أَرۡحَامُ|ٱلۡأُنثَيَيۡنِۖ|نَبِّـُٔونِي|بِعِلۡمٍ|إِن|كُنتُمۡ|صَٰدِقِينَ","t": "thamaniyata|azwajin|mina|al-dani|ith'nayni|wamina|al-ma'zi|ith'nayni|qul|aldhakarayni|harrama|ami|al-unthayayni|amma|ish'tamalat|alayhi|arhamu|al-unthayayni|nabbiuni|bi'il'min|in|kuntum|sadiqina","e": "۟ۙ/١٤٣/."},"144": {"p": 147,"j": 8,"h": 59,"m": 2,"r": 118,"i": "وَمِنَ|الْاِبِلِ|اثْنَیْنِ|وَمِنَ|الْبَقَرِ|اثْنَیْنِ ؕ—|قُلْ|ءٰٓالذَّكَرَیْنِ|حَرَّمَ|اَمِ|الْاُنْثَیَیْنِ|اَمَّا|اشْتَمَلَتْ|عَلَیْهِ|اَرْحَامُ|الْاُنْثَیَیْنِ ؕ—|اَمْ|كُنْتُمْ|شُهَدَآءَ|اِذْ|وَصّٰىكُمُ|اللّٰهُ|بِهٰذَا ۚ—|فَمَنْ|اَظْلَمُ|مِمَّنِ|افْتَرٰی|عَلَی|اللّٰهِ|كَذِبًا|لِّیُضِلَّ|النَّاسَ|بِغَیْرِ|عِلْمٍ ؕ—|اِنَّ|اللّٰهَ|لَا|یَهْدِی|الْقَوْمَ|الظّٰلِمِیْنَ","u": "وَمِنَ|ٱلۡإِبِلِ|ٱثۡنَيۡنِ|وَمِنَ|ٱلۡبَقَرِ|ٱثۡنَيۡنِۗ|قُلۡ|ءَآلذَّكَرَيۡنِ|حَرَّمَ|أَمِ|ٱلۡأُنثَيَيۡنِ|أَمَّا|ٱشۡتَمَلَتۡ|عَلَيۡهِ|أَرۡحَامُ|ٱلۡأُنثَيَيۡنِۖ|أَمۡ|كُنتُمۡ|شُهَدَآءَ|إِذۡ|وَصَّىٰكُمُ|ٱللَّهُ|بِهَٰذَاۚ|فَمَنۡ|أَظۡلَمُ|مِمَّنِ|ٱفۡتَرَىٰ|عَلَى|ٱللَّهِ|كَذِبٗا|لِّيُضِلَّ|ٱلنَّاسَ|بِغَيۡرِ|عِلۡمٍۚ|إِنَّ|ٱللَّهَ|لَا|يَهۡدِي|ٱلۡقَوۡمَ|ٱلظَّٰلِمِينَ","t": "wamina|al-ibili|ith'nayni|wamina|al-baqari|ith'nayni|qul|aldhakarayni|harrama|ami|al-unthayayni|amma|ish'tamalat|alayhi|arhamu|al-unthayayni|am|kuntum|shuhadaa|idh|wassakumu|al-lahu|bihadha|faman|azlamu|mimmani|if'tara|ala|al-lahi|kadhiban|liyudilla|al-nasa|bighayri|il'min|inna|al-laha|la|yahdi|al-qawma|al-zalimina","e": "۟۠/١٤٤/."},"145": {"p": 147,"j": 8,"h": 59,"m": 2,"r": 119,"i": "قُلْ|لَّاۤ|اَجِدُ|فِیْ|مَاۤ|اُوْحِیَ|اِلَیَّ|مُحَرَّمًا|عَلٰی|طَاعِمٍ|یَّطْعَمُهٗۤ|اِلَّاۤ|اَنْ|یَّكُوْنَ|مَیْتَةً|اَوْ|دَمًا|مَّسْفُوْحًا|اَوْ|لَحْمَ|خِنْزِیْرٍ|فَاِنَّهٗ|رِجْسٌ|اَوْ|فِسْقًا|اُهِلَّ|لِغَیْرِ|اللّٰهِ|بِهٖ ۚ—|فَمَنِ|اضْطُرَّ|غَیْرَ|بَاغٍ|وَّلَا|عَادٍ|فَاِنَّ|رَبَّكَ|غَفُوْرٌ|رَّحِیْمٌ","u": "قُل|لَّآ|أَجِدُ|فِي|مَآ|أُوحِيَ|إِلَيَّ|مُحَرَّمًا|عَلَىٰ|طَاعِمٖ|يَطۡعَمُهُۥٓ|إِلَّآ|أَن|يَكُونَ|مَيۡتَةً|أَوۡ|دَمٗا|مَّسۡفُوحًا|أَوۡ|لَحۡمَ|خِنزِيرٖ|فَإِنَّهُۥ|رِجۡسٌ|أَوۡ|فِسۡقًا|أُهِلَّ|لِغَيۡرِ|ٱللَّهِ|بِهِۦۚ|فَمَنِ|ٱضۡطُرَّ|غَيۡرَ|بَاغٖ|وَلَا|عَادٖ|فَإِنَّ|رَبَّكَ|غَفُورٞ|رَّحِيمٞ","t": "qul|la|ajidu|fi|ma|uhiya|ilayya|muharraman|ala|ta'imin|yat'amuhu|illa|an|yakuna|maytatan|aw|daman|masfuhan|aw|lahma|khinzirin|fa-innahu|rij'sun|aw|fis'qan|uhilla|lighayri|al-lahi|bihi|famani|ud'turra|ghayra|baghin|wala|adin|fa-inna|rabbaka|ghafurun|rahimun","e": "۟/١٤٥/."},"146": {"p": 147,"j": 8,"h": 59,"m": 2,"r": 119,"i": "وَعَلَی|الَّذِیْنَ|هَادُوْا|حَرَّمْنَا|كُلَّ|ذِیْ|ظُفُرٍ ۚ—|وَمِنَ|الْبَقَرِ|وَالْغَنَمِ|حَرَّمْنَا|عَلَیْهِمْ|شُحُوْمَهُمَاۤ|اِلَّا|مَا|حَمَلَتْ|ظُهُوْرُهُمَاۤ|اَوِ|الْحَوَایَاۤ|اَوْ|مَا|اخْتَلَطَ|بِعَظْمٍ ؕ—|ذٰلِكَ|جَزَیْنٰهُمْ|بِبَغْیِهِمْ ۖؗ—|وَاِنَّا|لَصٰدِقُوْنَ","u": "وَعَلَى|ٱلَّذِينَ|هَادُواْ|حَرَّمۡنَا|كُلَّ|ذِي|ظُفُرٖۖ|وَمِنَ|ٱلۡبَقَرِ|وَٱلۡغَنَمِ|حَرَّمۡنَا|عَلَيۡهِمۡ|شُحُومَهُمَآ|إِلَّا|مَا|حَمَلَتۡ|ظُهُورُهُمَآ|أَوِ|ٱلۡحَوَايَآ|أَوۡ|مَا|ٱخۡتَلَطَ|بِعَظۡمٖۚ|ذَٰلِكَ|جَزَيۡنَٰهُم|بِبَغۡيِهِمۡۖ|وَإِنَّا|لَصَٰدِقُونَ","t": "wa'ala|alladhina|hadu|harramna|kulla|dhi|zufurin|wamina|al-baqari|wal-ghanami|harramna|alayhim|shuhumahuma|illa|ma|hamalat|zuhuruhuma|awi|al-hawaya|aw|ma|ikh'talata|bi'azmin|dhalika|jazaynahum|bibaghyihim|wa-inna|lasadiquna","e": "۟/١٤٦/."},"147": {"p": 148,"j": 8,"h": 59,"m": 2,"r": 119,"i": "فَاِنْ|كَذَّبُوْكَ|فَقُلْ|رَّبُّكُمْ|ذُوْ|رَحْمَةٍ|وَّاسِعَةٍ ۚ—|وَلَا|یُرَدُّ|بَاْسُهٗ|عَنِ|الْقَوْمِ|الْمُجْرِمِیْنَ","u": "فَإِن|كَذَّبُوكَ|فَقُل|رَّبُّكُمۡ|ذُو|رَحۡمَةٖ|وَٰسِعَةٖ|وَلَا|يُرَدُّ|بَأۡسُهُۥ|عَنِ|ٱلۡقَوۡمِ|ٱلۡمُجۡرِمِينَ","t": "fa-in|kadhabuka|faqul|rabbukum|dhu|rahmatin|wasi'atin|wala|yuraddu|basuhu|ani|al-qawmi|al-muj'rimina","e": "۟/١٤٧/."},"148": {"p": 148,"j": 8,"h": 59,"m": 2,"r": 119,"i": "سَیَقُوْلُ|الَّذِیْنَ|اَشْرَكُوْا|لَوْ|شَآءَ|اللّٰهُ|مَاۤ|اَشْرَكْنَا|وَلَاۤ|اٰبَآؤُنَا|وَلَا|حَرَّمْنَا|مِنْ|شَیْءٍ ؕ—|كَذٰلِكَ|كَذَّبَ|الَّذِیْنَ|مِنْ|قَبْلِهِمْ|حَتّٰی|ذَاقُوْا|بَاْسَنَا ؕ—|قُلْ|هَلْ|عِنْدَكُمْ|مِّنْ|عِلْمٍ|فَتُخْرِجُوْهُ|لَنَا ؕ—|اِنْ|تَتَّبِعُوْنَ|اِلَّا|الظَّنَّ|وَاِنْ|اَنْتُمْ|اِلَّا|تَخْرُصُوْنَ","u": "سَيَقُولُ|ٱلَّذِينَ|أَشۡرَكُواْ|لَوۡ|شَآءَ|ٱللَّهُ|مَآ|أَشۡرَكۡنَا|وَلَآ|ءَابَآؤُنَا|وَلَا|حَرَّمۡنَا|مِن|شَيۡءٖۚ|كَذَٰلِكَ|كَذَّبَ|ٱلَّذِينَ|مِن|قَبۡلِهِمۡ|حَتَّىٰ|ذَاقُواْ|بَأۡسَنَاۗ|قُلۡ|هَلۡ|عِندَكُم|مِّنۡ|عِلۡمٖ|فَتُخۡرِجُوهُ|لَنَآۖ|إِن|تَتَّبِعُونَ|إِلَّا|ٱلظَّنَّ|وَإِنۡ|أَنتُمۡ|إِلَّا|تَخۡرُصُونَ","t": "sayaqulu|alladhina|ashraku|law|shaa|al-lahu|ma|ashrakna|wala|abauna|wala|harramna|min|shayin|kadhalika|kadhaba|alladhina|min|qablihim|hatta|dhaqu|basana|qul|hal|indakum|min|il'min|fatukh'rijuhu|lana|in|tattabi'una|illa|al-zana|wa-in|antum|illa|takhrusuna","e": "۟/١٤٨/."},"149": {"p": 148,"j": 8,"h": 59,"m": 2,"r": 119,"i": "قُلْ|فَلِلّٰهِ|الْحُجَّةُ|الْبَالِغَةُ ۚ—|فَلَوْ|شَآءَ|لَهَدٰىكُمْ|اَجْمَعِیْنَ","u": "قُلۡ|فَلِلَّهِ|ٱلۡحُجَّةُ|ٱلۡبَٰلِغَةُۖ|فَلَوۡ|شَآءَ|لَهَدَىٰكُمۡ|أَجۡمَعِينَ","t": "qul|falillahi|al-hujatu|al-balighatu|falaw|shaa|lahadakum|ajma'ina","e": "۟/١٤٩/."},"150": {"p": 148,"j": 8,"h": 59,"m": 2,"r": 119,"i": "قُلْ|هَلُمَّ|شُهَدَآءَكُمُ|الَّذِیْنَ|یَشْهَدُوْنَ|اَنَّ|اللّٰهَ|حَرَّمَ|هٰذَا ۚ—|فَاِنْ|شَهِدُوْا|فَلَا|تَشْهَدْ|مَعَهُمْ ۚ—|وَلَا|تَتَّبِعْ|اَهْوَآءَ|الَّذِیْنَ|كَذَّبُوْا|بِاٰیٰتِنَا|وَالَّذِیْنَ|لَا|یُؤْمِنُوْنَ|بِالْاٰخِرَةِ|وَهُمْ|بِرَبِّهِمْ|یَعْدِلُوْنَ","u": "قُلۡ|هَلُمَّ|شُهَدَآءَكُمُ|ٱلَّذِينَ|يَشۡهَدُونَ|أَنَّ|ٱللَّهَ|حَرَّمَ|هَٰذَاۖ|فَإِن|شَهِدُواْ|فَلَا|تَشۡهَدۡ|مَعَهُمۡۚ|وَلَا|تَتَّبِعۡ|أَهۡوَآءَ|ٱلَّذِينَ|كَذَّبُواْ|بِـَٔايَٰتِنَا|وَٱلَّذِينَ|لَا|يُؤۡمِنُونَ|بِٱلۡأٓخِرَةِ|وَهُم|بِرَبِّهِمۡ|يَعۡدِلُونَ","t": "qul|halumma|shuhadaakumu|alladhina|yashhaduna|anna|al-laha|harrama|hadha|fa-in|shahidu|fala|tashhad|ma'ahum|wala|tattabi'|ahwaa|alladhina|kadhabu|biayatina|wa-alladhina|la|yu'minuna|bil-akhirati|wahum|birabbihim|ya'diluna","e": "۟۠/١٥٠/."},"151": {"p": 148,"j": 8,"h": 60,"m": 2,"r": 120,"i": "قُلْ|تَعَالَوْا|اَتْلُ|مَا|حَرَّمَ|رَبُّكُمْ|عَلَیْكُمْ|اَلَّا|تُشْرِكُوْا|بِهٖ|شَیْـًٔا|وَّبِالْوَالِدَیْنِ|اِحْسَانًا ۚ—|وَلَا|تَقْتُلُوْۤا|اَوْلَادَكُمْ|مِّنْ|اِمْلَاقٍ ؕ—|نَحْنُ|نَرْزُقُكُمْ|وَاِیَّاهُمْ ۚ—|وَلَا|تَقْرَبُوا|الْفَوَاحِشَ|مَا|ظَهَرَ|مِنْهَا|وَمَا|بَطَنَ ۚ—|وَلَا|تَقْتُلُوا|النَّفْسَ|الَّتِیْ|حَرَّمَ|اللّٰهُ|اِلَّا|بِالْحَقِّ ؕ—|ذٰلِكُمْ|وَصّٰىكُمْ|بِهٖ|لَعَلَّكُمْ|تَعْقِلُوْنَ","u": "۞قُلۡ|تَعَالَوۡاْ|أَتۡلُ|مَا|حَرَّمَ|رَبُّكُمۡ|عَلَيۡكُمۡۖ|أَلَّا|تُشۡرِكُواْ|بِهِۦ|شَيۡـٔٗاۖ|وَبِٱلۡوَٰلِدَيۡنِ|إِحۡسَٰنٗاۖ|وَلَا|تَقۡتُلُوٓاْ|أَوۡلَٰدَكُم|مِّنۡ|إِمۡلَٰقٖ|نَّحۡنُ|نَرۡزُقُكُمۡ|وَإِيَّاهُمۡۖ|وَلَا|تَقۡرَبُواْ|ٱلۡفَوَٰحِشَ|مَا|ظَهَرَ|مِنۡهَا|وَمَا|بَطَنَۖ|وَلَا|تَقۡتُلُواْ|ٱلنَّفۡسَ|ٱلَّتِي|حَرَّمَ|ٱللَّهُ|إِلَّا|بِٱلۡحَقِّۚ|ذَٰلِكُمۡ|وَصَّىٰكُم|بِهِۦ|لَعَلَّكُمۡ|تَعۡقِلُونَ","t": "qul|ta'alaw|atlu|ma|harrama|rabbukum|alaykum|alla|tush'riku|bihi|shayan|wabil-walidayni|ih'sanan|wala|taqtulu|awladakum|min|im'laqin|nahnu|narzuqukum|wa-iyyahum|wala|taqrabu|al-fawahisha|ma|zahara|min'ha|wama|batana|wala|taqtulu|al-nafsa|allati|harrama|al-lahu|illa|bil-haqi|dhalikum|wassakum|bihi|la'allakum|ta'qiluna","e": "۟/١٥١/."},"152": {"p": 149,"j": 8,"h": 60,"m": 2,"r": 120,"i": "وَلَا|تَقْرَبُوْا|مَالَ|الْیَتِیْمِ|اِلَّا|بِالَّتِیْ|هِیَ|اَحْسَنُ|حَتّٰی|یَبْلُغَ|اَشُدَّهٗ ۚ—|وَاَوْفُوا|الْكَیْلَ|وَالْمِیْزَانَ|بِالْقِسْطِ ۚ—|لَا|نُكَلِّفُ|نَفْسًا|اِلَّا|وُسْعَهَا ۚ—|وَاِذَا|قُلْتُمْ|فَاعْدِلُوْا|وَلَوْ|كَانَ|ذَا|قُرْبٰی ۚ—|وَبِعَهْدِ|اللّٰهِ|اَوْفُوْا ؕ—|ذٰلِكُمْ|وَصّٰىكُمْ|بِهٖ|لَعَلَّكُمْ|تَذَكَّرُوْنَ","u": "وَلَا|تَقۡرَبُواْ|مَالَ|ٱلۡيَتِيمِ|إِلَّا|بِٱلَّتِي|هِيَ|أَحۡسَنُ|حَتَّىٰ|يَبۡلُغَ|أَشُدَّهُۥۚ|وَأَوۡفُواْ|ٱلۡكَيۡلَ|وَٱلۡمِيزَانَ|بِٱلۡقِسۡطِۖ|لَا|نُكَلِّفُ|نَفۡسًا|إِلَّا|وُسۡعَهَاۖ|وَإِذَا|قُلۡتُمۡ|فَٱعۡدِلُواْ|وَلَوۡ|كَانَ|ذَا|قُرۡبَىٰۖ|وَبِعَهۡدِ|ٱللَّهِ|أَوۡفُواْۚ|ذَٰلِكُمۡ|وَصَّىٰكُم|بِهِۦ|لَعَلَّكُمۡ|تَذَكَّرُونَ","t": "wala|taqrabu|mala|al-yatimi|illa|bi-allati|hiya|ahsanu|hatta|yablugha|ashuddahu|wa-awfu|al-kayla|wal-mizana|bil-qis'ti|la|nukallifu|nafsan|illa|wus'aha|wa-idha|qul'tum|fa-i'dilu|walaw|kana|dha|qur'ba|wabi'ahdi|al-lahi|awfu|dhalikum|wassakum|bihi|la'allakum|tadhakkaruna","e": "۟ۙ/١٥٢/."},"153": {"p": 149,"j": 8,"h": 60,"m": 2,"r": 120,"i": "وَاَنَّ|هٰذَا|صِرَاطِیْ|مُسْتَقِیْمًا|فَاتَّبِعُوْهُ ۚ—|وَلَا|تَتَّبِعُوا|السُّبُلَ|فَتَفَرَّقَ|بِكُمْ|عَنْ|سَبِیْلِهٖ ؕ—|ذٰلِكُمْ|وَصّٰىكُمْ|بِهٖ|لَعَلَّكُمْ|تَتَّقُوْنَ","u": "وَأَنَّ|هَٰذَا|صِرَٰطِي|مُسۡتَقِيمٗا|فَٱتَّبِعُوهُۖ|وَلَا|تَتَّبِعُواْ|ٱلسُّبُلَ|فَتَفَرَّقَ|بِكُمۡ|عَن|سَبِيلِهِۦۚ|ذَٰلِكُمۡ|وَصَّىٰكُم|بِهِۦ|لَعَلَّكُمۡ|تَتَّقُونَ","t": "wa-anna|hadha|sirati|mus'taqiman|fa-ittabi'uhu|wala|tattabi'u|al-subula|fatafarraqa|bikum|an|sabilihi|dhalikum|wassakum|bihi|la'allakum|tattaquna","e": "۟/١٥٣/."},"154": {"p": 149,"j": 8,"h": 60,"m": 2,"r": 120,"i": "ثُمَّ|اٰتَیْنَا|مُوْسَی|الْكِتٰبَ|تَمَامًا|عَلَی|الَّذِیْۤ|اَحْسَنَ|وَتَفْصِیْلًا|لِّكُلِّ|شَیْءٍ|وَّهُدًی|وَّرَحْمَةً|لَّعَلَّهُمْ|بِلِقَآءِ|رَبِّهِمْ|یُؤْمِنُوْنَ","u": "ثُمَّ|ءَاتَيۡنَا|مُوسَى|ٱلۡكِتَٰبَ|تَمَامًا|عَلَى|ٱلَّذِيٓ|أَحۡسَنَ|وَتَفۡصِيلٗا|لِّكُلِّ|شَيۡءٖ|وَهُدٗى|وَرَحۡمَةٗ|لَّعَلَّهُم|بِلِقَآءِ|رَبِّهِمۡ|يُؤۡمِنُونَ","t": "thumma|atayna|musa|al-kitaba|tamaman|ala|alladhi|ahsana|watafsilan|likulli|shayin|wahudan|warahmatan|la'allahum|biliqai|rabbihim|yu'minuna","e": "۟۠/١٥٤/."},"155": {"p": 149,"j": 8,"h": 60,"m": 2,"r": 121,"i": "وَهٰذَا|كِتٰبٌ|اَنْزَلْنٰهُ|مُبٰرَكٌ|فَاتَّبِعُوْهُ|وَاتَّقُوْا|لَعَلَّكُمْ|تُرْحَمُوْنَ","u": "وَهَٰذَا|كِتَٰبٌ|أَنزَلۡنَٰهُ|مُبَارَكٞ|فَٱتَّبِعُوهُ|وَٱتَّقُواْ|لَعَلَّكُمۡ|تُرۡحَمُونَ","t": "wahadha|kitabun|anzalnahu|mubarakun|fa-ittabi'uhu|wa-ittaqu|la'allakum|tur'hamuna","e": "۟ۙ/١٥٥/."},"156": {"p": 149,"j": 8,"h": 60,"m": 2,"r": 121,"i": "اَنْ|تَقُوْلُوْۤا|اِنَّمَاۤ|اُنْزِلَ|الْكِتٰبُ|عَلٰی|طَآىِٕفَتَیْنِ|مِنْ|قَبْلِنَا ۪—|وَاِنْ|كُنَّا|عَنْ|دِرَاسَتِهِمْ|لَغٰفِلِیْنَ","u": "أَن|تَقُولُوٓاْ|إِنَّمَآ|أُنزِلَ|ٱلۡكِتَٰبُ|عَلَىٰ|طَآئِفَتَيۡنِ|مِن|قَبۡلِنَا|وَإِن|كُنَّا|عَن|دِرَاسَتِهِمۡ|لَغَٰفِلِينَ","t": "an|taqulu|innama|unzila|al-kitabu|ala|taifatayni|min|qablina|wa-in|kunna|an|dirasatihim|laghafilina","e": "۟ۙ/١٥٦/."},"157": {"p": 149,"j": 8,"h": 60,"m": 2,"r": 121,"i": "اَوْ|تَقُوْلُوْا|لَوْ|اَنَّاۤ|اُنْزِلَ|عَلَیْنَا|الْكِتٰبُ|لَكُنَّاۤ|اَهْدٰی|مِنْهُمْ ۚ—|فَقَدْ|جَآءَكُمْ|بَیِّنَةٌ|مِّنْ|رَّبِّكُمْ|وَهُدًی|وَّرَحْمَةٌ ۚ—|فَمَنْ|اَظْلَمُ|مِمَّنْ|كَذَّبَ|بِاٰیٰتِ|اللّٰهِ|وَصَدَفَ|عَنْهَا ؕ—|سَنَجْزِی|الَّذِیْنَ|یَصْدِفُوْنَ|عَنْ|اٰیٰتِنَا|سُوْٓءَ|الْعَذَابِ|بِمَا|كَانُوْا|یَصْدِفُوْنَ","u": "أَوۡ|تَقُولُواْ|لَوۡ|أَنَّآ|أُنزِلَ|عَلَيۡنَا|ٱلۡكِتَٰبُ|لَكُنَّآ|أَهۡدَىٰ|مِنۡهُمۡۚ|فَقَدۡ|جَآءَكُم|بَيِّنَةٞ|مِّن|رَّبِّكُمۡ|وَهُدٗى|وَرَحۡمَةٞۚ|فَمَنۡ|أَظۡلَمُ|مِمَّن|كَذَّبَ|بِـَٔايَٰتِ|ٱللَّهِ|وَصَدَفَ|عَنۡهَاۗ|سَنَجۡزِي|ٱلَّذِينَ|يَصۡدِفُونَ|عَنۡ|ءَايَٰتِنَا|سُوٓءَ|ٱلۡعَذَابِ|بِمَا|كَانُواْ|يَصۡدِفُونَ","t": "aw|taqulu|law|anna|unzila|alayna|al-kitabu|lakunna|ahda|min'hum|faqad|jaakum|bayyinatun|min|rabbikum|wahudan|warahmatun|faman|azlamu|mimman|kadhaba|biayati|al-lahi|wasadafa|anha|sanajzi|alladhina|yasdifuna|an|ayatina|sua|al-'adhabi|bima|kanu|yasdifuna","e": "۟/١٥٧/."},"158": {"p": 150,"j": 8,"h": 60,"m": 2,"r": 121,"i": "هَلْ|یَنْظُرُوْنَ|اِلَّاۤ|اَنْ|تَاْتِیَهُمُ|الْمَلٰٓىِٕكَةُ|اَوْ|یَاْتِیَ|رَبُّكَ|اَوْ|یَاْتِیَ|بَعْضُ|اٰیٰتِ|رَبِّكَ ؕ—|یَوْمَ|یَاْتِیْ|بَعْضُ|اٰیٰتِ|رَبِّكَ|لَا|یَنْفَعُ|نَفْسًا|اِیْمَانُهَا|لَمْ|تَكُنْ|اٰمَنَتْ|مِنْ|قَبْلُ|اَوْ|كَسَبَتْ|فِیْۤ|اِیْمَانِهَا|خَیْرًا ؕ—|قُلِ|انْتَظِرُوْۤا|اِنَّا|مُنْتَظِرُوْنَ","u": "هَلۡ|يَنظُرُونَ|إِلَّآ|أَن|تَأۡتِيَهُمُ|ٱلۡمَلَٰٓئِكَةُ|أَوۡ|يَأۡتِيَ|رَبُّكَ|أَوۡ|يَأۡتِيَ|بَعۡضُ|ءَايَٰتِ|رَبِّكَۗ|يَوۡمَ|يَأۡتِي|بَعۡضُ|ءَايَٰتِ|رَبِّكَ|لَا|يَنفَعُ|نَفۡسًا|إِيمَٰنُهَا|لَمۡ|تَكُنۡ|ءَامَنَتۡ|مِن|قَبۡلُ|أَوۡ|كَسَبَتۡ|فِيٓ|إِيمَٰنِهَا|خَيۡرٗاۗ|قُلِ|ٱنتَظِرُوٓاْ|إِنَّا|مُنتَظِرُونَ","t": "hal|yanzuruna|illa|an|tatiyahumu|al-malaikatu|aw|yatiya|rabbuka|aw|yatiya|ba'du|ayati|rabbika|yawma|yati|ba'du|ayati|rabbika|la|yanfa'u|nafsan|imanuha|lam|takun|amanat|min|qablu|aw|kasabat|fi|imaniha|khayran|quli|intaziru|inna|muntaziruna","e": "۟/١٥٨/."},"159": {"p": 150,"j": 8,"h": 60,"m": 2,"r": 121,"i": "اِنَّ|الَّذِیْنَ|فَرَّقُوْا|دِیْنَهُمْ|وَكَانُوْا|شِیَعًا|لَّسْتَ|مِنْهُمْ|فِیْ|شَیْءٍ ؕ—|اِنَّمَاۤ|اَمْرُهُمْ|اِلَی|اللّٰهِ|ثُمَّ|یُنَبِّئُهُمْ|بِمَا|كَانُوْا|یَفْعَلُوْنَ","u": "إِنَّ|ٱلَّذِينَ|فَرَّقُواْ|دِينَهُمۡ|وَكَانُواْ|شِيَعٗا|لَّسۡتَ|مِنۡهُمۡ|فِي|شَيۡءٍۚ|إِنَّمَآ|أَمۡرُهُمۡ|إِلَى|ٱللَّهِ|ثُمَّ|يُنَبِّئُهُم|بِمَا|كَانُواْ|يَفۡعَلُونَ","t": "inna|alladhina|farraqu|dinahum|wakanu|shiya'an|lasta|min'hum|fi|shayin|innama|amruhum|ila|al-lahi|thumma|yunabbi-uhum|bima|kanu|yaf 'aluna","e": "۟/١٥٩/."},"160": {"p": 150,"j": 8,"h": 60,"m": 2,"r": 121,"i": "مَنْ|جَآءَ|بِالْحَسَنَةِ|فَلَهٗ|عَشْرُ|اَمْثَالِهَا ۚ—|وَمَنْ|جَآءَ|بِالسَّیِّئَةِ|فَلَا|یُجْزٰۤی|اِلَّا|مِثْلَهَا|وَهُمْ|لَا|یُظْلَمُوْنَ","u": "مَن|جَآءَ|بِٱلۡحَسَنَةِ|فَلَهُۥ|عَشۡرُ|أَمۡثَالِهَاۖ|وَمَن|جَآءَ|بِٱلسَّيِّئَةِ|فَلَا|يُجۡزَىٰٓ|إِلَّا|مِثۡلَهَا|وَهُمۡ|لَا|يُظۡلَمُونَ","t": "man|jaa|bil-hasanati|falahu|ashru|amthaliha|waman|jaa|bil-sayi-ati|fala|yuj'za|illa|mith'laha|wahum|la|yuz'lamuna","e": "۟/١٦٠/."},"161": {"p": 150,"j": 8,"h": 60,"m": 2,"r": 121,"i": "قُلْ|اِنَّنِیْ|هَدٰىنِیْ|رَبِّیْۤ|اِلٰی|صِرَاطٍ|مُّسْتَقِیْمٍ ۚ۬—|دِیْنًا|قِیَمًا|مِّلَّةَ|اِبْرٰهِیْمَ|حَنِیْفًا ۚ—|وَمَا|كَانَ|مِنَ|الْمُشْرِكِیْنَ","u": "قُلۡ|إِنَّنِي|هَدَىٰنِي|رَبِّيٓ|إِلَىٰ|صِرَٰطٖ|مُّسۡتَقِيمٖ|دِينٗا|قِيَمٗا|مِّلَّةَ|إِبۡرَٰهِيمَ|حَنِيفٗاۚ|وَمَا|كَانَ|مِنَ|ٱلۡمُشۡرِكِينَ","t": "qul|innani|hadani|rabbi|ila|siratin|mus'taqimin|dinan|qiyaman|millata|ib'rahima|hanifan|wama|kana|mina|al-mush'rikina","e": "۟/١٦١/."},"162": {"p": 150,"j": 8,"h": 60,"m": 2,"r": 121,"i": "قُلْ|اِنَّ|صَلَاتِیْ|وَنُسُكِیْ|وَمَحْیَایَ|وَمَمَاتِیْ|لِلّٰهِ|رَبِّ|الْعٰلَمِیْنَ","u": "قُلۡ|إِنَّ|صَلَاتِي|وَنُسُكِي|وَمَحۡيَايَ|وَمَمَاتِي|لِلَّهِ|رَبِّ|ٱلۡعَٰلَمِينَ","t": "qul|inna|salati|wanusuki|wamahyaya|wamamati|lillahi|rabbi|al-'alamina","e": "۟ۙ/١٦٢/."},"163": {"p": 150,"j": 8,"h": 60,"m": 2,"r": 121,"i": "لَا|شَرِیْكَ|لَهٗ ۚ—|وَبِذٰلِكَ|اُمِرْتُ|وَاَنَا|اَوَّلُ|الْمُسْلِمِیْنَ","u": "لَا|شَرِيكَ|لَهُۥۖ|وَبِذَٰلِكَ|أُمِرۡتُ|وَأَنَا۠|أَوَّلُ|ٱلۡمُسۡلِمِينَ","t": "la|sharika|lahu|wabidhalika|umir'tu|wa-ana|awwalu|al-mus'limina","e": "۟/١٦٣/."},"164": {"p": 150,"j": 8,"h": 60,"m": 2,"r": 121,"i": "قُلْ|اَغَیْرَ|اللّٰهِ|اَبْغِیْ|رَبًّا|وَّهُوَ|رَبُّ|كُلِّ|شَیْءٍ ؕ—|وَلَا|تَكْسِبُ|كُلُّ|نَفْسٍ|اِلَّا|عَلَیْهَا ۚ—|وَلَا|تَزِرُ|وَازِرَةٌ|وِّزْرَ|اُخْرٰی ۚ—|ثُمَّ|اِلٰی|رَبِّكُمْ|مَّرْجِعُكُمْ|فَیُنَبِّئُكُمْ|بِمَا|كُنْتُمْ|فِیْهِ|تَخْتَلِفُوْنَ","u": "قُلۡ|أَغَيۡرَ|ٱللَّهِ|أَبۡغِي|رَبّٗا|وَهُوَ|رَبُّ|كُلِّ|شَيۡءٖۚ|وَلَا|تَكۡسِبُ|كُلُّ|نَفۡسٍ|إِلَّا|عَلَيۡهَاۚ|وَلَا|تَزِرُ|وَازِرَةٞ|وِزۡرَ|أُخۡرَىٰۚ|ثُمَّ|إِلَىٰ|رَبِّكُم|مَّرۡجِعُكُمۡ|فَيُنَبِّئُكُم|بِمَا|كُنتُمۡ|فِيهِ|تَخۡتَلِفُونَ","t": "qul|aghayra|al-lahi|abghi|rabban|wahuwa|rabbu|kulli|shayin|wala|taksibu|kullu|nafsin|illa|alayha|wala|taziru|waziratun|wiz'ra|ukh'ra|thumma|ila|rabbikum|marji'ukum|fayunabbi-ukum|bima|kuntum|fihi|takhtalifuna","e": "۟/١٦٤/."},"165": {"p": 150,"j": 8,"h": 60,"m": 2,"r": 121,"i": "وَهُوَ|الَّذِیْ|جَعَلَكُمْ|خَلٰٓىِٕفَ|الْاَرْضِ|وَرَفَعَ|بَعْضَكُمْ|فَوْقَ|بَعْضٍ|دَرَجٰتٍ|لِّیَبْلُوَكُمْ|فِیْ|مَاۤ|اٰتٰىكُمْ ؕ—|اِنَّ|رَبَّكَ|سَرِیْعُ|الْعِقَابِ ۖؗۗ—|وَاِنَّهٗ|لَغَفُوْرٌ|رَّحِیْمٌ","u": "وَهُوَ|ٱلَّذِي|جَعَلَكُمۡ|خَلَٰٓئِفَ|ٱلۡأَرۡضِ|وَرَفَعَ|بَعۡضَكُمۡ|فَوۡقَ|بَعۡضٖ|دَرَجَٰتٖ|لِّيَبۡلُوَكُمۡ|فِي|مَآ|ءَاتَىٰكُمۡۗ|إِنَّ|رَبَّكَ|سَرِيعُ|ٱلۡعِقَابِ|وَإِنَّهُۥ|لَغَفُورٞ|رَّحِيمُۢ","t": "wahuwa|alladhi|ja'alakum|khalaifa|al-ardi|warafa'a|ba'dakum|fawqa|ba'din|darajatin|liyabluwakum|fi|ma|atakum|inna|rabbaka|sari'u|al-'iqabi|wa-innahu|laghafurun|rahimun","e": "۟۠/١٦٥/."}}