{"1":"Муг1арах нийсденна  латтача малайкех дув буъ  Аз//муг1араш дарца","2":"Д1ай-хьай лехкаш долчарех дув буъ Аз//лахкарца","3":"бешачарех а//хьехам","4":"боккъал//шун Даьла//Ца1 ма-в","5":"Даьла ва Из//сигалений а//лаьттан а//цу шинена юкъе мел долчун а//*//Даьла ва из//малхбоаленеи","6":"Боккъал//хозленца кийчъяй Оаха//сигале//дунен//хозленца//седкъий","7":"Лора а яьй Оаха из//х1ара//*//шайт1ах//духьал долча","8":"цар ладувг1аргдоацаш//*//тоабанга//*//лакхерча//хаьшкаш детт царна//масса//*//оаг1орахьара","9":"уж лелхадеш//царна//1азап а хургда//даим дола","10":"из мел доацар//*//ше катехар//цкъа катохарца//т1аккха цунна т1ехьадоал//хаьшк//къорга йоаккха, е доагаду","11":"Хаттал 1а царга//уж ба//ч1оаг1аг1а//хьакхолларгахь//е//уж ба//Оаха кхеллараш//боккъал а Оаха//хьакхеллаб уж//топпарах//*//т1алетача","12":"Х1аьта//хьо цецвувл//уж кхард","13":"царна хьехам бича//*//хьехаме хилац уж//*","14":"Шоашта б1аргаяйча//*//белгало//кхард уж","15":"Цар оал//ма дац//ер//*//бозбуачал мара//белггала","16":"Тхо дайча//*//тхо хилча//лаьтта а//т1ехкаш а//тхо//дийн а даь г1овттадергда","17":"Ай тха дай а//хьалха д1абаха","18":"1а д1аала//Даьра г1овттадергда//шоаш//сизадаьнна а долаш","19":"ма дац//из//ц1ог1а  тохар мара//цкъа//т1аккха//уж//хьожаргба","20":"Цар аргда//Ва тхо х1алакьхилар!//ер//ди ма дий//бекхаман","21":"Ер//ди да//къоастаман//из да из//шо хинна//ше//харцдеш","22":"Хьагулбе оаш//ужаши//зулам даьраш//цар новкъостийи//из х1амейи//уж хинна//шийна 1ибадат деш","23":"воацаш//*//Аллах1//т1анийсбе оаш уж//наькъ т1а//*//жожаг1ата","24":"совцабе уж//боккъал а уж//хоаттаме хург ма-б","25":"фу даьд//шоана//в1аший г1о х1ана дац оаш//*","26":"бакъда//уж//тахан//карабаха ба","27":"т1аберзаргба//царех цхьабараш//вокхарна//*//в1аший хетташ","28":"цар аргда//боккъал а шо//шо дар//тхона т1аухаш//аьтта оаг1орахьара//*","29":"вокхар аргда//бакъда//шо хиннадац//*//им дилла","30":"ма//бацар кара//тха//шоана т1ехь//цхьаккха а низ//*//бакъда//шо дар//нах//т1ехдувлаш, тувладенна","31":"т1аккха бакъ хиннад//вайна т1а//дош//вай Даьла//Боккъал а вай//1азап 1овшаргдолаш ма-д","32":"т1аккха шо а тувладаьд Оаха//Боккъал а тхо//тхо дар//тувладенна","33":"боккъал а уж//цу дийнахьа//1азапагахь//*//юкъа хург ма-б","34":"Боккъал а Оаха//иштта//ду Оаха//къа дерашца","35":"боккъал а уж//уж хиннаб//аьлча//*//шоашка//вац//цхьаккха даьла//Аллах1 воацар//*//курал еш","36":"цар оалар//ай боккъал  а тхо//бутаргдолаш да//тхоай даьлий//оазархо бахьан долаш//в1ашт1ехьвоаца?","37":"бакъда//из веннав//бакъчунца//бакъ а баьб цо//элчаш","38":"боккъал а шо//1овшаргдолаш ма-д//1азап//лозавеш дола","39":"шоана бекхам а ма бац//*//цу х1амах мара//*//шо хиннача//оашош деш","40":"мел боацараш//лаьш//Аллах1а//ц1енбаь бола","41":"уж//царна хургда//рузкъа//ховш дола, белггала","42":"сомаш хургба//уж//сий даь, лийрх1а а хургба","43":"ялсмала бешамашка//*//ни1матан","44":"маьнгеш т1а//*//юхьдухьал болаш","45":"гобоахаргба//царна//дизача пелаца//маларах, хьастах//*","46":"к1ай долаш//мерза а долаш, чам болаш//моларашта","47":"хургдац//цунгахь//хьаькъал д1адахар а//е//уж хург ма бац//цох//шоаш бохабеш","48":"царна хургба//царна мара локхаш боацараш//шоай б1аргаш//доккхий б1аргаш дола истий","49":"уж болчох тара хургба//фуъах//лорадеш долча","50":"т1аберзаргба//царех цхьабараш//вокхарна//*//в1аший хетташ","51":"аргда//моллаг1а оалачо//царех//боккъал а со//вар//са//новкъост","52":"ше оалаш//ай боккъал а хьо//бакъдечарех ва?//*","53":"ай вай дайча//*//вай хилча//лаьтта а//т1ехкаш а//боккъал а вай//воашта бекхам бергболаш да","54":"цо аргда//дий шо//*//хьожаргдолаш","55":"т1аккха хьожаргва из//цига б1аргагургва цунна из//юккъе воаллаш//*//жожаг1ата","56":"аргда цо//дув ма буъ Аз Аллах1ах//боккъал а//хьо гарга ма вар//1айха со х1алакьве","57":"ни1мат хиннадецаре//*//са Даьла//со хург ма вар//хьабоалабаьчарех//*","58":"деций//вай//лергдолаш?","59":"валар мара//*//хьалхара//ма дац//вай//воашта 1азап лургдолаш","60":"боккъал//ер//ше//толам ма-б//боккха","61":"укх санначоа//*//1амал  йойла//1амал ечар","62":"из да//дикаг1а//хьоашала//е//хи ба//заккъума оал","63":"боккъал а Оаха//из баьб Оаха//питам болаш, зем болаш//зуламхошта","64":"боккъал а из//хи ба//ше арабоалаш//бухера//*//жожаг1ата","65":"цун сомаш//долчох тара да//кортош//шайт1ай","66":"боккъал а уж//дуаргдолаш ма-б//цох//т1аккха хьалъюзаргйолаш а ма-б//цох//шоай гигаш","67":"цул т1ехьаг1а//боккъал//царна хург ма-д//цу т1а, цул совг1а//малар//д1айхача хих//*","68":"цул т1ехьаг1а//боккъал//цар берзар//жожаг1ате а ма-д//*","69":"боккъал а уж//царна корабаьбар//шоай дай//тувлабенна болаш","70":"т1аккха уж//цар ларах//*//сихбенна болхаш бар","71":"дув ма буъ Аз//тувлабеннабар//царел хьалха//дукхаг1бараш//хьалха д1абахарех","72":"дув ма буъ Аз//Оаха ма бахийтабар//царна юкъе//кхерам лураш","73":"т1аккха хьажал  хьо//мишта//хилар//т1ехьале, чаккхе//шоашта кхерам беннарий","74":"мел боацараш//лай//Аллах1а//ц1енбаь бола","75":"дув ма буъ Аз//Тхога кхайкавар//Нухь//ма дика а да-кх//Тхо жоп луш дараш","76":"к1алхарваьккхар Оаха из а//цун дезал а//саготанах//*//йоккхача","77":"Оаха вир из а//цун дезал а//шоаш//юхебусаргбараш","78":"Оаха дитар//цунна дика ц1и яккхар//т1ехьа т1абоаг1ачаргахь//*","79":"Салам-моаршал//хилда//Нухьа//1аламашкахь//*","80":"боккъал Оаха//иштта//бекхам бу//дика дерашта","81":"боккъал из//Тха лаьех ва//*//им диллача","82":"цул т1ехьаг1а//хила бахийтар Оаха//вожаш","83":"боккъал а//цун тоабах ма-в//*//Ибрах1им а","84":"из венача хана//*//ший Даьлага//дегаца//ц1енача, маьрша","85":"цо аьннача хана//*//ший даьгеи//ший къамагеи//малаг1ча х1аман//1ибадат ду оаш","86":"дагабеха оапаш//даьлий//Аллах1а воацаш//*//беза шоана","87":"х1аьта фу//хет шоана//Даьлах//1аламий","88":"цига хьалхьежар из//цкъа хьажарца//седкъашка//*","89":"цо аьлар//боккъал а со//цамогаш ва","90":"д1абийрза д1абахар уж//цунах//букъ берзабаь","91":"цига т1авахар из//цар даьлий болча//*//цо аьлар//ай//(х1ама) дааций оаш","92":"фу даьд//шоана//йист х1ана хилац шо//*","93":"т1аккха т1авийрзар из//царна//дохадеш,  тохаш//аьттигаца","94":"т1аккха т1абийрза баьхкар уж//из волча//сихбенна","95":"цо аьлар//1ибадат ду оаш//оашаш хьадаьрашта//*","96":"Аллах1 ма вий//шо хьакхеллар//оаш хьадеш дар а//*","97":"Цар аьлар//хьалъе оаш//цунна//цхьа г1ишло//т1аккха кхосса оаш из//ц1ерал//*","98":"лейнадар царна//цунна//маькарло е//т1аккха оаха царех бир//лохаг1бараш","99":"цо аьлар//боккъал со//водаш ва//сай Даьлага//*//Цо нийсвергва со","100":"Са даьла//ва 1а//сона//ц1енабарех//*","101":"кхаъ баьккхар Оаха цунга//к1аьнкаца//к1аьда волча","102":"т1аккха//из кхаьчача//цунца//д1а-хьа леларга//цо аьлар//ва са во1илг!//боккъал а сона//гу//г1анахь//*//се хилар//хьона урс хьокхаш//х1аьта хьажал хьо//фу//хет хьона//цо аьлар//х1ай са да!//хьаде 1а//из х1ама//хьайга амар дер//со короргва хьона//лайнадале//*//Аллах1а//сабаре болчарех//*","103":"т1аккха//уж шиъ мут1ахьа хиннача хана//цо из 1о а виллача//оаг1ора","104":"цунга кхайкар Тхо//://ва Ибрах1им! (аьнна)","105":"бакъдир 1а//*//г1а//боккъал а Оаха//иштта//бекхам бу Оаха//дика дерашта","106":"боккъал//ер//ше//бала ма-б, зер ма-д//белггала","107":"хьелам белар Оаха цох//урс хьекха х1ама даларца//доккха, деза","108":"Дика ц1и яккхар дитад Оаха//цунна//т1ехьа т1абоаг1ачаргахь//*","109":"Салам-моаршал//хилда//Ибрах1има","110":"иштта//бекхам бу Оаха//дика дерашта","111":"боккъал а из//Тха лаьех ма-в//*//им диллача","112":"цунга кхаъ баьккхар Оаха//Исхьакъаца//пайхамар волаш//ц1енабарех волаш//*","113":"Беркат даьдар Оаха//цунна а//Исхьакъа а//*//цу шинне т1ехьенах ва//*//дика дер а//зулам дер а//ший дег1а//белггала","114":"дув ма буъ Аз//Оаха дика даьдар//Мусайна а//*//Х1аруна а","115":"к1алхарбаьхабар Оаха уж шиъ а//цар къам а//сагатонах, балах//*//боккхача","116":"царна г1о дир Оаха//т1аккха уж хилар//шоаш//котбаьннараш","117":"цу шиннена деннад Оаха//китаб//дикка белгалдеш дола","118":"уж шиъ нийсвир Оаха//наькъ т1а//нийсача","119":"дика ц1и яьккхар дитад Оаха//царна т1ехь//1аламашкахь//*","120":"Салам-моаршал//хилда//Мусайна а//Х1аруна а","121":"боккъал Оаха//иштта//бекхам бу Оаха//дика дерашта","122":"боккъал уж шиъ//Тха лаьех ма-б//*//им диллача","123":"боккъал//Илъяс//ма-в//элчаех","124":"цо аьннача хана//*//ший къамага//ай кхераций шо//*","125":"ай кхайка шо, 1ибадат ду оаш//Ба1ла//вут оаш//Т1ехдикаг1вар//кхолларех","126":"Аллах1//Шоай даьла вола//шун дай а Даьла вола//*//хьалха д1абахача","127":"т1аккха  харцвир цар из//боккъал а уж//хьабоалаберг ма-б","128":"мел боацараш//лаьш//Аллах1а//ц1енбаь","129":"Дика ц1и яккхар дитад Оаха//цунна т1ехь//1аламашкахь//*","130":"Салам-моаршал//хилда//Илъясашта","131":"боккъал Оаха//иштта//бекхам бу Оаха//дика дерашта","132":"боккъал из//Тха лаьех ма-в//*//им диллача","133":"боккъал//Лут1//элчаех ма-в//*","134":"Оаха к1алхарваьккхача хана из а//*//цун дезал а//берригаш а","135":"йоккха саг мел йоацар//*//бисарашта юкъе хинна йола//*","136":"цул  т1ехьаг1а//х1алакбир Оаха//вожаш","137":"боккъал а шо//т1ехдувлаш ма лел//царна юхе г1олла//1уйрана","138":"бийсанна а//х1аьта//хьаькъале даг1аций шо","139":"боккъал//Юнус а//элчаех ма-в//*","140":"из веддача хана//*//кема т1а ха//*//диззача","141":"Т1аккха кхаж тессар цо//т1аккха из хилар//(кхаж тассаргахь) ийшабаьрех//кхаьчар кхаж","142":"цига  д1акхаьллар из//боккхача ч1аькъаро//ше//шийх бехк баьккха волаш","143":"из хиннавецаре//*//*//тасбихь яьчарех//*","144":"воалларг ма вар из//цун керахь//*//денга кхаччалца//*//уж г1овттабеча","145":"т1аккха аракхессар Оаха из//яьсса аре йолча//ше//цамогаш волаш","146":"хьат1адалийтар Оаха//цунна//хетолг//ябакха//*","147":"Вахийтар Оаха из//б1аь//*//эзарга//е//дукхаг1болчарга","148":"Цига цар им диллар//пайда эцийтар Оаха царга//цхьан ханага кхаччалца//*","149":"Фу оал хьажал хьо цар//Ай хьа Даьла//мехкарий болаш//царна//къонгаш ба","150":"Е//Оаха кхеллад//малайкаш//кхал долаш//уж//тешаш болаш","151":"Ай//цар//шоашкара хоарцо т1акхоллаш//*//ма йоах","152":"дезал баьб//Аллах1а//Даьра уж//харцлувш маб","153":"Хержаб Цо//мехкарий//къонгашта т1ехь//*","154":"Фу даьд//шоана//мишта//ду оаш хьукам","155":"Ай//хьехаме даг1аций шо","156":"Е//шоага//далил да//белггала","157":"Хьадувла//шоай китабаца//нагахь//шо//бакълувш дале","158":"Еллай цар//Цуннеи//джинашта юкъеи//*//гаргало//дув ма буъ Аз//ха ма хайнад//джинашта//шоаш//гаргдоаладергдолга","159":"Ц1ена ва//Аллах1//цу х1амах//цар куца дечох","160":"мел боацараш//лаьш//Аллах1а//шоаш ц1енбаь бола","161":"Боккъал шо а//из х1ама а//оаш шийна 1ибадат дер","162":"ма дац//шо//Цунна духьал//цхьаккхе а кегавергволаш","163":"из мел воацар//*//ше//г1оргвар//жожаг1ата","164":"ма дац//Тхох//шийна йолаш мара//*//меттиг//йовзаш","165":"боккъал а тхо//тхо//муг1арах латтараш ма-д","166":"боккъал а тхо//тхоаш//тасбийхь ераш ма-д","167":"нагахь//уж хиннабале а//шоаш яхаш","168":"баларе//*//тхога//хьехам//хьалха д1абахарех//*","169":"хург ма дар тхо//лаьш//Аллах1а//ц1ендаь","170":"Т1аккха керастал дир цар//цунца//Ховргда цана//*","171":"дув ма буъ Аз//хьалхадааьннад//тха дош//тха лаьшта//элчаш болча","172":"боккъал а уж//шоаш//котбоахаргбараш ма-б","173":"боккьал//тха эскар//шоаш маб//котбаргбараш а","174":"д1аверз хьо//царех//ха яллалца//*","175":"Б1арахьажа хьо царна//гург-м да царна//*","176":"Тха 1азап//да цар сихдер","177":"т1аккха//из дессача//уж болча метте//ма во хургья -кх//1уйре//шоашта кхерам бенначар","178":"Д1аверза хьо//царех//цхьа ха яллалца//*","179":"Б1арахьажа хьо//гург-м да царна//*","180":"Ц1енна ва//хьа Даьла//Даьла//сийлен//цар деча куцах//*","181":"салам-моаршал//хилда//элчашта","182":"хоастам ба//Аллах1а//Даьла волча//1аламий"}